Workbook

Sheet รายชื่อพนักงานลาออกพ้นสภาพ
A1: ลำดับ | B1: รหัสพนักงาน | C1: ชื่อ - สกุล | D1: ตำแหน่ง | E1: แผนก | F1: E-Mail | G1: ทำงานวันสุดท้าย ( วัน-เดือน-ปี ) | H1: วันที่พ้นสภาพ ( วัน-เดือน-ปี ) | I1: สถานะการลาออก/พ้นสภาพ | J1: สถานะการตรวจสอบเอกสาร | K1: สถานะการปิดลาออกจาก HR Online | L1: ปัจจัยการลาออก (For Report) | M1: เหตุผลการลาออก | N1: ลบข้อมูล Email | O1: ลบข้อมูลระบบ REM | P1: ลบข้อมูลระบบ CMS
A2: 838 | B2: BK650037 | C2: นายกษมา ชาญวิบูลย์ | D2: 8659 พนักงานขับรถส่วนกลาง | E2: แผนกยานพาหนะ | F2: kasamac@sena.co.th | I2: ยกเลิกลาออก | J2: ส่งเอกสารถึงพนักงาน | L2: ปัจจัยที่ 2 ความสัมพันธ์และบุคคลากรในองค์กร
A3: 898 | B3: ???? | C3: ???? | I3: ลาออก | J3: ส่งเอกสารถึงพนักงาน
A4: 1046 | B4: BK680355 | C4: นายวิทยา จงบรรจบ | D4: 7501 โฟร์แมนควบคุมงาน | E4: นิช โมโน เมกะ สเปซ บางนา | F4: witthayaj@sena.co.th | G4: 46081 | H4: 46082 | I4: ลาออก | J4: ส่งเอกสารถึงพนักงาน | K4: ปิดลาออกแล้ว | L4: ปัจจัยที่ 2 ความสัมพันธ์และบุคคลากรในองค์กร
A5: 1079 | B5: BK680275 | C5: นายปวเรศ ปัญจศิลป์ | D5: 7406 เจ้าหน้าที่สนับสนุนการตลาด | E5: แผนกการตลาดบ้าน 1C | F5: pavaretp@sena.co.th | G5: 46022 | H5: 46023 | I5: ลาออก | J5: ได้รับเอกสารแล้ว | K5: ปิดลาออกแล้ว | L5: ปัจจัยที่ 3 งานในหน้าที่
A6: 1082 | B6: SSG | I6: ยกเลิกลาออก
A7: 1092 | B7: VMS680102 | C7: นางสาวชิรัชยา สุรรัตน์ | D7: 5859 ผู้จัดการอาคาร | E7: แผนกอาคารชุด เสนาคิทท์ พหลโยธิน - นวนคร เฟส 1 | F7: chiratchayas@senxgroup.com | G7: 46022 | H7: 46023 | I7: ยกเลิกลาออก | J7: ส่งเอกสารถึงพนักงาน
A8: 1101 | B8: BK680400 | C8: นายดนัยเดช สวายประโคน | D8: 5555 วิศวกรไฟฟ้า | E8: เสนาคิทท์ สำโรง อินเตอร์เชนจ์ | F8: danaydechs@sena.co.th | G8: 46022 | H8: 46023 | I8: ลาออก | J8: ได้รับเอกสารแล้ว | K8: ปิดลาออกแล้ว | L8: ปัจจัยที่ 5 โอกาสในการเติบโต/พัฒนา
A9: 1130 | B9: VMS680318 | C9: นางสาวกนกวรรณ แห้วดี | D9: 6759 เจ้าหน้าที่บัญชีปิดงบอาวุโส | E9: ฝ่ายบัญชีและการเงิน | F9: kanokwanh@senxgroup.com | G9: 46022 | H9: 46023 | I9: ลาออก | J9: ได้รับเอกสารแล้ว | K9: ปิดลาออกแล้ว | L9: ปัจจัยที่ 3 งานในหน้าที่ | M9: รายละเอียดค่อนข้างเยอะ มีความซับซ้อนต้องใช้เวลา และมีกำหนดส่งงานที่ค่อนข้างกระชันชิดในแต่ละเดือน
A10: 1131 | B10: BK680590 | C10: น.ส.นันทิภา รัตนมาตย์ | D10: 7504 เจ้าหน้าที่ธุรการโครงการ | E10: โคซี่ รามอินทรา - คู้บอน | F10: nuntipar@sena.co.th | G10: 46022 | H10: 46023 | I10: ลาออก | J10: ได้รับเอกสารแล้ว | K10: ปิดลาออกแล้ว | L10: ปัจจัยที่ 6 ความจำเป็นส่วนตัว
A11: 1142 | B11: BK680637 | C11: นายพิฆเนศ ถาวรพงศ์สถิต | D11: 6401 เจ้าหน้าที่ขายและสินเชื่ออาวุโส | E11: เสนา วิลเลจ รามอินทรา กม.9 | F11: pikanatet@sena.co.th | G11: 46022 | H11: 46023 | I11: ลาออก | J11: ได้รับเอกสารแล้ว | K11: ปิดลาออกแล้ว | L11: ปัจจัยที่ 7 Probation (ไม่ผ่านทดลองงาน)
A12: 1143 | B12: VMS670135 | C12: นายวิณัฐ โภคา | D12: 8857 ช่างเทคนิค | E12: แผนกอาคารชุด เดอะ ทรี อินเตอร์เชนจ์ | F12: winutp@senxgroup.com | G12: 46022 | H12: 46023 | I12: ลาออก | J12: ได้รับเอกสารแล้ว | K12: ปิดลาออกแล้ว | L12: ปัจจัยที่ 9 เหตุผลอื่น ๆ | M12: หมดสัญญาบริหารโครงการ
A13: 1144 | B13: BK600104 | C13: น.ส.อนันตญา มินตา | D13: 4563 วิศวกรประมาณราคาอาวุโส | E13: แผนกสถาปัตย์คอนโด 1,2 | F13: anantayam@sena.co.th | G13: 46022 | H13: 46023 | I13: ลาออก | J13: ได้รับเอกสารแล้ว | K13: ปิดลาออกแล้ว | L13: ปัจจัยที่ 6 ความจำเป็นส่วนตัว | M13: ประกอบธุรกิจส่วนตัวกับครอบครัวที่ชลบุรี เป็นผู้รับเหมา
A14: 1145 | B14: BK680561 | C14: น.ส.สุพัฒตรา พุ่มจิ๋ว | D14: 7504 เจ้าหน้าที่ธุรการโครงการ | E14: เสนาคิทท์ บางนา - ก.ม.29 เฟส 1,2 | F14: Suphattrap@sena.co.th | G14: 46022 | H14: 46023 | I14: ลาออก | J14: ได้รับเอกสารแล้ว | K14: ปิดลาออกแล้ว | L14: ปัจจัยที่ 4 องค์กร
A15: 1148 | B15: BK680564 | C15: น.ส.เขมจิรา บุญคำ | D15: 8501 พนักงานธุรการโครงการ | E15: เสนา พาร์ค แกรนด์ รามอินทรา เฟส 2 | F15: Khemjirab@sena.co.th | G15: 46142 | H15: 46143 | I15: ลาออก | J15: ได้รับเอกสารแล้ว | K15: ปิดลาออกแล้ว | L15: ปัจจัยที่ 6 ความจำเป็นส่วนตัว
A16: 1151 | B16: VMS680181 | C16: นางสาวณัฐวรรณ ศิริปรุ | D16: 7853 เจ้าหน้าที่บัญชีนิติบุคคล | E16: แผนกบัญชีแนวราบ | F16: nattawans@senxgroup.com | G16: 46022 | H16: 46023 | I16: ลาออก | J16: ได้รับเอกสารแล้ว | K16: ปิดลาออกแล้ว | L16: ปัจจัยที่ 1 ผลตอบแทนการทำงาน | M16: 1.ต้องทำงานของคนเก่าที่ลาออกไม่ได้ต่องานกันซึ่งทำงานให้งานมีที่มีอยู่ปัจจุบันปิดงบไม่ทัน 2. ได้งานใหม่เงินเดือนเพิ่มจากเดิม 5,000 บาท
A17: 1153 | B17: VMS680078 | C17: นางสาวณัฐชนท เรืองทรัพย์บำรุง | D17: 5754 ผู้ช่วยหัวหน้าแผนกบัญชีลูกหนี้ | E17: แผนกการเงินรับ | F17: natchanontr@senxgroup.com | G17: 46022 | H17: 46023 | I17: ลาออก | J17: ได้รับเอกสารแล้ว | K17: ปิดลาออกแล้ว | L17: ปัจจัยที่ 6 ความจำเป็นส่วนตัว | M17: เนื่องจากต้องกลับย้ายกลับไปอยู่บ้านต่างจังหวัดกำแพงเพชร ทำธุรกิจส่วนตัวทำขนมขาย
A18: 1154 | B18: VMS670136 | C18: นายเทิดศักดิ์ ขันโอฬาร | D18: 8857 ช่างเทคนิค | E18: แผนกอาคารชุด เดอะ ทรี อินเตอร์เชนจ์ | F18: terdsakk@senxgroup.com | G18: 46022 | H18: 46023 | I18: ลาออก | J18: ได้รับเอกสารแล้ว | K18: ปิดลาออกแล้ว | L18: ปัจจัยที่ 9 เหตุผลอื่น ๆ | M18: หมดสัญญาบริหารโครงการ
A19: 1159 | B19: VMS680145 | C19: นายอานนท์ เส้งคล้าย | D19: 7855 หัวหน้าช่างประจำอาคาร | E19: แผนกอาคารชุด ไอ-เฮาส์ ลากูน่า การ์เด้น | F19: arnons@senxgroup.com | G19: 46022 | H19: 46023 | I19: ลาออก | J19: ได้รับเอกสารแล้ว | K19: ปิดลาออกแล้ว | L19: ปัจจัยที่ 1 ผลตอบแทนการทำงาน | M19: ได้งานใหม่ บริษัท ลีฟ อัลติเมท แวลูส์ จำกัด เงินเดือนเพิ่มขึ้น 7,000 บาท ดูโครงการห้องจำนวน 1,400 ห้อง
A20: 1160 | B20: BK680219 | C20: น.ส.ฤชาลักษณ์ จิตอารี | D20: 33 ผู้จัดการ | E20: ฝ่ายบริหารการขายคอนโด 4A | F20: luachaluckj@sena.co.th | G20: 46022 | H20: 46023 | I20: ลาออกไม่ครบ 30 วัน | J20: ได้รับเอกสารแล้ว | K20: ปิดลาออกแล้ว
A21: 1162 | B21: VMS680109 | C21: นายเศรษฐวุฒิ สอนง่าย | D21: 8855 ช่างประจำอาคาร | E21: แผนกอาคารชุด เสนาคิทท์ รังสิต - ติวานนท์ | F21: sethtawuts@senxgroup.com | G21: 46022 | H21: 46023 | I21: ลาออกไม่ครบ 30 วัน | J21: ได้รับเอกสารแล้ว | K21: ปิดลาออกแล้ว | L21: ปัจจัยที่ 1 ผลตอบแทนการทำงาน | M21: ได้งานใหม่เงินเดือนเพิ่ม จากเดิม 2,000 บาทและเลื่อนตำแหน่งจาก Officer เป็น Senior ทำงานกับบริษัท โนเบิ้ล
A22: 1165 | B22: VMS680329 | C22: นางสาวดวงธิดา วัฒนกุล | D22: 7854 เจ้าหน้าที่นิติบุคคล | E22: แผนกอาคารชุด โชคชัยร่วมมิตร คอนโด | F22: duangtidaw@senxgroup.com | G22: 46022 | H22: 46023 | I22: ลาออกไม่ครบ 30 วัน | J22: ได้รับเอกสารแล้ว | K22: ปิดลาออกแล้ว | L22: ปัจจัยที่ 6 ความจำเป็นส่วนตัว | M22: ทำธุรกิจกับครอบครัวเปิดร้านกาแฟ
A23: 1166 | B23: VMS680184 | C23: นายพะเยาว์ พุทธสีมา | D23: 8855 ช่างประจำอาคาร | E23: แผนกอาคารชุด นิช โมโน รามคำแหง | F23: payaop@senxgroup.com | G23: 46022 | H23: 46023 | I23: ลาออก | J23: ได้รับเอกสารแล้ว | K23: ปิดลาออกแล้ว | L23: ปัจจัยที่ 6 ความจำเป็นส่วนตัว | M23: ไปทำธุรกิจประเภทรับเหมาก่อสร้าง
A24: 1168 | B24: VMS680237 | C24: นายอุทิศ สุจำนงค์ | D24: 8855 ช่างประจำอาคาร | E24: แผนกอาคารชุด แมเนอร์ สนามบินน้ำ | F24: autids@senxgroup.com | G24: 46022 | H24: 46023 | I24: ลาออก | K24: ปิดลาออกแล้ว
A25: 1172 | B25: VMS670037 | C25: นายจักรกฤษ์ ธรรมวงศ์ | D25: 8855 ช่างประจำอาคาร | E25: แผนกอาคารชุด เวรี่ ลาซาล สุขุมวิท 105 | F25: jukkritt@senxgroup.com | G25: 46022 | H25: 46023 | I25: ลาออกไม่ครบ 30 วัน | J25: ได้รับเอกสารแล้ว | K25: ปิดลาออกแล้ว | L25: ปัจจัยที่ 1 ผลตอบแทนการทำงาน | M25: เหตุผลเนื่องจากผ่านมาไม่มีการปรับเงินเดือน ทำให้ตัดสินใจลาออก
A26: 1173 | B26: VMS680183 | C26: นายพีรพัฒน์ อภัยพิพัฒน์ | D26: 8855 ช่างประจำอาคาร | E26: แผนกอาคารชุด แอทโมซ รัชดา - ห้วยขวาง | F26: peerapata@senxgroup.com | G26: 46030 | H26: 46031 | I26: ยกเลิกลาออก | M26: เหตุุผลที่ลาออกเนื่องจาก ติดเรียนวันเสาร์- อาทิตย์
A27: 1178 | B27: BK670055 | C27: น.ส.รัชนีกร แพงทรัพย์ | D27: 7759 เจ้าหน้าที่บัญชีปิดงบ | E27: แผนกบัญชีต้นทุน | F27: ratchaneekornp@sena.co.th | G27: 46053 | H27: 46054 | I27: ลาออก | J27: ได้รับเอกสารแล้ว | K27: ปิดลาออกแล้ว | L27: ปัจจัยที่ 5 โอกาสในการเติบโต/พัฒนา
A28: 1179 | B28: VMS680130 | C28: นายรัตนชัย พลช่วย | D28: 8855 ช่างประจำอาคาร | E28: แผนกอาคารชุด เสนาคิทท์ เทพารักษ์ - บางบ่อ 2 | F28: rattanachaip@senxgroup.com | G28: 46037 | H28: 46038 | I28: ลาออก | J28: ได้รับเอกสารแล้ว | K28: ปิดลาออกแล้ว | L28: ปัจจัยที่ 6 ความจำเป็นส่วนตัว | M28: กลับบ้านต่างจังหวัดไปดูแลพ่อที่ป่วยเนื่องจากพิษราเดินไม่ได้ตอนนี้รักษาตัวอยู่ที่โรงพยาบาล
A29: 1180 | B29: VMS680113 | C29: นางสาวกุสุมา เล้าสูงเนิน | D29: 7853 เจ้าหน้าที่บัญชีนิติบุคคล | E29: แผนกการเงินจ่าย | F29: kusumal@senxgroup.com | G29: 46037 | H29: 46038 | I29: ลาออก | J29: ได้รับเอกสารแล้ว | K29: ปิดลาออกแล้ว | L29: ปัจจัยที่ 3 งานในหน้าที่ | M29: เหตุผลเนื่องจากขั้นตอนการทำงานที่ซับซ้อน ปรับเปลี่ยนตลอดทำให้งานที่ทำวนไปวนมา เหมือนการทำงานไม่มี Flow การทำงาน และ ได้งานใหม่ซึ่งที่ใหม่ให้เดือนเพิ่ม 5,000 บาท + เงินค่าไม่สาย ไม่ลา ไม่ขาดงาน อีก 1,000 บาท
A30: 1181 | B30: VMS670162 | C30: นางสาววิภารัตน์ ตระกูลสัมพันธ์ | D30: 7504 เจ้าหน้าที่ธุรการโครงการ | E30: แผนกอาคารชุด เดอะ เชดด์ สาทร 1 | F30: wiparattr@senxgroup.com | G30: 46045 | H30: 46046 | I30: ลาออก | J30: ได้รับเอกสารแล้ว | K30: ปิดลาออกแล้ว | L30: ปัจจัยที่ 6 ความจำเป็นส่วนตัว | M30: เนื่องจากต้องย้ายไปอยู่ต่างจังหวัดกับพี่สาวที่ชลบุรี และ ต้องการทำงานในรูปแบบ Office ทำงาน 5 วัน ได้หยุดเสาร์ - อาทิตย์
A31: 1183 | B31: BK680663 | C31: น.ส.กิรณา ครองศิริ | D31: 7401 เจ้าหน้าที่ขายและสินเชื่อ | E31: นิช โมโน บางโพ | F31: kiranak@sena.co.th | G31: 46040 | H31: 46041 | I31: ลาออกไม่ครบ 30 วัน | J31: ได้รับเอกสารแล้ว | K31: ปิดลาออกแล้ว | L31: ปัจจัยที่ 2 ความสัมพันธ์และบุคคลากรในองค์กร
A32: 1185 | B32: VMS620164 | C32: นางสาวปนัดดา อยู่แขก | D32: 5859 ผู้จัดการอาคาร | E32: แผนกอาคารชุด เวนโต้ คอนโด เกษตร นวมินทร์ | F32: panadday@senxgroup.com | G32: 46023 | H32: 46024 | I32: ยกเลิกลาออก
A33: 1186 | B33: VMS680278 | C33: นายสิรวิชญ์ หวังสมนึก | D33: 8855 ช่างประจำอาคาร | E33: แผนกอาคารชุด เวรี่ ลาซาล สุขุมวิท 105 | F33: sirawitw@senxgroup.com | G33: 46037 | H33: 46038 | I33: ลาออก | J33: ได้รับเอกสารแล้ว | K33: ปิดลาออกแล้ว | L33: ปัจจัยที่ 7 Probation (ไม่ผ่านทดลองงาน) | M33: ไม่ผ่านทดลองงาน
A34: 1187 | B34: VMS680301 | C34: นายศุภชัย มานะผล | D34: 8855 ช่างประจำอาคาร | E34: แผนกอาคารชุด เวรี่ ลาซาล สุขุมวิท 105 | F34: supachaim@senxgroup.com | G34: 46053 | H34: 46054 | I34: ลาออก | J34: ได้รับเอกสารแล้ว | K34: ปิดลาออกแล้ว | L34: ปัจจัยที่ 7 Probation (ไม่ผ่านทดลองงาน) | M34: ไม่ผ่านทดลองงาน
A35: 1188 | B35: VMS670300 | C35: นางสาวศิริพรรณ จิตรชัยภูมิ | D35: 7854 เจ้าหน้าที่นิติบุคคล | E35: แผนกอาคารชุด นิช โมโน พระราม 9 | F35: siripunj@senxgroup.com | G35: 46030 | H35: 46031 | I35: ลาออกไม่ครบ 30 วัน | J35: ได้รับเอกสารแล้ว | K35: ปิดลาออกแล้ว | L35: ปัจจัยที่ 1 ผลตอบแทนการทำงาน | M35: ได้งานที่ใหม่เดินทางใกล้บ้าน เงินเดือนเพิ่มจากเดิม 1,500 บาท ทำงานไม่มีปัญหา
A36: 1189 | B36: VMS680177 | C36: นายพิพัฒพงษ์ ชัยสุวรรณ | D36: 8855 ช่างประจำอาคาร | E36: แผนกอาคารชุด แอทโมซ รัชดา - ห้วยขวาง | F36: pipatpongc@senxgroup.com | G36: 46027 | H36: 46028 | I36: ลาออกไม่ครบ 30 วัน | K36: ปิดลาออกแล้ว | L36: ปัจจัยที่ 1 ผลตอบแทนการทำงาน | M36: ได้งานใหม่ทำในตำแหน่งธุรการจัดซื้อ เป็นโรงงานจะมี OT ซึ่งได้เงินเดือนเพิ่มจากเดิม 2,500 บาท
A37: 1190 | B37: SX680017 | C37: นางสาวปุณยนุช สืบนุกูล | D37: 7754 เจ้าหน้าที่บัญชีลูกหนี้ | E37: แผนกบัญชีลูกหนี้ | F37: poonyanuchs@senxgroup.com | G37: 46022 | H37: 46023 | I37: ลาออกไม่ครบ 30 วัน | K37: ปิดลาออกแล้ว | L37: ปัจจัยที่ 7 Probation (ไม่ผ่านทดลองงาน) | M37: ไม่ผ่านทดลองงาน
A38: 1191 | B38: BK680553 | C38: น.ส.ดวงจันทร์ วงทองนิล | D38: 7504 เจ้าหน้าที่ธุรการโครงการ | E38: เสนา วิลล์ ลำลูกกา - คลอง 6 | F38: duangjanw@sena.co.th | G38: 46053 | H38: 46054 | I38: ลาออก | J38: ได้รับเอกสารแล้ว | K38: ปิดลาออกแล้ว | L38: ปัจจัยที่ 6 ความจำเป็นส่วนตัว
A39: 1192 | B39: BK680394 | C39: นายสุรกานต์ หาญตระกูล | D39: 5501 วิศวกรสนาม | E39: เสนาคิทท์ สำโรง อินเตอร์เชนจ์ | F39: surakanh@sena.co.th | G39: 46053 | H39: 46054 | I39: ลาออก | J39: ได้รับเอกสารแล้ว | K39: ปิดลาออกแล้ว | L39: ปัจจัยที่ 1 ผลตอบแทนการทำงาน
A40: 1193 | B40: BK680654 | C40: นายพิชชากร ชอุ่มผล | D40: 6401 เจ้าหน้าที่ขายและสินเชื่ออาวุโส | E40: เสนา วิลเลจ บางนา - กม.29 | F40: pichchakornc@sena.co.th | G40: 46022 | H40: 46023 | I40: ลาออกไม่ครบ 30 วัน | J40: ต้นสังกัดแจ้งทางเมล์ | K40: ปิดลาออกแล้ว
A41: 1194 | B41: SMF670005 | C41: นางสาววันวิสาข์ พลอยประเสริฐ | D41: 7974 เจ้าหน้าที่ประสานงาน | E41: แผนกค้าปลีกและพัฒนาผลิตภัณฑ์ (Smartify) | F41: wanwisap@senxgroup.com | G41: 46053 | H41: 46054 | I41: ลาออก | J41: ได้รับเอกสารแล้ว | K41: ปิดลาออกแล้ว | L41: ปัจจัยที่ 1 ผลตอบแทนการทำงาน | M41: ได้งานใหม่เป็น หน่วยงานรัฐวิสาหกิจ มีสวัสดิการเบิกค่ารักษาได้
A42: 1195 | B42: VMS680272 | C42: นางสาวขณิตา โพติยะ | D42: 5859 ผู้จัดการอาคาร | E42: แผนกอาคารชุด เสนาคิทท์ เทพารักษ์ - บางบ่อ 1 | F42: khanitap@senxgroup.com | G42: 46053 | H42: 46054 | I42: ยกเลิกลาออก
A43: 1196 | B43: VMS650116 | C43: นางสาวมณีรัตน์ ภูจักนิล | D43: 5859 ผู้จัดการอาคาร | E43: แผนกอาคารชุด เฟล็กซี่ รัตนาธิเบศร์ | F43: maneerutp@senxgroup.com | G43: 46037 | H43: 46038 | I43: ลาออกไม่ครบ 30 วัน | J43: ได้รับเอกสารแล้ว | K43: ปิดลาออกแล้ว | L43: ปัจจัยที่ 1 ผลตอบแทนการทำงาน | M43: ได้งานใหม่ ที่บริษัท SC Asset เงินเดือนเพิ่มจากเดิม ประมาณ 4,000 บาท
A44: 1197 | B44: BK680301 | C44: นายนิพนธ์ ราชโยธา | D44: 34 ผู้จัดการโครงการ | E44: ฝ่ายบริหารโครงการคอนโด 11C | F44: niponr@sena.co.th | G44: 46053 | H44: 46054 | I44: ลาออกไม่ครบ 30 วัน | J44: ส่งเอกสารถึงพนักงาน | K44: ปิดลาออกแล้ว | L44: ปัจจัยที่ 6 ความจำเป็นส่วนตัว
A45: 1198 | B45: BK680244 | C45: นายคณิตกุล เทอดรัตนเกียรติ | D45: 7401 เจ้าหน้าที่ขายและสินเชื่อ | E45: เฟล็กซี่ รัตนาธิเบศร์ | F45: kanitkult@sena.co.th | G45: 46053 | H45: 46054 | I45: ลาออกไม่ครบ 30 วัน | J45: ได้รับเอกสารแล้ว | K45: ปิดลาออกแล้ว | L45: ปัจจัยที่ 6 ความจำเป็นส่วนตัว
A46: 1199 | B46: BK680287 | C46: น.ส.กัญญ์สชาญ์ ชัยธนัตถ์โชค | D46: 8401 พนักงานขายและสินเชื่อ | E46: บ้านบูรพา พราวน์ทาวน์ บ่อวิน | F46: kansachac@sena.co.th | G46: 46053 | H46: 46054 | I46: ลาออกไม่ครบ 30 วัน | J46: ส่งเอกสารถึงพนักงาน | K46: ปิดลาออกแล้ว | L46: ปัจจัยที่ 3 งานในหน้าที่
A47: 1200 | B47: VMS680305 | C47: นายธนวัช ศรีปลั่ง | D47: 8855 ช่างประจำอาคาร | E47: แผนกอาคารชุด นิช โมโน สุขุมวิท - ปู่เจ้า | F47: thanawats@senxgroup.com | G47: 46050 | H47: 46051 | I47: ยกเลิกลาออก | L47: ปัจจัยที่ 7 Probation (ไม่ผ่านทดลองงาน) | M47: ไม่ผ่านทดลองงาน
A48: 1201 | B48: VMS680315 | C48: นางสาวฐัชชนันท์ ธาระผล | D48: 7854 เจ้าหน้าที่นิติบุคคล | E48: แผนกมาตรฐานโครงการใหม่ | F48: thatchanant@senxgroup.com | G48: 46022 | H48: 46023 | I48: ปลดออก | J48: ต้นสังกัดแจ้งทางเมล์ | K48: ปิดลาออกแล้ว
A49: 1202 | B49: BK650266 | C49: นายศักดิ์สิทธิ์ รัตนภักดี | D49: 7973 ช่างซ่อมบำรุง | E49: แผนกอาคารสถานที่ | F49: saksitr@sena.co.th | G49: 46066 | H49: 46067 | I49: ลาออก | J49: ได้รับเอกสารแล้ว | K49: ปิดลาออกแล้ว | L49: ปัจจัยที่ 5 โอกาสในการเติบโต/พัฒนา
A50: 1203 | B50: VMS690020 | C50: นางสาวกรรณิการ์ น้อยวิไล | D50: 7854 เจ้าหน้าที่นิติบุคคล | E50: แผนกอาคารชุด นิช โมโน แจ้งวัฒนะ | F50: kannikan@senxgroup.com | G50: 46033 | H50: 46034 | I50: ปลดออก | J50: ต้นสังกัดแจ้งทางเมล์ | K50: ปิดลาออกแล้ว
A51: 1204 | B51: VMS680372 | C51: นายอรรถโรบล เกิดมนตรี | D51: 7855 หัวหน้าช่างประจำอาคาร | E51: แผนกอาคารชุด ไอ-เฮาส์ ลากูน่า การ์เด้น | F51: auttororong@senxgroup.com | G51: 46053 | H51: 46054 | I51: ลาออก | J51: ได้รับเอกสารแล้ว | K51: ปิดลาออกแล้ว | L51: ปัจจัยที่ 7 Probation (ไม่ผ่านทดลองงาน) | M51: ไม่ผ่านทดลองงาน / เนื่องจากบกพร่องต่อหน้าที่ไม่มีการตรวจปั้มน้ำ และ กรรมการที่โครงการขอให้เปลี่ยนตัว
A52: 1205 | B52: VMS690008 | C52: นายวรวุธ งามเนตร | D52: 7855 หัวหน้าช่างประจำอาคาร | E52: แผนกอาคารชุด เดอะนิช ไพรด์ ทองหล่อ - เพชรบุรี | F52: worawutn@senxgroup.com | G52: 46028 | H52: 46029 | I52: ปลดออก | J52: ต้นสังกัดแจ้งทางเมล์ | K52: ปิดลาออกแล้ว
A53: 1206 | B53: BK680200 | C53: น.ส.โชติรัตน์ สว่างวงษ์ | D53: 6402 เจ้าหน้าที่การตลาดอาวุโส | E53: ฝ่ายบริหารการตลาดคอนโด 2B | F53: chotirats@sena.co.th | G53: 46069 | H53: 46070 | I53: ลาออก | J53: ได้รับเอกสารแล้ว | K53: ปิดลาออกแล้ว | L53: ปัจจัยที่ 1 ผลตอบแทนการทำงาน
A54: 1207 | B54: BK670057 | C54: นายอัฐพล บุญค่ำชู | D54: 3601 ผู้ชำนาญการ 1 | E54: ฝ่าย Project Management Strategy | F54: oatthaphonb@sena.co.th | G54: 46076 | H54: 46077 | I54: ลาออก | K54: ปิดลาออกแล้ว | L54: ปัจจัยที่ 1 ผลตอบแทนการทำงาน
A55: 1208 | B55: VMS680118 | C55: นายนาธาน สาเฮาะ | D55: 8855 ช่างประจำอาคาร | E55: แผนกอาคารชุด นิช โมโน รามคำแหง | F55: nathans@senxgroup.com | G55: 46052 | H55: 46053 | I55: ลาออก | J55: ได้รับเอกสารแล้ว | K55: ปิดลาออกแล้ว | L55: ปัจจัยที่ 6 ความจำเป็นส่วนตัว | M55: กลับต่างจังหวัดไปอยู่ใต้ แต่งงาน และ ไปเกณฑ์ทหาร
A56: 1209 | B56: VMS680312 | C56: นางสาวพิชญาภา พรมประเสริฐ | D56: 7754 เจ้าหน้าที่บัญชีลูกหนี้ | E56: 7754 เจ้าหน้าที่บัญชีลูกหนี้ | F56: pichayaphap@senxgroup.com | G56: 46053 | H56: 46054 | I56: ลาออกไม่ครบ 30 วัน | J56: ได้รับเอกสารแล้ว | K56: ปิดลาออกแล้ว | L56: ปัจจัยที่ 1 ผลตอบแทนการทำงาน | M56: ได้งานใหม่เงินเดือนเพิ่มขึ้น และทำใหม่ที่ทำงานใกล้บ้านทำให้ประหยัดค่าเดินทาง
A57: 1210 | B57: SGA680006 | C57: นายมานพ ศรีวิไลเลิศ | D57: 4403 หัวหน้างานขาย | E57: แผนกขาย | F57: manops@senasolarenergy.com | G57: 46053 | H57: 46054 | I57: ลาออกไม่ครบ 30 วัน | J57: ได้รับเอกสารแล้ว | K57: ปิดลาออกแล้ว
A58: 1211 | B58: VMS680357 | C58: นายณคเรศ ดอกมณฑา | D58: 8855 ช่างประจำอาคาร | E58: แผนกอาคารชุด เสนาคิทท์ ศรีนครินทร์ - ศรีด่าน | F58: nakaretd@senxgroup.com | G58: 46068 | H58: 46069 | I58: ลาออก | K58: ปิดลาออกแล้ว | L58: ปัจจัยที่ 1 ผลตอบแทนการทำงาน | M58: ได้งานใหม่ ซึ่งเงินเดือนเพิ่มจากเดิม 2,000 บาท และเหตุผลเพิ่มจำนวนบุคคลากรตำแหน่งธุรการไม่เพียงพอ ทำให้ต้องมาช่วยแยกพัสดุ
A59: 1212 | B59: VMS690014 | C59: นางสาวชัญญนัท ภู่อารีย์ | D59: 7854 เจ้าหน้าที่นิติบุคคล | E59: แผนกอาคารชุด เดอะ เชดด์ สาทร 1 | F59: chanyanatp@senxgroup.com | G59: 46043 | H59: 46044 | I59: ปลดออก | J59: ต้นสังกัดแจ้งทางเมล์ | K59: ปิดลาออกแล้ว | M59: โทรติดต่อไม่ได้
A60: 1213 | B60: VMS650087 | C60: นางสาวสินจัย ชัยศรี | D60: 8854 พนักงานนิติบุคคล | E60: แผนกอาคารชุด เอ สเปซ มี บางนา | F60: sinjaic@senxgroup.com | G60: 46052 | H60: 46053 | I60: ลาออก | J60: ได้รับเอกสารแล้ว | K60: ปิดลาออกแล้ว | L60: ปัจจัยที่ 1 ผลตอบแทนการทำงาน | M60: ได้งานใหม่เงินเดือนเพ่ิม 3,000 บาท และเหตุผลเพิ่มให้มาทำในตำแหน่ง ผจก. บอกจะมีการปรับตำแหน่ง และปรับเงินเดือนให้ แต่ไม่ได้มีการปรับตามที่แจ้ง
A61: 1214 | B61: VMS690006 | C61: นายวิฑูรย์ หิรัญสุข | D61: 7853 เจ้าหน้าที่บัญชีนิติบุคคล | E61: แผนกการเงินจ่าย | F61: withunh@senxgroup.com | G61: 46053 | H61: 46054 | I61: ลาออกไม่ครบ 30 วัน | J61: ได้รับเอกสารแล้ว | K61: ปิดลาออกแล้ว | L61: ปัจจัยที่ 3 งานในหน้าที่ | M61: กระบวนการทำงานเอกสารจากหน้างานไม่ครบถ้วน ส่งเอกสารไป - กลับ ทำให้ไม่ทันรอบของเอกสาร
A62: 1215 | B62: SX670017 | C62: นายตรึก โตบัณฑิตย์ | D62: 6501 โฟร์แมนควบคุมงานอาวุโส | E62: เสนา วิลล์ วงแหวน - บางบัวทอง | F62: trukt@senxgroup.com | G62: 46053 | H62: 46054 | I62: ลาออกไม่ครบ 30 วัน | K62: ปิดลาออกแล้ว | L62: ปัจจัยที่ 6 ความจำเป็นส่วนตัว | M62: เนื่องจากมีปัญญาเรื่องสุขภาพ ด้านดวงตา
A63: 1216 | B63: VMS680085 | C63: นายอาโมทย์ พิมสิม | D63: 8855 ช่างประจำอาคาร | E63: แผนกอาคารชุด ปีติ สุขุมวิท 101 | F63: armotep@senaxgroup.com | G63: 46076 | H63: 46077 | I63: ลาออก | J63: ได้รับเอกสารแล้ว | K63: ปิดลาออกแล้ว | L63: ปัจจัยที่ 3 งานในหน้าที่ | M63: ได้งานใหม่ หยุดเสาร์ - อาทิตย์ ซึ่งได้ทำงานที่เดียวกับที่แฟนทำงาน เป็นบริษัท ผลิตโซล่าเซลล์
A64: 1217 | B64: VMS680336 | C64: นายธนะวัตร แพร่งสุวรรณ์ | D64: 8855 ช่างประจำอาคาร | E64: แผนกอาคารชุด นิช โมโน พระราม 9 | F64: thanawatp@senxgroup.com | G64: 46042 | H64: 46043 | I64: ปลดออก | J64: ต้นสังกัดแจ้งทางเมล์ | K64: ปิดลาออกแล้ว | L64: ปัจจัยที่ 3 งานในหน้าที่ | M64: เนื่องจากให้ย้ายไปประจำโครงการอื่น เหตุผลเรื่องการเดินทางไกล ปัจจุบันพักแถวลาดพร้าว 110 ซึ่งโครงการที่ย้ายมาอยู่แถววิภาวดีรังสิตการเดินทางไกล
A65: 1218 | B65: BK680589 | C65: น.ส.อัญพัชญ์ พีระภักดีพงศ์ | D65: 23 ผู้อำนวยการ | E65: สายงานบริหารการขาย และการตลาดคอนโด 4 | F65: aunyapachp@sena.co.th | G65: 46112 | H65: 46113 | I65: ลาออก | J65: ได้รับเอกสารแล้ว | K65: ปิดลาออกแล้ว
A66: 1219 | B66: BK680226 | C66: น.ส.ฐิตาภรณ์ ยวงทอง | D66: 5404 ผู้ช่วยหัวหน้างานขายและสินเชื่อ | E66: โคซี่ บีทีเอส สะพานใหม่ | F66: thitaporny@sena.co.th | G66: 46076 | H66: 46077 | I66: ลาออก | J66: ได้รับเอกสารแล้ว | K66: ปิดลาออกแล้ว | L66: ปัจจัยที่ 1 ผลตอบแทนการทำงาน
A67: 1220 | B67: VMS680289 | C67: นางสาวพรพรหม ชาญชัย | D67: 5859 ผู้จัดการอาคาร | E67: แผนกอาคารชุด เฟล็กซี่ สาทร - เจริญนคร เฟส 2 | F67: pornpromc@senxgroup.com | G67: 46037 | H67: 46038 | I67: ปลดออก | K67: ปิดลาออกแล้ว
A68: 1221 | B68: SP680031 | C68: น.ส.ชลีรัตน์ สำรวล | D68: 36 ผู้ช่วยผู้จัดการ | E68: แผนกบัญชีต้นทุน | F68: chaleeruts@sena.co.th | G68: 46081 | H68: 46082 | I68: ยกเลิกลาออก | J68: ส่งเอกสารถึงพนักงาน | L68: ปัจจัยที่ 5 โอกาสในการเติบโต/พัฒนา
A69: 1222 | B69: BK690003 | C69: น.ส.กมลชนก ศุภวุฒิ | D69: 7301 เจ้าหน้าที่จัดสรรเงินทุน | E69: แผนก Project Budgeting & Budgeting Control | F69: kamonchanoksu@sena.co.th | G69: 46053 | H69: 46054 | I69: ลาออกไม่ครบ 30 วัน | J69: ได้รับเอกสารแล้ว | K69: ปิดลาออกแล้ว | L69: ปัจจัยที่ 3 งานในหน้าที่
A70: 1223 | B70: SSG670009 | C70: นายกิตติภูมิ ฐิติโรจนเทพา | D70: 8806 ผู้ช่วยช่าง | E70: ฝ่ายบำรุงรักษา | F70: kittipoomk@senasolarenergy.com | G70: 46081 | H70: 46082 | I70: ลาออก | J70: ได้รับเอกสารแล้ว | K70: ปิดลาออกแล้ว
A71: 1224 | B71: SX680021 | C71: นางสาวลัคนา ไวเจริญกุล | D71: 6601 เจ้าหน้าที่จัดซื้ออาวุโส | E71: แผนกทรัพย์สินสำนักงาน | F71: lakanaw@senxgroup.com | G71: 46053 | H71: 46054 | I71: ลาออกไม่ครบ 30 วัน | J71: ได้รับเอกสารแล้ว | K71: ปิดลาออกแล้ว | L71: ปัจจัยที่ 5 โอกาสในการเติบโต/พัฒนา | M71: ได้งานใหม่ ได้เงินเดือนเพิ่ม 3,000 บาท
A72: 1225 | B72: BK680171 | C72: น.ส.สุภาพร แข่งขัน | D72: 7405 เจ้าหน้าที่การตลาด | E72: สายงานบริหารการขาย และการตลาดคอนโด 1 | F72: supapornk@sena.co.th | G72: 46081 | H72: 46082 | I72: ลาออก | J72: ได้รับเอกสารแล้ว | K72: ปิดลาออกแล้ว | L72: ปัจจัยที่ 1 ผลตอบแทนการทำงาน
A73: 1226 | B73: SGA680015 | C73: น.ส.ณัฐกานต์ รัตนกุล | D73: 7988 เจ้าหน้าที่ธุรการขาย | E73: ฝ่ายลูกค้าสัมพันธ์ | F73: nutthakarnr@senasolarenergy.com | G73: 46053 | H73: 46054 | I73: ลาออกไม่ครบ 30 วัน | J73: ได้รับเอกสารแล้ว | K73: ปิดลาออกแล้ว
A74: 1227 | B74: BK680158 | C74: น.ส.วณิชชยา อายุโย | D74: 7353 เจ้าหน้าที่ประสานงานขายและการตลาด | E74: สายงานบริหารการขายคอนโด 1 | F74: wanitchayaa@sena.co.th | G74: 46081 | H74: 46082 | I74: ลาออก | J74: ได้รับเอกสารแล้ว | K74: ปิดลาออกแล้ว | L74: ปัจจัยที่ 1 ผลตอบแทนการทำงาน
A75: 1228 | B75: VMS690016 | C75: นายนนท์ จักรแก้ว | D75: 8855 ช่างประจำอาคาร | E75: แผนกอาคารชุด เสนาคิทท์ รังสิต - ติวานนท์ | F75: nonj@senxgroup.com | G75: 46053 | H75: 46054 | I75: ปลดออก | J75: ต้นสังกัดแจ้งทางเมล์ | K75: ปิดลาออกแล้ว
A76: 1229 | B76: SGA690001 | C76: น.ส.บุญยานุช หอมไกรลาศ | D76: 7154 เจ้าหน้าที่ลูกค้าสัมพันธ์ | E76: แผนกลูกค้าสัมพันธ์ | F76: boonyanuth@senasolarenergy.com | G76: 46081 | H76: 46082 | I76: ลาออก | J76: ได้รับเอกสารแล้ว | K76: ปิดลาออกแล้ว
A77: 1230 | B77: VMS680210 | C77: นายปริทรรศ์ โพธิ์น้อยงาม | D77: 8855 ช่างประจำอาคาร | E77: แผนกอาคารชุด นิช โมโน อิสรภาพ | F77: pareetasp@senxgroup.com | G77: 46053 | H77: 46054 | I77: ปลดออก | J77: ต้นสังกัดแจ้งทางเมล์ | K77: ปิดลาออกแล้ว
A78: 1231 | B78: SPS670023 | C78: นางสาวชนกนันท์ สายสิงห์ | D78: 36 ผู้ช่วยผู้จัดการ | E78: ฝ่าย Inter Sales | F78: chanoknuns@senxgroup.com | G78: 46066 | H78: 46067 | I78: ลาออกไม่ครบ 30 วัน | K78: ปิดลาออกแล้ว | L78: ปัจจัยที่ 6 ความจำเป็นส่วนตัว | M78: เนื่องจากไปทำร้านอาหารกับญาติ ที่ประเทศจีน
A79: 1232 | B79: VMS680227 | C79: นายการุณย์ เอี่ยมสอาด | D79: 5860 ผู้จัดการหมู่บ้าน | E79: แผนกหมู่บ้านจัดสรร โซนสำเพ็ง 2 | F79: karoonl@senxgroup.com | G79: 46081 | H79: 46082 | I79: ลาออก | K79: ปิดลาออกแล้ว | M79: เนื่ื่องด้วยปริมาณงานที่ทำมีคนเดียวทำให้งานโหลด และเอกสารต้องไปให้คณะกรรมการเซ็นต์ซึ่งอยู่คนละที่ ทำให้เอกสารกว่าจะเซ็นต์ช้า
A80: 1233 | B80: VMS680012 | C80: นางสาวจิรอร จันทร์สว่าง | D80: 7854 เจ้าหน้าที่นิติบุคคล | E80: แผนกอาคารชุด นิช โมโน สุขุมวิท - ปู่เจ้า | F80: jiraonj@sexgroup.com | G80: 46084 | H80: 46085 | I80: ลาออก | K80: ปิดลาออกแล้ว | L80: ปัจจัยที่ 1 ผลตอบแทนการทำงาน | M80: ได้งานใหม่เงินเพิ่มจากเดิม 1,000 บาท และเปลี่ยนสายงานเป็นตำแหน่งเจ้าหน้าที่จัดซื้อ
A81: 1234 | B81: VMS670387 | C81: นายถวิลศักดิ์ รอดเรือง | D81: 8855 ช่างประจำอาคาร | E81: แผนกอาคารชุด อีส 2 พระราม 2 | F81: tawinsakr@senxgroup.com | G81: 46053 | H81: 46054 | I81: ปลดออก | J81: ต้นสังกัดแจ้งทางเมล์ | K81: ปิดลาออกแล้ว | L81: ปัจจัยที่ 6 ความจำเป็นส่วนตัว | M81: กลับไปดูย่าที่ป่วยไม่มีคนดูแล ที่จังหวัดอำนาจเจริญ
A82: 1235 | B82: BK680521 | C82: นายสุทธิพงษ์ ทองมี | D82: 6558 เจ้าหน้าที่เขียนแบบอาวุโส | E82: แผนก Project Support | F82: suttipongt@sena.co.th | G82: 46081 | H82: 46082 | I82: ลาออกไม่ครบ 30 วัน | J82: ได้รับเอกสารแล้ว | K82: ปิดลาออกแล้ว
A83: 1236 | B83: VMS670120 | C83: นายเมธาสิทธิ์ ถาปันแก้ว | D83: 8254 ช่างเทคนิค | E83: แผนกอาคารชุด โมทีฟ คอนโด | F83: methasitt@senxgroup.com | G83: 46053 | H83: 46054 | I83: ปลดออก | J83: ต้นสังกัดแจ้งทางเมล์ | K83: ปิดลาออกแล้ว
A84: 1237 | B84: VMS690011 | C84: นายอนุสรณ์ สังข์สกุล | D84: 7855 หัวหน้าช่างประจำอาคาร | E84: แผนกอาคารชุด เสนาคิทท์ เอ็มอาร์ที บางแค | F84: anusons@senxgroup.com | G84: 46058 | H84: 46059 | I84: ปลดออก | J84: ต้นสังกัดแจ้งทางเมล์ | K84: ปิดลาออกแล้ว | M84: ติดต่อไม่ได้ไม่รับสาย
A85: 1238 | B85: VMS690039 | C85: นายธนัตถ์ ทรงวิริยะ | D85: 8855 ช่างประจำอาคาร | E85: แผนกอาคารชุด นิช โมโน บางโพ | F85: tanuts@senxgroup.com | G85: 46068 | H85: 46069 | I85: ลาออกไม่ครบ 30 วัน | K85: ปิดลาออกแล้ว | M85: ได้งานใหม่ในสายงานที่เรียนมาวิศกรรมเครื่องกล เป็นโรงงานคุมงานสายการผลิต
A86: 1239 | B86: SX690002 | C86: นางพัชรพร บัวดิศ | D86: 7660 เจ้าหน้าที่ประชาสัมพันธ์ | E86: แผนกบริหารข้อร้องเรียน | F86: patcharpornb@senxgroup.com | G86: 46055 | H86: 46056 | I86: ปลดออก | J86: ต้นสังกัดแจ้งทางเมล์ | K86: ปิดลาออกแล้ว
A87: 1240 | B87: VMS690060 | C87: นายจักรพงษ์ แสนพล | D87: 8855 ช่างประจำอาคาร | E87: แผนกอาคารชุด เวรี่ ลาซาล สุขุมวิท 105 | F87: Jakkapongs@senxgroup.com | G87: 46056 | H87: 46057 | I87: ปลดออก | J87: ต้นสังกัดแจ้งทางเมล์ | K87: ปิดลาออกแล้ว
A88: 1241 | B88: VMS690047 | C88: นายสิริวัฒน์ บุญราษฎร์ | D88: 8855 ช่างประจำอาคาร | E88: แผนกอาคารชุด คอลเลซซิโอ สาทร - พิพัฒน์ | F88: siriwatb@senxgroup.com | G88: 46063 | H88: 46064 | I88: ปลดออก | K88: ปิดลาออกแล้ว
A89: 1242 | B89: VMS680364 | C89: นางสาวนิชานันท์ สิทธิวรลักษณ์ | D89: 5859 ผู้จัดการอาคาร | E89: แผนกมาตรฐานโครงการใหม่ | F89: nichanuns@senxgroup.com | G89: 46055 | H89: 46056 | I89: ปลดออก | K89: ปิดลาออกแล้ว
A90: 1243 | B90: SPS680005 | C90: นางสาวนลินรัตน์ เอื้อโชคทวีวัฒน์ | D90: 7657 เจ้าหน้าที่ธุรการ | E90: แผนก RentNex | F90: nalinrata@senxgroup.com | G90: 46063 | H90: 46064 | I90: ปลดออก | K90: ปิดลาออกแล้ว
A91: 1244 | B91: BK680662 | C91: น.ส.ปวิตรา แสงรำไพ | D91: 6401 เจ้าหน้าที่ขายและสินเชื่ออาวุโส | E91: ปีติ สุขุมวิท 101 | F91: pawitras@sena.co.th | G91: 46081 | H91: 46082 | I91: ลาออกไม่ครบ 30 วัน | J91: ได้รับเอกสารแล้ว | K91: ปิดลาออกแล้ว
A92: 1245 | B92: BK690021 | C92: น.ส.ธันยารัศมิ์ ศุภประเสริฐ | D92: 7504 เจ้าหน้าที่ธุรการโครงการ | E92: เสนา วิลเลจ บางนา - กม.29 | F92: thanyarats@sena.co.th | G92: 46068 | H92: 46069 | I92: ลาออกไม่ครบ 30 วัน | K92: ปิดลาออกแล้ว | L92: ปัจจัยที่ 3 งานในหน้าที่
A93: 1246 | B93: BK680294 | C93: นายไพโรจน์ สินเพราะ | D93: 23 ผู้อำนวยการ | E93: สายงานบริหารโครงการคอนโด 11 | F93: pairoajs@sena.co.th | G93: 46099 | H93: 46100 | I93: ลาออก | J93: ได้รับเอกสารแล้ว | K93: ปิดลาออกแล้ว | L93: ปัจจัยที่ 5 โอกาสในการเติบโต/พัฒนา
A94: 1247 | B94: VMS680342 | C94: นางสาวไพลิน เชื้อวงษ์ | D94: 5860 ผู้จัดการหมู่บ้าน | E94: แผนกหมู่บ้านจัดสรร โซนรัตนาธิเบศร์ - บางบัวทอง | F94: pailinc@senxgroup.com | G94: 46093 | H94: 46094 | I94: ลาออก | K94: ปิดลาออกแล้ว | M94: รับผิดชอบ 4 โครง ทำให้ดูหน้าโครงการไม่ทั่วถึงและต้องวางระบบการทำงานใหม่ และ ในกรณีที่เจอปัญหาหัวหน้า AM ให้หาคำตอบจาก ผจก. คนอื่น
A95: 1248 | B95: VMS690034 | C95: นางสาวสุลัดดา แซ่เจีย | D95: 8971 พนักงานต้อนรับและบริการ | E95: แผนกอาคารชุด ปีติ สุขุมวิท 101 | F95: suladdas@senxgroup.com | G95: 46098 | H95: 46099 | I95: ลาออก | K95: ปิดลาออกแล้ว | M95: ต้องส่งอาหาร,ส่งของ,แบกน้ำแพ๊ค ส่งให้กับลูกบ้านทำให้ตอนนี้มีปัญหากับสุขภาพก้ามเนื้ออักเสบ
A96: 1249 | B96: VMS680102 | C96: นางสาวชิรัชยา สุรรัตน์ | D96: 5859 ผู้จัดการอาคาร | E96: แผนกอาคารชุด เสนาคิทท์ พหลโยธิน - นวนคร | F96: chiratchayas@senxgroup.com | G96: 46096 | H96: 46097 | I96: ลาออก | K96: ปิดลาออกแล้ว | M96: ต้องกลับต่างจังหวัดดูพ่อที่ป่วยนอนติดเตียง
A97: 1250 | B97: VMS680224 | C97: นายจิตติ แดงทิม | D97: 7854 เจ้าหน้าที่นิติบุคคล | E97: แผนกอาคารชุด เดอะนิช ไพรด์ ทองหล่อ - เพชรบุรี | F97: chittid@senxgroup.com | G97: 46081 | H97: 46082 | I97: ลาออกไม่ครบ 30 วัน | K97: ปิดลาออกแล้ว | M97: การเดินทางไกลบ้านปัจจุบันพักแถวดาวคะนอง และมีค่าน้ำมันทีต้องเติมเดือนละประมาณ 6,000 บาท
A98: 1251 | B98: VMS670396 | C98: นางสาววิภาวี ปานรอด | D98: 6851 ผู้ช่วยผู้จัดการอาคาร | E98: แผนกอาคารชุด โชคชัยร่วมมิตร คอนโด | F98: wipaweepa@senxgroup.com | G98: 46081 | H98: 46082 | I98: ลาออก | K98: ปิดลาออกแล้ว | M98: ได้งานใหม่ บ.LPP เงินเดือนเพิ่ม 3,000 บาท และ เดินทางไกลจากเดิมเนื่องจากปัจจุบันพัก 2 ที่ แถวพระราม 7 และ จอมทอง
A99: 1252 | B99: BK680665 | C99: น.ส.อลิสมาส เสงี่ยมวงศ์ | D99: 31.1 ผู้จัดการอาวุโส | E99: ฝ่ายบริหารการขายคอนโด 1E | F99: alissamass@sena.co.th | G99: 46081 | H99: 46082 | I99: ลาออกไม่ครบ 30 วัน | J99: ได้รับเอกสารแล้ว | K99: ปิดลาออกแล้ว | L99: ปัจจัยที่ 7 Probation (ไม่ผ่านทดลองงาน)
A100: 1253 | B100: BK680667 | C100: น.ส.ปาณิสรา สงพะโยม | D100: 6303 เจ้าหน้าที่กำกับดูแลอาวุโส | E100: แผนกกำกับดูแลกิจการ | F100: panisaras@sena.co.th | G100: 46081 | H100: 46082 | I100: ลาออกไม่ครบ 30 วัน | J100: ได้รับเอกสารแล้ว | K100: ปิดลาออกแล้ว | L100: ปัจจัยที่ 3 งานในหน้าที่
...

Sheet เลขที่เอกสารใบลาออก
A1: วันที่ | B1: รหัสพนักงาน | C1: ชื่อนามสกุล | D1: ตำแหน่ง | E1: ฝ่าย/แผนก | F1: วันที่พ้นสภาพ | G1: เลขที่เอกสารใบลาออก | H1: เลขที่เอกสาร Sena D | I1: เลขที่เอกสาร Sen X | J1: เลขที่เอกสาร Sena Green
A2: 45304 | B2: SD660001 | C2: นางสาวกาญจนา เทวกุล | D2: 21 ผู้อำนวยการอาวุโส | E2: สายงาน Brand & Strategic Communication | F2: 45304 | G2: 2024-001 | J2: =if(IF(OR(LEFT(B2,3)="SSE",LEFT(B2,3)="ESE",LEFT(B2,3)="SGA",LEFT(B2,3)="SRF",LEFT(B2,3)="SSG",LEFT(B2,3)="SGE"),"SGE")="SGE","SG2024-"&if(counta(#REF!)-countifs(#REF!,"")+1<=9,"00"&counta(#REF!)-countifs(#REF!,"")+1,if(counta(#REF!)-countifs(#REF!,"")+1<=99,"0"&counta(#REF!)-countifs(#REF!,"")+1,counta(#REF!)-countifs(#REF!,"")+1)),"")
A3: 45323 | B3: SX670050 | C3: นายธวัช สินสิงห์ | D3: 34 ผู้จัดการโครงการ | E3: ฝ่ายก่อสร้าง 52C | F3: 45323 | G3: 2024-002 | I3: SX-2024-001 | J3: =if(IF(OR(LEFT(B3,3)="SSE",LEFT(B3,3)="ESE",LEFT(B3,3)="SGA",LEFT(B3,3)="SRF",LEFT(B3,3)="SSG",LEFT(B3,3)="SGE"),"SGE")="SGE","SG2024-"&if(counta($J$2:J2)-countifs($J$2:J2,"")+1<=9,"00"&counta($J$2:J2)-countifs($J$2:J2,"")+1,if(counta($J$2:J2)-countifs($J$2:J2,"")+1<=99,"0"&counta($J$2:J2)-countifs($J$2:J2,"")+1,counta($J$2:J2)-countifs($J$2:J2,"")+1)),"")
A4: 45352 | B4: BK660105 | C4: นางสาวกฤติยา พวงปัญญา | D4: 7759 เจ้าหน้าที่บัญชีปิดงบ | E4: แผนกบัญชีต้นทุน | F4: 45352 | G4: 2024-003 | J4: =if(IF(OR(LEFT(B4,3)="SSE",LEFT(B4,3)="ESE",LEFT(B4,3)="SGA",LEFT(B4,3)="SRF",LEFT(B4,3)="SSG",LEFT(B4,3)="SGE"),"SGE")="SGE","SG2024-"&if(counta($J$2:J3)-countifs($J$2:J3,"")+1<=9,"00"&counta($J$2:J3)-countifs($J$2:J3,"")+1,if(counta($J$2:J3)-countifs($J$2:J3,"")+1<=99,"0"&counta($J$2:J3)-countifs($J$2:J3,"")+1,counta($J$2:J3)-countifs($J$2:J3,"")+1)),"")
A5: 45367 | B5: SD650010 | C5: นายธีระวัต เกิดสุข | D5: 7155 เจ้าหน้าที่กราฟฟิค | E5: แผนก Graphic Designer | F5: 45367 | G5: 2024-004 | J5: =if(IF(OR(LEFT(B5,3)="SSE",LEFT(B5,3)="ESE",LEFT(B5,3)="SGA",LEFT(B5,3)="SRF",LEFT(B5,3)="SSG",LEFT(B5,3)="SGE"),"SGE")="SGE","SG2024-"&if(counta($J$2:J4)-countifs($J$2:J4,"")+1<=9,"00"&counta($J$2:J4)-countifs($J$2:J4,"")+1,if(counta($J$2:J4)-countifs($J$2:J4,"")+1<=99,"0"&counta($J$2:J4)-countifs($J$2:J4,"")+1,counta($J$2:J4)-countifs($J$2:J4,"")+1)),"")
A6: 45383 | B6: BK610104 | C6: อุบลทิพย์ เอกชัยเรืองเดช | D6: 6551 สถาปนิกอาวุโส | E6: แผนกพัฒนาธุรกิจและสรรหาที่ดิน | F6: 45390 | G6: 2024-005 | J6: =if(IF(OR(LEFT(B6,3)="SSE",LEFT(B6,3)="ESE",LEFT(B6,3)="SGA",LEFT(B6,3)="SRF",LEFT(B6,3)="SSG",LEFT(B6,3)="SGE"),"SGE")="SGE","SG2024-"&if(counta($J$2:J5)-countifs($J$2:J5,"")+1<=9,"00"&counta($J$2:J5)-countifs($J$2:J5,"")+1,if(counta($J$2:J5)-countifs($J$2:J5,"")+1<=99,"0"&counta($J$2:J5)-countifs($J$2:J5,"")+1,counta($J$2:J5)-countifs($J$2:J5,"")+1)),"")
A7: 45383 | B7: MMS660436 | C7: นางสาวอัยลดา กรโกษา | D7: 33 ผู้จัดการ | E7: ฝ่ายการตลาดธุรกิจ 2D | F7: 45383 | G7: 2024-006 | J7: =if(IF(OR(LEFT(B7,3)="SSE",LEFT(B7,3)="ESE",LEFT(B7,3)="SGA",LEFT(B7,3)="SRF",LEFT(B7,3)="SSG",LEFT(B7,3)="SGE"),"SGE")="SGE","SG2024-"&if(counta($J$2:J6)-countifs($J$2:J6,"")+1<=9,"00"&counta($J$2:J6)-countifs($J$2:J6,"")+1,if(counta($J$2:J6)-countifs($J$2:J6,"")+1<=99,"0"&counta($J$2:J6)-countifs($J$2:J6,"")+1,counta($J$2:J6)-countifs($J$2:J6,"")+1)),"")
A8: 45352 | B8: BK660130 | C8: นางสาวปนัดดา ศรีมาตย์ | D8: 7451 เจ้าหน้าที่สินเชื่อ | E8: ฝ่ายการตลาดธุรกิจ 2D | F8: 45352 | G8: 2024-007 | J8: =if(IF(OR(LEFT(B8,3)="SSE",LEFT(B8,3)="ESE",LEFT(B8,3)="SGA",LEFT(B8,3)="SRF",LEFT(B8,3)="SSG",LEFT(B8,3)="SGE"),"SGE")="SGE","SG2024-"&if(counta($J$2:J7)-countifs($J$2:J7,"")+1<=9,"00"&counta($J$2:J7)-countifs($J$2:J7,"")+1,if(counta($J$2:J7)-countifs($J$2:J7,"")+1<=99,"0"&counta($J$2:J7)-countifs($J$2:J7,"")+1,counta($J$2:J7)-countifs($J$2:J7,"")+1)),"")
A9: 45352 | B9: BK660144 | C9: นางสาวพิรญาณ์ พิมพา | D9: 7453 เจ้าหน้าที่ภูมิทัศน์ | E9: แผนกดูแลภูมิทัศน์ | F9: 45352 | G9: 2024-008 | J9: =if(IF(OR(LEFT(B9,3)="SSE",LEFT(B9,3)="ESE",LEFT(B9,3)="SGA",LEFT(B9,3)="SRF",LEFT(B9,3)="SSG",LEFT(B9,3)="SGE"),"SGE")="SGE","SG2024-"&if(counta($J$2:J8)-countifs($J$2:J8,"")+1<=9,"00"&counta($J$2:J8)-countifs($J$2:J8,"")+1,if(counta($J$2:J8)-countifs($J$2:J8,"")+1<=99,"0"&counta($J$2:J8)-countifs($J$2:J8,"")+1,counta($J$2:J8)-countifs($J$2:J8,"")+1)),"")
A10: 45383 | B10: BK650039 | C10: นางสาวเพ็ญพิชชา แซ่หลี | D10: 7759 เจ้าหน้าที่บัญชีปิดงบ | E10: แผนกบัญชีต้นทุน | F10: 45383 | G10: 2024-009 | J10: =if(IF(OR(LEFT(B10,3)="SSE",LEFT(B10,3)="ESE",LEFT(B10,3)="SGA",LEFT(B10,3)="SRF",LEFT(B10,3)="SSG",LEFT(B10,3)="SGE"),"SGE")="SGE","SG2024-"&if(counta($J$2:J9)-countifs($J$2:J9,"")+1<=9,"00"&counta($J$2:J9)-countifs($J$2:J9,"")+1,if(counta($J$2:J9)-countifs($J$2:J9,"")+1<=99,"0"&counta($J$2:J9)-countifs($J$2:J9,"")+1,counta($J$2:J9)-countifs($J$2:J9,"")+1)),"")
A11: 45383 | B11: VMS660042 | C11: นายนิธิพล คัมภีรพันธ์ | D11: 8855 ช่างประจำอาคาร | E11: ส่วนงานวิศวกรรม | F11: 45383 | G11: 2024-010 | I11: SX-VMS2024-001 | J11: =if(IF(OR(LEFT(B11,3)="SSE",LEFT(B11,3)="ESE",LEFT(B11,3)="SGA",LEFT(B11,3)="SRF",LEFT(B11,3)="SSG",LEFT(B11,3)="SGE"),"SGE")="SGE","SG2024-"&if(counta($J$2:J10)-countifs($J$2:J10,"")+1<=9,"00"&counta($J$2:J10)-countifs($J$2:J10,"")+1,if(counta($J$2:J10)-countifs($J$2:J10,"")+1<=99,"0"&counta($J$2:J10)-countifs($J$2:J10,"")+1,counta($J$2:J10)-countifs($J$2:J10,"")+1)),"")
A12: 45380 | B12: VMS650135 | C12: นายพุฒ กกกลิ่น | D12: 8855 ช่างประจำอาคาร | E12: ส่วนงานวิศวกรรม | F12: 45380 | G12: 2024-011 | I12: SX-VMS2024-002 | J12: =if(IF(OR(LEFT(B12,3)="SSE",LEFT(B12,3)="ESE",LEFT(B12,3)="SGA",LEFT(B12,3)="SRF",LEFT(B12,3)="SSG",LEFT(B12,3)="SGE"),"SGE")="SGE","SG2024-"&if(counta($J$2:J11)-countifs($J$2:J11,"")+1<=9,"00"&counta($J$2:J11)-countifs($J$2:J11,"")+1,if(counta($J$2:J11)-countifs($J$2:J11,"")+1<=99,"0"&counta($J$2:J11)-countifs($J$2:J11,"")+1,counta($J$2:J11)-countifs($J$2:J11,"")+1)),"")
A13: 45383 | B13: MMS660398 | C13: นางสาวภัสร์ฐิตา ตรีภพวริทธิ์ธร | D13: 6401 เจ้าหน้าที่ขายและสินเชื่ออาวุโส | E13: บ้านร่วมทางฝัน 6 ปิ่นเกล้า-บรมราชชนนี | F13: 45383 | G13: 2024-012 | J13: =if(IF(OR(LEFT(B13,3)="SSE",LEFT(B13,3)="ESE",LEFT(B13,3)="SGA",LEFT(B13,3)="SRF",LEFT(B13,3)="SSG",LEFT(B13,3)="SGE"),"SGE")="SGE","SG2024-"&if(counta($J$2:J12)-countifs($J$2:J12,"")+1<=9,"00"&counta($J$2:J12)-countifs($J$2:J12,"")+1,if(counta($J$2:J12)-countifs($J$2:J12,"")+1<=99,"0"&counta($J$2:J12)-countifs($J$2:J12,"")+1,counta($J$2:J12)-countifs($J$2:J12,"")+1)),"")
A14: 45395 | B14: BK650105 | C14: นางสาวธรรญธร โคมพันธ์ | D14: 7705 เจ้าหน้าที่โอนกรรมสิทธิ์ | E14: แผนกโอนกรรมสิทธิ์ | F14: 45395 | G14: 2024-013 | J14: =if(IF(OR(LEFT(B14,3)="SSE",LEFT(B14,3)="ESE",LEFT(B14,3)="SGA",LEFT(B14,3)="SRF",LEFT(B14,3)="SSG",LEFT(B14,3)="SGE"),"SGE")="SGE","SG2024-"&if(counta($J$2:J13)-countifs($J$2:J13,"")+1<=9,"00"&counta($J$2:J13)-countifs($J$2:J13,"")+1,if(counta($J$2:J13)-countifs($J$2:J13,"")+1<=99,"0"&counta($J$2:J13)-countifs($J$2:J13,"")+1,counta($J$2:J13)-countifs($J$2:J13,"")+1)),"")
A15: 45383 | B15: VMS660120 | C15: นายเดชา อุ่นหะวงค์ | D15: 7855 หัวหน้าช่างประจำอาคาร | E15: แผนกอาคารชุด เฟล็กซี่ เตาปูน อินเตอร์เชนจ์ | F15: 45383 | G15: 2024-014 | I15: SX-VMS2024-003 | J15: =if(IF(OR(LEFT(B15,3)="SSE",LEFT(B15,3)="ESE",LEFT(B15,3)="SGA",LEFT(B15,3)="SRF",LEFT(B15,3)="SSG",LEFT(B15,3)="SGE"),"SGE")="SGE","SG2024-"&if(counta($J$2:J14)-countifs($J$2:J14,"")+1<=9,"00"&counta($J$2:J14)-countifs($J$2:J14,"")+1,if(counta($J$2:J14)-countifs($J$2:J14,"")+1<=99,"0"&counta($J$2:J14)-countifs($J$2:J14,"")+1,counta($J$2:J14)-countifs($J$2:J14,"")+1)),"")
A16: 45383 | B16: VMS660134 | C16: นายธนวัฒน์ พิวัฒน์สมบัติ | D16: 7854 เจ้าหน้าที่นิติบุคคล | E16: แผนกอาคารชุด เฟล็กซี่ รัตนาธิเบศร์ | F16: 45383 | G16: 2024-015 | I16: SX-VMS2024-004 | J16: =if(IF(OR(LEFT(B16,3)="SSE",LEFT(B16,3)="ESE",LEFT(B16,3)="SGA",LEFT(B16,3)="SRF",LEFT(B16,3)="SSG",LEFT(B16,3)="SGE"),"SGE")="SGE","SG2024-"&if(counta($J$2:J15)-countifs($J$2:J15,"")+1<=9,"00"&counta($J$2:J15)-countifs($J$2:J15,"")+1,if(counta($J$2:J15)-countifs($J$2:J15,"")+1<=99,"0"&counta($J$2:J15)-countifs($J$2:J15,"")+1,counta($J$2:J15)-countifs($J$2:J15,"")+1)),"")
A17: 45383 | B17: BK650277 | C17: นายชัยวิชิต เจริญชัยเพชร | D17: 7705 เจ้าหน้าที่โอนกรรมสิทธิ์ | E17: แผนกโอนกรรมสิทธิ์ | F17: 45383 | G17: 2024-016 | J17: =if(IF(OR(LEFT(B17,3)="SSE",LEFT(B17,3)="ESE",LEFT(B17,3)="SGA",LEFT(B17,3)="SRF",LEFT(B17,3)="SSG",LEFT(B17,3)="SGE"),"SGE")="SGE","SG2024-"&if(counta($J$2:J16)-countifs($J$2:J16,"")+1<=9,"00"&counta($J$2:J16)-countifs($J$2:J16,"")+1,if(counta($J$2:J16)-countifs($J$2:J16,"")+1<=99,"0"&counta($J$2:J16)-countifs($J$2:J16,"")+1,counta($J$2:J16)-countifs($J$2:J16,"")+1)),"")
A18: 45383 | B18: MMS660430 | C18: นายศิร พวงธนสาร | D18: 7405 เจ้าหน้าที่การตลาด | E18: แผนกการตลาดธุรกิจ 2B | F18: 45383 | G18: 2024-017 | J18: =if(IF(OR(LEFT(B18,3)="SSE",LEFT(B18,3)="ESE",LEFT(B18,3)="SGA",LEFT(B18,3)="SRF",LEFT(B18,3)="SSG",LEFT(B18,3)="SGE"),"SGE")="SGE","SG2024-"&if(counta($J$2:J17)-countifs($J$2:J17,"")+1<=9,"00"&counta($J$2:J17)-countifs($J$2:J17,"")+1,if(counta($J$2:J17)-countifs($J$2:J17,"")+1<=99,"0"&counta($J$2:J17)-countifs($J$2:J17,"")+1,counta($J$2:J17)-countifs($J$2:J17,"")+1)),"")
A19: 45383 | B19: SX670064 | C19: นายสิทธิชัย มีสุข | D19: 7502 ช่างสำรวจ | E19: ส่วนสำรวจโครงการก่อสร้าง 52 | F19: 45383 | G19: 2024-018 | I19: SX-2024-002 | J19: =if(IF(OR(LEFT(B19,3)="SSE",LEFT(B19,3)="ESE",LEFT(B19,3)="SGA",LEFT(B19,3)="SRF",LEFT(B19,3)="SSG",LEFT(B19,3)="SGE"),"SGE")="SGE","SG2024-"&if(counta($J$2:J18)-countifs($J$2:J18,"")+1<=9,"00"&counta($J$2:J18)-countifs($J$2:J18,"")+1,if(counta($J$2:J18)-countifs($J$2:J18,"")+1<=99,"0"&counta($J$2:J18)-countifs($J$2:J18,"")+1,counta($J$2:J18)-countifs($J$2:J18,"")+1)),"")
A20: 45383 | B20: MMS670014 | C20: นางสาวรัชนีกร ผ่องใส | D20: 6402 เจ้าหน้าที่การตลาดอาวุโส | E20: แผนกการตลาดธุรกิจ 41A | F20: 45383 | G20: 2024-019 | J20: =if(IF(OR(LEFT(B20,3)="SSE",LEFT(B20,3)="ESE",LEFT(B20,3)="SGA",LEFT(B20,3)="SRF",LEFT(B20,3)="SSG",LEFT(B20,3)="SGE"),"SGE")="SGE","SG2024-"&if(counta($J$2:J19)-countifs($J$2:J19,"")+1<=9,"00"&counta($J$2:J19)-countifs($J$2:J19,"")+1,if(counta($J$2:J19)-countifs($J$2:J19,"")+1<=99,"0"&counta($J$2:J19)-countifs($J$2:J19,"")+1,counta($J$2:J19)-countifs($J$2:J19,"")+1)),"")
C21: นางสาวรุจิรา น้ำทอง | G21: 2024-020 | J21: =if(IF(OR(LEFT(B21,3)="SSE",LEFT(B21,3)="ESE",LEFT(B21,3)="SGA",LEFT(B21,3)="SRF",LEFT(B21,3)="SSG",LEFT(B21,3)="SGE"),"SGE")="SGE","SG2024-"&if(counta($J$2:J20)-countifs($J$2:J20,"")+1<=9,"00"&counta($J$2:J20)-countifs($J$2:J20,"")+1,if(counta($J$2:J20)-countifs($J$2:J20,"")+1<=99,"0"&counta($J$2:J20)-countifs($J$2:J20,"")+1,counta($J$2:J20)-countifs($J$2:J20,"")+1)),"")
A22: 45383 | B22: ELR660003 | C22: นางสาวเสาวณี สุขขำมาศ | D22: 7971 เจ้าหน้าที่ต้อนรับและบริการ | E22: แผนกอาคารชุด ปีติ สุขุมวิท 101 | F22: 45383 | G22: 2024-021 | I22: SX-ELR2024-001 | J22: =if(IF(OR(LEFT(B22,3)="SSE",LEFT(B22,3)="ESE",LEFT(B22,3)="SGA",LEFT(B22,3)="SRF",LEFT(B22,3)="SSG",LEFT(B22,3)="SGE"),"SGE")="SGE","SG2024-"&if(counta($J$2:J21)-countifs($J$2:J21,"")+1<=9,"00"&counta($J$2:J21)-countifs($J$2:J21,"")+1,if(counta($J$2:J21)-countifs($J$2:J21,"")+1<=99,"0"&counta($J$2:J21)-countifs($J$2:J21,"")+1,counta($J$2:J21)-countifs($J$2:J21,"")+1)),"")
A23: 45398 | B23: BK620192 | C23: นางสาวอนุศรา สิงห์สา | D23: 31 ผู้จัดการอาวุโส | E23: ฝ่ายจัดสรรเงินทุน | F23: 45398 | G23: 2024-022 | J23: =if(IF(OR(LEFT(B23,3)="SSE",LEFT(B23,3)="ESE",LEFT(B23,3)="SGA",LEFT(B23,3)="SRF",LEFT(B23,3)="SSG",LEFT(B23,3)="SGE"),"SGE")="SGE","SG2024-"&if(counta($J$2:J22)-countifs($J$2:J22,"")+1<=9,"00"&counta($J$2:J22)-countifs($J$2:J22,"")+1,if(counta($J$2:J22)-countifs($J$2:J22,"")+1<=99,"0"&counta($J$2:J22)-countifs($J$2:J22,"")+1,counta($J$2:J22)-countifs($J$2:J22,"")+1)),"")
A24: 45367 | B24: SP17660004 | C24: วิลาวัณย์ อุดศรี | D24: 7754 เจ้าหน้าที่บัญชีลูกหนี้ | E24: แผนกบัญชีลูกหนี้ (ร่วมทุน) | F24: 45367 | G24: 2024-023 | J24: =if(IF(OR(LEFT(B24,3)="SSE",LEFT(B24,3)="ESE",LEFT(B24,3)="SGA",LEFT(B24,3)="SRF",LEFT(B24,3)="SSG",LEFT(B24,3)="SGE"),"SGE")="SGE","SG2024-"&if(counta($J$2:J23)-countifs($J$2:J23,"")+1<=9,"00"&counta($J$2:J23)-countifs($J$2:J23,"")+1,if(counta($J$2:J23)-countifs($J$2:J23,"")+1<=99,"0"&counta($J$2:J23)-countifs($J$2:J23,"")+1,counta($J$2:J23)-countifs($J$2:J23,"")+1)),"")
A25: 45399 | B25: MMS660219 | C25: นางสาวธนัชภรณ์ พรมวาด | D25: 4401 หัวหน้างานขายและสินเชื่อ | E25: เสนาคิทท์ สาทร-กัลปพฤกษ์ | F25: 45399 | G25: 2024-024 | J25: =if(IF(OR(LEFT(B25,3)="SSE",LEFT(B25,3)="ESE",LEFT(B25,3)="SGA",LEFT(B25,3)="SRF",LEFT(B25,3)="SSG",LEFT(B25,3)="SGE"),"SGE")="SGE","SG2024-"&if(counta($J$2:J24)-countifs($J$2:J24,"")+1<=9,"00"&counta($J$2:J24)-countifs($J$2:J24,"")+1,if(counta($J$2:J24)-countifs($J$2:J24,"")+1<=99,"0"&counta($J$2:J24)-countifs($J$2:J24,"")+1,counta($J$2:J24)-countifs($J$2:J24,"")+1)),"")
A26: 45383 | B26: MMS650142 | C26: นางสาวรัฐติกรณ์ ฤทธิ์ประเสริฐ | D26: 6401 เจ้าหน้าที่ขายและสินเชื่ออาวุโส | E26: เสนา คิทท์ เพชรเกษม-พุทธมณฑลสาย 7 | F26: 45383 | G26: 2024-025 | J26: =if(IF(OR(LEFT(B26,3)="SSE",LEFT(B26,3)="ESE",LEFT(B26,3)="SGA",LEFT(B26,3)="SRF",LEFT(B26,3)="SSG",LEFT(B26,3)="SGE"),"SGE")="SGE","SG2024-"&if(counta($J$2:J25)-countifs($J$2:J25,"")+1<=9,"00"&counta($J$2:J25)-countifs($J$2:J25,"")+1,if(counta($J$2:J25)-countifs($J$2:J25,"")+1<=99,"0"&counta($J$2:J25)-countifs($J$2:J25,"")+1,counta($J$2:J25)-countifs($J$2:J25,"")+1)),"")
A27: 45371 | B27: VMS660103 | C27: นายสนิท อินประภัทตร์ | D27: 8855 ช่างประจำอาคาร | E27: แผนกวิศวกรรมส่วนกลาง | F27: 45371 | G27: 2024-026 | I27: SX-VMS2024-005 | J27: =if(IF(OR(LEFT(B27,3)="SSE",LEFT(B27,3)="ESE",LEFT(B27,3)="SGA",LEFT(B27,3)="SRF",LEFT(B27,3)="SSG",LEFT(B27,3)="SGE"),"SGE")="SGE","SG2024-"&if(counta($J$2:J26)-countifs($J$2:J26,"")+1<=9,"00"&counta($J$2:J26)-countifs($J$2:J26,"")+1,if(counta($J$2:J26)-countifs($J$2:J26,"")+1<=99,"0"&counta($J$2:J26)-countifs($J$2:J26,"")+1,counta($J$2:J26)-countifs($J$2:J26,"")+1)),"")
A28: 45400 | B28: MMS660312 | C28: นางสาวปาลญา อัศวะลาภา | D28: 6401 เจ้าหน้าที่ขายและสินเชื่ออาวุโส | E28: เสนาคิทท์ สาทร-กัลปพฤกษ์ | F28: 45400 | G28: 2024-027 | J28: =if(IF(OR(LEFT(B28,3)="SSE",LEFT(B28,3)="ESE",LEFT(B28,3)="SGA",LEFT(B28,3)="SRF",LEFT(B28,3)="SSG",LEFT(B28,3)="SGE"),"SGE")="SGE","SG2024-"&if(counta($J$2:J27)-countifs($J$2:J27,"")+1<=9,"00"&counta($J$2:J27)-countifs($J$2:J27,"")+1,if(counta($J$2:J27)-countifs($J$2:J27,"")+1<=99,"0"&counta($J$2:J27)-countifs($J$2:J27,"")+1,counta($J$2:J27)-countifs($J$2:J27,"")+1)),"")
A29: 45413 | B29: VMS620065 | C29: นายประชา สมจิตร์ | D29: 6856 หัวหน้าช่างประจำอาคารอาวุโส | E29: แผนกพัฒนางานบริหารอาคาร (Start Up) | F29: 45413 | G29: 2024-029 | I29: SX-VMS2024-006 | J29: =if(IF(OR(LEFT(B29,3)="SSE",LEFT(B29,3)="ESE",LEFT(B29,3)="SGA",LEFT(B29,3)="SRF",LEFT(B29,3)="SSG",LEFT(B29,3)="SGE"),"SGE")="SGE","SG2024-"&if(counta($J$2:J28)-countifs($J$2:J28,"")+1<=9,"00"&counta($J$2:J28)-countifs($J$2:J28,"")+1,if(counta($J$2:J28)-countifs($J$2:J28,"")+1<=99,"0"&counta($J$2:J28)-countifs($J$2:J28,"")+1,counta($J$2:J28)-countifs($J$2:J28,"")+1)),"")
A30: 45413 | B30: SX660026 | C30: นายสุภกิณห์ ภัทรมั่นคงสกุล | D30: 7755 เจ้าหน้าที่บัญชีต้นทุน | E30: แผนกบัญชีต้นทุน | F30: 45413 | G30: 2024-030 | I30: SX-2024-003 | J30: =if(IF(OR(LEFT(B30,3)="SSE",LEFT(B30,3)="ESE",LEFT(B30,3)="SGA",LEFT(B30,3)="SRF",LEFT(B30,3)="SSG",LEFT(B30,3)="SGE"),"SGE")="SGE","SG2024-"&if(counta($J$2:J29)-countifs($J$2:J29,"")+1<=9,"00"&counta($J$2:J29)-countifs($J$2:J29,"")+1,if(counta($J$2:J29)-countifs($J$2:J29,"")+1<=99,"0"&counta($J$2:J29)-countifs($J$2:J29,"")+1,counta($J$2:J29)-countifs($J$2:J29,"")+1)),"")
A31: 45413 | B31: BK660035 | C31: นายภูวเดช อีศรัตน์ | D31: เจ้าหน้าที่อาวุโส | E31: แผนกสินเชื่อ 1 | F31: 45413 | G31: 2024-031 | J31: =if(IF(OR(LEFT(B31,3)="SSE",LEFT(B31,3)="ESE",LEFT(B31,3)="SGA",LEFT(B31,3)="SRF",LEFT(B31,3)="SSG",LEFT(B31,3)="SGE"),"SGE")="SGE","SG2024-"&if(counta($J$2:J30)-countifs($J$2:J30,"")+1<=9,"00"&counta($J$2:J30)-countifs($J$2:J30,"")+1,if(counta($J$2:J30)-countifs($J$2:J30,"")+1<=99,"0"&counta($J$2:J30)-countifs($J$2:J30,"")+1,counta($J$2:J30)-countifs($J$2:J30,"")+1)),"")
A32: 45413 | B32: SP18660003 | C32: นางสาวกนกทิพย์ แก้วสียา | D32: 7759 เจ้าหน้าที่บัญชีปิดงบ | E32: แผนกบัญชีงบการเงิน (ร่วมทุน) | F32: 45413 | G32: 2024-032 | J32: =if(IF(OR(LEFT(B32,3)="SSE",LEFT(B32,3)="ESE",LEFT(B32,3)="SGA",LEFT(B32,3)="SRF",LEFT(B32,3)="SSG",LEFT(B32,3)="SGE"),"SGE")="SGE","SG2024-"&if(counta($J$2:J31)-countifs($J$2:J31,"")+1<=9,"00"&counta($J$2:J31)-countifs($J$2:J31,"")+1,if(counta($J$2:J31)-countifs($J$2:J31,"")+1<=99,"0"&counta($J$2:J31)-countifs($J$2:J31,"")+1,counta($J$2:J31)-countifs($J$2:J31,"")+1)),"")
A33: 45398 | B33: BK610009 | C33: นายศุภกร ศรีวิเศษ | D33: 7551 สถาปนิก | E33: แผนก DESIGN DEVELOP | F33: 45398 | G33: 2024-033 | J33: =if(IF(OR(LEFT(B33,3)="SSE",LEFT(B33,3)="ESE",LEFT(B33,3)="SGA",LEFT(B33,3)="SRF",LEFT(B33,3)="SSG",LEFT(B33,3)="SGE"),"SGE")="SGE","SG2024-"&if(counta($J$2:J32)-countifs($J$2:J32,"")+1<=9,"00"&counta($J$2:J32)-countifs($J$2:J32,"")+1,if(counta($J$2:J32)-countifs($J$2:J32,"")+1<=99,"0"&counta($J$2:J32)-countifs($J$2:J32,"")+1,counta($J$2:J32)-countifs($J$2:J32,"")+1)),"")
A34: 45413 | B34: MMS650047 | C34: นางสาวธนกร ใหม่จันทร์ | D34: 5101 ผู้ช่วยหัวหน้าแผนก | E34: แผนกการตลาดธุรกิจ 12 | F34: 45413 | G34: 2024-034 | J34: =if(IF(OR(LEFT(B34,3)="SSE",LEFT(B34,3)="ESE",LEFT(B34,3)="SGA",LEFT(B34,3)="SRF",LEFT(B34,3)="SSG",LEFT(B34,3)="SGE"),"SGE")="SGE","SG2024-"&if(counta($J$2:J33)-countifs($J$2:J33,"")+1<=9,"00"&counta($J$2:J33)-countifs($J$2:J33,"")+1,if(counta($J$2:J33)-countifs($J$2:J33,"")+1<=99,"0"&counta($J$2:J33)-countifs($J$2:J33,"")+1,counta($J$2:J33)-countifs($J$2:J33,"")+1)),"")
A35: 45413 | B35: BK660002 | C35: นางสาวแพรพลอย สุขสุทอง | D35: 7601 เจ้าหน้าที่จัดซื้อ | E35: แผนกจัดซื้อแนวสูง | F35: 45413 | G35: 2024-035 | J35: =if(IF(OR(LEFT(B35,3)="SSE",LEFT(B35,3)="ESE",LEFT(B35,3)="SGA",LEFT(B35,3)="SRF",LEFT(B35,3)="SSG",LEFT(B35,3)="SGE"),"SGE")="SGE","SG2024-"&if(counta($J$2:J34)-countifs($J$2:J34,"")+1<=9,"00"&counta($J$2:J34)-countifs($J$2:J34,"")+1,if(counta($J$2:J34)-countifs($J$2:J34,"")+1<=99,"0"&counta($J$2:J34)-countifs($J$2:J34,"")+1,counta($J$2:J34)-countifs($J$2:J34,"")+1)),"")
A36: 45413 | B36: BK670040 | C36: นางสาวยุวเทวี กลางบุรัมย์ | D36: 7659 เจ้าหน้าที่ประสานงานทั่วไป | E36: สายงาน Supply Chain Planning | F36: 45413 | G36: 2024-036 | J36: =if(IF(OR(LEFT(B36,3)="SSE",LEFT(B36,3)="ESE",LEFT(B36,3)="SGA",LEFT(B36,3)="SRF",LEFT(B36,3)="SSG",LEFT(B36,3)="SGE"),"SGE")="SGE","SG2024-"&if(counta($J$2:J35)-countifs($J$2:J35,"")+1<=9,"00"&counta($J$2:J35)-countifs($J$2:J35,"")+1,if(counta($J$2:J35)-countifs($J$2:J35,"")+1<=99,"0"&counta($J$2:J35)-countifs($J$2:J35,"")+1,counta($J$2:J35)-countifs($J$2:J35,"")+1)),"")
A37: 45413 | B37: BK650299 | C37: นางสาวปรีดาวรรณ ทัพพ่วง | D37: 23 ผู้อำนวยการ | E37: สายงานบริการลูกค้าด้านสินเชื่อ | F37: 45413 | G37: 2024-037 | J37: =if(IF(OR(LEFT(B37,3)="SSE",LEFT(B37,3)="ESE",LEFT(B37,3)="SGA",LEFT(B37,3)="SRF",LEFT(B37,3)="SSG",LEFT(B37,3)="SGE"),"SGE")="SGE","SG2024-"&if(counta($J$2:J36)-countifs($J$2:J36,"")+1<=9,"00"&counta($J$2:J36)-countifs($J$2:J36,"")+1,if(counta($J$2:J36)-countifs($J$2:J36,"")+1<=99,"0"&counta($J$2:J36)-countifs($J$2:J36,"")+1,counta($J$2:J36)-countifs($J$2:J36,"")+1)),"")
A38: 45413 | B38: VMS660034 | C38: นายภาวัช นราสินธนโชค | D38: 5859 ผู้จัดการอาคาร | E38: แผนกอาคารชุด นิช โมโน เมกะ สเปซ บางนา | F38: 45413 | G38: 2024-038 | I38: SX-VMS2024-007 | J38: =if(IF(OR(LEFT(B38,3)="SSE",LEFT(B38,3)="ESE",LEFT(B38,3)="SGA",LEFT(B38,3)="SRF",LEFT(B38,3)="SSG",LEFT(B38,3)="SGE"),"SGE")="SGE","SG2024-"&if(counta($J$2:J37)-countifs($J$2:J37,"")+1<=9,"00"&counta($J$2:J37)-countifs($J$2:J37,"")+1,if(counta($J$2:J37)-countifs($J$2:J37,"")+1<=99,"0"&counta($J$2:J37)-countifs($J$2:J37,"")+1,counta($J$2:J37)-countifs($J$2:J37,"")+1)),"")
A39: 45413 | B39: VMS650109 | C39: นายนนวัต บวรวัชรเมธี | D39: 5859 ผู้จัดการอาคาร | E39: แผนกพัฒนางานบริหารอาคาร (Start Up) | F39: 45413 | G39: 2024-039 | I39: SX-VMS2024-008 | J39: =if(IF(OR(LEFT(B39,3)="SSE",LEFT(B39,3)="ESE",LEFT(B39,3)="SGA",LEFT(B39,3)="SRF",LEFT(B39,3)="SSG",LEFT(B39,3)="SGE"),"SGE")="SGE","SG2024-"&if(counta($J$2:J38)-countifs($J$2:J38,"")+1<=9,"00"&counta($J$2:J38)-countifs($J$2:J38,"")+1,if(counta($J$2:J38)-countifs($J$2:J38,"")+1<=99,"0"&counta($J$2:J38)-countifs($J$2:J38,"")+1,counta($J$2:J38)-countifs($J$2:J38,"")+1)),"")
A40: 45413 | B40: VMS650118 | C40: นางสาวอาแอเสาะ สาแล๊ะ | D40: 7854 เจ้าหน้าที่นิติบุคคล | E40: ส่วนงานดูแลอาคาร | F40: 45413 | G40: 2024-040 | I40: SX-VMS2024-009 | J40: =if(IF(OR(LEFT(B40,3)="SSE",LEFT(B40,3)="ESE",LEFT(B40,3)="SGA",LEFT(B40,3)="SRF",LEFT(B40,3)="SSG",LEFT(B40,3)="SGE"),"SGE")="SGE","SG2024-"&if(counta($J$2:J39)-countifs($J$2:J39,"")+1<=9,"00"&counta($J$2:J39)-countifs($J$2:J39,"")+1,if(counta($J$2:J39)-countifs($J$2:J39,"")+1<=99,"0"&counta($J$2:J39)-countifs($J$2:J39,"")+1,counta($J$2:J39)-countifs($J$2:J39,"")+1)),"")
A41: 45413 | B41: SD650008 | C41: นายอธิรักษ์ ธรมธัช | D41: 7157 เจ้าหน้าที่การตลาดออนไลน์ | E41: แผนก Online Marketing | F41: 45413 | G41: 2024-041 | J41: =if(IF(OR(LEFT(B41,3)="SSE",LEFT(B41,3)="ESE",LEFT(B41,3)="SGA",LEFT(B41,3)="SRF",LEFT(B41,3)="SSG",LEFT(B41,3)="SGE"),"SGE")="SGE","SG2024-"&if(counta($J$2:J40)-countifs($J$2:J40,"")+1<=9,"00"&counta($J$2:J40)-countifs($J$2:J40,"")+1,if(counta($J$2:J40)-countifs($J$2:J40,"")+1<=99,"0"&counta($J$2:J40)-countifs($J$2:J40,"")+1,counta($J$2:J40)-countifs($J$2:J40,"")+1)),"")
A42: 45413 | B42: BK640183 | C42: นายโสภณัฐ พรมสุทธิพันธ์ | D42: 7755 เจ้าหน้าที่บัญชีต้นทุน | E42: แผนกบัญชีต้นทุน | F42: 45413 | G42: 2024-042 | J42: =if(IF(OR(LEFT(B42,3)="SSE",LEFT(B42,3)="ESE",LEFT(B42,3)="SGA",LEFT(B42,3)="SRF",LEFT(B42,3)="SSG",LEFT(B42,3)="SGE"),"SGE")="SGE","SG2024-"&if(counta($J$2:J41)-countifs($J$2:J41,"")+1<=9,"00"&counta($J$2:J41)-countifs($J$2:J41,"")+1,if(counta($J$2:J41)-countifs($J$2:J41,"")+1<=99,"0"&counta($J$2:J41)-countifs($J$2:J41,"")+1,counta($J$2:J41)-countifs($J$2:J41,"")+1)),"")
A43: 45413 | B43: VMS630030 | C43: นายสิทธิกร ปานบุญทอง | D43: 8855 ช่างประจำอาคาร | E43: ส่วนงานวิศวกรรม | F43: 45413 | G43: 2024-043 | I43: SX-VMS2024-010 | J43: =if(IF(OR(LEFT(B43,3)="SSE",LEFT(B43,3)="ESE",LEFT(B43,3)="SGA",LEFT(B43,3)="SRF",LEFT(B43,3)="SSG",LEFT(B43,3)="SGE"),"SGE")="SGE","SG2024-"&if(counta($J$2:J42)-countifs($J$2:J42,"")+1<=9,"00"&counta($J$2:J42)-countifs($J$2:J42,"")+1,if(counta($J$2:J42)-countifs($J$2:J42,"")+1<=99,"0"&counta($J$2:J42)-countifs($J$2:J42,"")+1,counta($J$2:J42)-countifs($J$2:J42,"")+1)),"")
A44: 45411 | B44: VMS660108 | C44: นางสาวมุทิตา เปล่งสงคราม | D44: 36 ผู้ช่วยผู้จัดการ | E44: ฝ่ายบริหารนิติบุคคลหมู่บ้านจัดสรร (SENA) | F44: 45411 | G44: 2024-044 | I44: SX-VMS2024-011 | J44: =if(IF(OR(LEFT(B44,3)="SSE",LEFT(B44,3)="ESE",LEFT(B44,3)="SGA",LEFT(B44,3)="SRF",LEFT(B44,3)="SSG",LEFT(B44,3)="SGE"),"SGE")="SGE","SG2024-"&if(counta($J$2:J43)-countifs($J$2:J43,"")+1<=9,"00"&counta($J$2:J43)-countifs($J$2:J43,"")+1,if(counta($J$2:J43)-countifs($J$2:J43,"")+1<=99,"0"&counta($J$2:J43)-countifs($J$2:J43,"")+1,counta($J$2:J43)-countifs($J$2:J43,"")+1)),"")
A45: 45413 | B45: MMS660308 | C45: นายสุทัศน์ มาตรักษ์ | D45: 4501 วิศวกรโครงการ | E45: เสนา วิลล์ ลำลูกกา - คลอง 6 | F45: 45413 | G45: 2024-045 | J45: =if(IF(OR(LEFT(B45,3)="SSE",LEFT(B45,3)="ESE",LEFT(B45,3)="SGA",LEFT(B45,3)="SRF",LEFT(B45,3)="SSG",LEFT(B45,3)="SGE"),"SGE")="SGE","SG2024-"&if(counta($J$2:J44)-countifs($J$2:J44,"")+1<=9,"00"&counta($J$2:J44)-countifs($J$2:J44,"")+1,if(counta($J$2:J44)-countifs($J$2:J44,"")+1<=99,"0"&counta($J$2:J44)-countifs($J$2:J44,"")+1,counta($J$2:J44)-countifs($J$2:J44,"")+1)),"")
A46: 45413 | B46: VMS640037 | C46: นายประพัทธ์ สืบรักษ์ | D46: 7854 เจ้าหน้าที่นิติบุคคล | E46: ส่วนงานดูแลอาคาร | F46: 45413 | G46: 2024-046 | I46: SX-VMS2024-012 | J46: =if(IF(OR(LEFT(B46,3)="SSE",LEFT(B46,3)="ESE",LEFT(B46,3)="SGA",LEFT(B46,3)="SRF",LEFT(B46,3)="SSG",LEFT(B46,3)="SGE"),"SGE")="SGE","SG2024-"&if(counta($J$2:J45)-countifs($J$2:J45,"")+1<=9,"00"&counta($J$2:J45)-countifs($J$2:J45,"")+1,if(counta($J$2:J45)-countifs($J$2:J45,"")+1<=99,"0"&counta($J$2:J45)-countifs($J$2:J45,"")+1,counta($J$2:J45)-countifs($J$2:J45,"")+1)),"")
A47: 45413 | B47: VMS640029 | C47: นางสาวสุกัญญา โพธิ์ประยูร | D47: 7854 เจ้าหน้าที่นิติบุคคล | E47: ส่วนงานดูแลอาคาร | F47: 45413 | G47: 2024-047 | I47: SX-VMS2024-013 | J47: =if(IF(OR(LEFT(B47,3)="SSE",LEFT(B47,3)="ESE",LEFT(B47,3)="SGA",LEFT(B47,3)="SRF",LEFT(B47,3)="SSG",LEFT(B47,3)="SGE"),"SGE")="SGE","SG2024-"&if(counta($J$2:J46)-countifs($J$2:J46,"")+1<=9,"00"&counta($J$2:J46)-countifs($J$2:J46,"")+1,if(counta($J$2:J46)-countifs($J$2:J46,"")+1<=99,"0"&counta($J$2:J46)-countifs($J$2:J46,"")+1,counta($J$2:J46)-countifs($J$2:J46,"")+1)),"")
A48: 45413 | B48: VMS650102 | C48: นายกฤตเมธ สีสัย | D48: 8857 ช่างเทคนิค | E48: แผนกวิศวกรรมส่วนกลาง | F48: 45413 | G48: 2024-048 | I48: SX-VMS2024-014 | J48: =if(IF(OR(LEFT(B48,3)="SSE",LEFT(B48,3)="ESE",LEFT(B48,3)="SGA",LEFT(B48,3)="SRF",LEFT(B48,3)="SSG",LEFT(B48,3)="SGE"),"SGE")="SGE","SG2024-"&if(counta($J$2:J47)-countifs($J$2:J47,"")+1<=9,"00"&counta($J$2:J47)-countifs($J$2:J47,"")+1,if(counta($J$2:J47)-countifs($J$2:J47,"")+1<=99,"0"&counta($J$2:J47)-countifs($J$2:J47,"")+1,counta($J$2:J47)-countifs($J$2:J47,"")+1)),"")
A49: 45413 | B49: BK660041 | C49: นางสาวปวริศา โสภาวาง | D49: 7303 เจ้าหน้าที่กำกับดูแล | E49: แผนกกำกับดูแลกิจการ | F49: 45413 | G49: 2024-049 | J49: =if(IF(OR(LEFT(B49,3)="SSE",LEFT(B49,3)="ESE",LEFT(B49,3)="SGA",LEFT(B49,3)="SRF",LEFT(B49,3)="SSG",LEFT(B49,3)="SGE"),"SGE")="SGE","SG2024-"&if(counta($J$2:J48)-countifs($J$2:J48,"")+1<=9,"00"&counta($J$2:J48)-countifs($J$2:J48,"")+1,if(counta($J$2:J48)-countifs($J$2:J48,"")+1<=99,"0"&counta($J$2:J48)-countifs($J$2:J48,"")+1,counta($J$2:J48)-countifs($J$2:J48,"")+1)),"")
A50: 45404 | B50: MMS660316 | C50: นางสาวพรรณทิพย์ หิรัญศุภโชติ | D50: 7401 เจ้าหน้าที่ขายและสินเชื่อ | E50: เสนาคิทท์ รัตนาธิเบศร์-บางบัวทอง | F50: 45404 | G50: 2024-050 | J50: =if(IF(OR(LEFT(B50,3)="SSE",LEFT(B50,3)="ESE",LEFT(B50,3)="SGA",LEFT(B50,3)="SRF",LEFT(B50,3)="SSG",LEFT(B50,3)="SGE"),"SGE")="SGE","SG2024-"&if(counta($J$2:J49)-countifs($J$2:J49,"")+1<=9,"00"&counta($J$2:J49)-countifs($J$2:J49,"")+1,if(counta($J$2:J49)-countifs($J$2:J49,"")+1<=99,"0"&counta($J$2:J49)-countifs($J$2:J49,"")+1,counta($J$2:J49)-countifs($J$2:J49,"")+1)),"")
A51: 45387 | B51: BK660060 | C51: นางสาวจินตนา นิกรรัมย์ | D51: 7352 เจ้าหน้าที่ประสานงานโครงการ | E51: สายงานพัฒนาโครงการและพัฒนาผลิตภัณฑ์ | F51: 45387 | G51: 2024-051 | J51: =if(IF(OR(LEFT(B51,3)="SSE",LEFT(B51,3)="ESE",LEFT(B51,3)="SGA",LEFT(B51,3)="SRF",LEFT(B51,3)="SSG",LEFT(B51,3)="SGE"),"SGE")="SGE","SG2024-"&if(counta($J$2:J50)-countifs($J$2:J50,"")+1<=9,"00"&counta($J$2:J50)-countifs($J$2:J50,"")+1,if(counta($J$2:J50)-countifs($J$2:J50,"")+1<=99,"0"&counta($J$2:J50)-countifs($J$2:J50,"")+1,counta($J$2:J50)-countifs($J$2:J50,"")+1)),"")
A52: 45416 | B52: SX660033 | C52: นางสาวจิตปราณี สีหนาทธัญญ | D52: 7756 เจ้าหน้าที่บัญชีทั่วไป | E52: แผนกบัญชีทั่วไป | F52: 45416 | G52: 2024-052 | I52: SX-2024-004 | J52: =if(IF(OR(LEFT(B52,3)="SSE",LEFT(B52,3)="ESE",LEFT(B52,3)="SGA",LEFT(B52,3)="SRF",LEFT(B52,3)="SSG",LEFT(B52,3)="SGE"),"SGE")="SGE","SG2024-"&if(counta($J$2:J51)-countifs($J$2:J51,"")+1<=9,"00"&counta($J$2:J51)-countifs($J$2:J51,"")+1,if(counta($J$2:J51)-countifs($J$2:J51,"")+1<=99,"0"&counta($J$2:J51)-countifs($J$2:J51,"")+1,counta($J$2:J51)-countifs($J$2:J51,"")+1)),"")
A53: 45413 | B53: MMS650485 | C53: นายชลกร อุ่นมีศรี | D53: 7354 Project Coordinator | E53: สายงานก่อสร้าง 11 | F53: 45413 | G53: 2024-053 | J53: =if(IF(OR(LEFT(B53,3)="SSE",LEFT(B53,3)="ESE",LEFT(B53,3)="SGA",LEFT(B53,3)="SRF",LEFT(B53,3)="SSG",LEFT(B53,3)="SGE"),"SGE")="SGE","SG2024-"&if(counta($J$2:J52)-countifs($J$2:J52,"")+1<=9,"00"&counta($J$2:J52)-countifs($J$2:J52,"")+1,if(counta($J$2:J52)-countifs($J$2:J52,"")+1<=99,"0"&counta($J$2:J52)-countifs($J$2:J52,"")+1,counta($J$2:J52)-countifs($J$2:J52,"")+1)),"")
A54: 45413 | B54: BK660095 | C54: นางสาวกาญจนา กาบินพงษ์ | D54: 7660 เจ้าหน้าที่ประชาสัมพันธ์ | E54: แผนกบริการสำนักงาน | F54: 45413 | G54: 2024-054 | J54: =if(IF(OR(LEFT(B54,3)="SSE",LEFT(B54,3)="ESE",LEFT(B54,3)="SGA",LEFT(B54,3)="SRF",LEFT(B54,3)="SSG",LEFT(B54,3)="SGE"),"SGE")="SGE","SG2024-"&if(counta($J$2:J53)-countifs($J$2:J53,"")+1<=9,"00"&counta($J$2:J53)-countifs($J$2:J53,"")+1,if(counta($J$2:J53)-countifs($J$2:J53,"")+1<=99,"0"&counta($J$2:J53)-countifs($J$2:J53,"")+1,counta($J$2:J53)-countifs($J$2:J53,"")+1)),"")
A55: 45413 | B55: BK660009 | C55: นายมนตรี อินทร์สำราญ | D55: 7503 โฟร์แมนเกษตร | E55: แผนกดูแลภูมิทัศน์ (Green) | F55: 45413 | G55: 2024-055 | J55: =if(IF(OR(LEFT(B55,3)="SSE",LEFT(B55,3)="ESE",LEFT(B55,3)="SGA",LEFT(B55,3)="SRF",LEFT(B55,3)="SSG",LEFT(B55,3)="SGE"),"SGE")="SGE","SG2024-"&if(counta($J$2:J54)-countifs($J$2:J54,"")+1<=9,"00"&counta($J$2:J54)-countifs($J$2:J54,"")+1,if(counta($J$2:J54)-countifs($J$2:J54,"")+1<=99,"0"&counta($J$2:J54)-countifs($J$2:J54,"")+1,counta($J$2:J54)-countifs($J$2:J54,"")+1)),"")
A56: 45418 | B56: BK560029 | C56: นางสาวนิตยา วงษ์ดี | D56: 49 เลขานุการผู้ช่วยกรรมการผู้จัดการ | E56: สายงานสนับสนุนงานก่อสร้าง | F56: 45418 | G56: 2024-056 | J56: =if(IF(OR(LEFT(B56,3)="SSE",LEFT(B56,3)="ESE",LEFT(B56,3)="SGA",LEFT(B56,3)="SRF",LEFT(B56,3)="SSG",LEFT(B56,3)="SGE"),"SGE")="SGE","SG2024-"&if(counta($J$2:J55)-countifs($J$2:J55,"")+1<=9,"00"&counta($J$2:J55)-countifs($J$2:J55,"")+1,if(counta($J$2:J55)-countifs($J$2:J55,"")+1<=99,"0"&counta($J$2:J55)-countifs($J$2:J55,"")+1,counta($J$2:J55)-countifs($J$2:J55,"")+1)),"")
A57: 45415 | B57: MMS650082 | C57: นายวัชรพล ธรรมรักษ์เจริญ | D57: 7503 โฟร์แมนเกษตร | E57: เสนา วิลล์ ลำลูกกา - คลอง 6 | F57: 45415 | G57: 2024-057 | J57: =if(IF(OR(LEFT(B57,3)="SSE",LEFT(B57,3)="ESE",LEFT(B57,3)="SGA",LEFT(B57,3)="SRF",LEFT(B57,3)="SSG",LEFT(B57,3)="SGE"),"SGE")="SGE","SG2024-"&if(counta($J$2:J56)-countifs($J$2:J56,"")+1<=9,"00"&counta($J$2:J56)-countifs($J$2:J56,"")+1,if(counta($J$2:J56)-countifs($J$2:J56,"")+1<=99,"0"&counta($J$2:J56)-countifs($J$2:J56,"")+1,counta($J$2:J56)-countifs($J$2:J56,"")+1)),"")
A58: 45413 | B58: SX670072 | C58: ว่าที่ ร.ต.หญิงอรอุมา นิลรักษา | D58: 6401 เจ้าหน้าที่ขายและสินเชื่ออาวุโส | E58: ส่วนการขายเสนา อเวนิว 1-2 และเวล่า รังสิต - คลอง 1 | F58: 45413 | G58: 2024-058 | I58: SX-2024-005 | J58: =if(IF(OR(LEFT(B58,3)="SSE",LEFT(B58,3)="ESE",LEFT(B58,3)="SGA",LEFT(B58,3)="SRF",LEFT(B58,3)="SSG",LEFT(B58,3)="SGE"),"SGE")="SGE","SG2024-"&if(counta($J$2:J57)-countifs($J$2:J57,"")+1<=9,"00"&counta($J$2:J57)-countifs($J$2:J57,"")+1,if(counta($J$2:J57)-countifs($J$2:J57,"")+1<=99,"0"&counta($J$2:J57)-countifs($J$2:J57,"")+1,counta($J$2:J57)-countifs($J$2:J57,"")+1)),"")
A59: 45413 | B59: VMS640030 | C59: นายภูริพัฒน์ พวงสมบัติ | D59: 8855 ช่างประจำอาคาร | E59: แผนกอาคารชุด นิช โมโน เมกะ สเปซ บางนา | F59: 45413 | G59: 2024-059 | I59: SX-VMS2024-015 | J59: =if(IF(OR(LEFT(B59,3)="SSE",LEFT(B59,3)="ESE",LEFT(B59,3)="SGA",LEFT(B59,3)="SRF",LEFT(B59,3)="SSG",LEFT(B59,3)="SGE"),"SGE")="SGE","SG2024-"&if(counta($J$2:J58)-countifs($J$2:J58,"")+1<=9,"00"&counta($J$2:J58)-countifs($J$2:J58,"")+1,if(counta($J$2:J58)-countifs($J$2:J58,"")+1<=99,"0"&counta($J$2:J58)-countifs($J$2:J58,"")+1,counta($J$2:J58)-countifs($J$2:J58,"")+1)),"")
A60: 45413 | B60: VMS640032 | C60: นายกระแสฟ้า หวังผล | D60: 8855 ช่างประจำอาคาร | E60: แผนกอาคารชุด นิช โมโน เมกะ สเปซ บางนา | F60: 45413 | G60: 2024-060 | I60: SX-VMS2024-016 | J60: =if(IF(OR(LEFT(B60,3)="SSE",LEFT(B60,3)="ESE",LEFT(B60,3)="SGA",LEFT(B60,3)="SRF",LEFT(B60,3)="SSG",LEFT(B60,3)="SGE"),"SGE")="SGE","SG2024-"&if(counta($J$2:J59)-countifs($J$2:J59,"")+1<=9,"00"&counta($J$2:J59)-countifs($J$2:J59,"")+1,if(counta($J$2:J59)-countifs($J$2:J59,"")+1<=99,"0"&counta($J$2:J59)-countifs($J$2:J59,"")+1,counta($J$2:J59)-countifs($J$2:J59,"")+1)),"")
A61: 45413 | B61: MMS650120 | C61: นางสาวฐิติภรณ์ บำรุงสงฆ์ | D61: 7504 เจ้าหน้าที่ธุรการโครงการ | E61: เสนา วีว่า ฉลองกรุง - ลาดกระบัง | F61: 45413 | G61: 2024-061 | J61: =if(IF(OR(LEFT(B61,3)="SSE",LEFT(B61,3)="ESE",LEFT(B61,3)="SGA",LEFT(B61,3)="SRF",LEFT(B61,3)="SSG",LEFT(B61,3)="SGE"),"SGE")="SGE","SG2024-"&if(counta($J$2:J60)-countifs($J$2:J60,"")+1<=9,"00"&counta($J$2:J60)-countifs($J$2:J60,"")+1,if(counta($J$2:J60)-countifs($J$2:J60,"")+1<=99,"0"&counta($J$2:J60)-countifs($J$2:J60,"")+1,counta($J$2:J60)-countifs($J$2:J60,"")+1)),"")
A62: 45413 | B62: SX670079 | C62: นางสาวสุกัญญา ศรีวิชัย | D62: 7401 เจ้าหน้าที่ขายและสินเชื่อ | E62: ส่วนการขายเสนา วิลเลจ ติวานนท์ - บางกะดี | F62: 45413 | G62: 2024-062 | I62: SX-2024-006 | J62: =if(IF(OR(LEFT(B62,3)="SSE",LEFT(B62,3)="ESE",LEFT(B62,3)="SGA",LEFT(B62,3)="SRF",LEFT(B62,3)="SSG",LEFT(B62,3)="SGE"),"SGE")="SGE","SG2024-"&if(counta($J$2:J61)-countifs($J$2:J61,"")+1<=9,"00"&counta($J$2:J61)-countifs($J$2:J61,"")+1,if(counta($J$2:J61)-countifs($J$2:J61,"")+1<=99,"0"&counta($J$2:J61)-countifs($J$2:J61,"")+1,counta($J$2:J61)-countifs($J$2:J61,"")+1)),"")
A63: 45413 | B63: VMS660041 | C63: นายพีรพล พุทธชาติกุล | D63: 8855 ช่างประจำอาคาร | E63: ส่วนงานวิศวกรรม | F63: 45413 | G63: 2024-063 | I63: SX-VMS2024-017 | J63: =if(IF(OR(LEFT(B63,3)="SSE",LEFT(B63,3)="ESE",LEFT(B63,3)="SGA",LEFT(B63,3)="SRF",LEFT(B63,3)="SSG",LEFT(B63,3)="SGE"),"SGE")="SGE","SG2024-"&if(counta($J$2:J62)-countifs($J$2:J62,"")+1<=9,"00"&counta($J$2:J62)-countifs($J$2:J62,"")+1,if(counta($J$2:J62)-countifs($J$2:J62,"")+1<=99,"0"&counta($J$2:J62)-countifs($J$2:J62,"")+1,counta($J$2:J62)-countifs($J$2:J62,"")+1)),"")
A64: 45418 | B64: MMS650511 | C64: นางสาวณัฐพร แซ่ล้อ | D64: 7354 Project Coordinator | E64: สำนักบริหารโครงการ 2 | F64: 45418 | G64: 2024-064 | J64: =if(IF(OR(LEFT(B64,3)="SSE",LEFT(B64,3)="ESE",LEFT(B64,3)="SGA",LEFT(B64,3)="SRF",LEFT(B64,3)="SSG",LEFT(B64,3)="SGE"),"SGE")="SGE","SG2024-"&if(counta($J$2:J63)-countifs($J$2:J63,"")+1<=9,"00"&counta($J$2:J63)-countifs($J$2:J63,"")+1,if(counta($J$2:J63)-countifs($J$2:J63,"")+1<=99,"0"&counta($J$2:J63)-countifs($J$2:J63,"")+1,counta($J$2:J63)-countifs($J$2:J63,"")+1)),"")
A65: 45383 | B65: MMS660436 | C65: นางสาวอัยลดา กรโกษา | D65: 33 ผู้จัดการ | E65: ฝ่ายการตลาดธุรกิจ 2D | F65: 45383 | G65: 2024-065 | J65: =if(IF(OR(LEFT(B65,3)="SSE",LEFT(B65,3)="ESE",LEFT(B65,3)="SGA",LEFT(B65,3)="SRF",LEFT(B65,3)="SSG",LEFT(B65,3)="SGE"),"SGE")="SGE","SG2024-"&if(counta($J$2:J64)-countifs($J$2:J64,"")+1<=9,"00"&counta($J$2:J64)-countifs($J$2:J64,"")+1,if(counta($J$2:J64)-countifs($J$2:J64,"")+1<=99,"0"&counta($J$2:J64)-countifs($J$2:J64,"")+1,counta($J$2:J64)-countifs($J$2:J64,"")+1)),"")
A66: 45400 | B66: BK660021 | C66: นายเสกสม จิรวรรณสกุล | D66: 23 ผู้อำนวยการ | E66: สายงานบริหารทรัพยากรบุคคล | F66: 45400 | G66: 2024-066 | J66: =if(IF(OR(LEFT(B66,3)="SSE",LEFT(B66,3)="ESE",LEFT(B66,3)="SGA",LEFT(B66,3)="SRF",LEFT(B66,3)="SSG",LEFT(B66,3)="SGE"),"SGE")="SGE","SG2024-"&if(counta($J$2:J65)-countifs($J$2:J65,"")+1<=9,"00"&counta($J$2:J65)-countifs($J$2:J65,"")+1,if(counta($J$2:J65)-countifs($J$2:J65,"")+1<=99,"0"&counta($J$2:J65)-countifs($J$2:J65,"")+1,counta($J$2:J65)-countifs($J$2:J65,"")+1)),"")
A67: 45416 | B67: MMS650089 | C67: นายกิตติภณ อภิโรจน์ | D67: 6404 เจ้าหน้าที่การตลาดภาคสนามอาวุโส | E67: แผนกการตลาดธุรกิจ 3A | F67: 45416 | G67: 2024-067 | J67: =if(IF(OR(LEFT(B67,3)="SSE",LEFT(B67,3)="ESE",LEFT(B67,3)="SGA",LEFT(B67,3)="SRF",LEFT(B67,3)="SSG",LEFT(B67,3)="SGE"),"SGE")="SGE","SG2024-"&if(counta($J$2:J66)-countifs($J$2:J66,"")+1<=9,"00"&counta($J$2:J66)-countifs($J$2:J66,"")+1,if(counta($J$2:J66)-countifs($J$2:J66,"")+1<=99,"0"&counta($J$2:J66)-countifs($J$2:J66,"")+1,counta($J$2:J66)-countifs($J$2:J66,"")+1)),"")
A68: 45413 | B68: JSA670003 | C68: น.ส.ตวิษา ธรรมดี | D68: 4101 หัวหน้าแผนก | E68: แผนกบริหารเสนาเฮ้าส์ สาขาพหลโยธิน 30 | F68: 45413 | G68: 2024-068 | I68: SX-JSA2024-001 | J68: =if(IF(OR(LEFT(B68,3)="SSE",LEFT(B68,3)="ESE",LEFT(B68,3)="SGA",LEFT(B68,3)="SRF",LEFT(B68,3)="SSG",LEFT(B68,3)="SGE"),"SGE")="SGE","SG2024-"&if(counta($J$2:J67)-countifs($J$2:J67,"")+1<=9,"00"&counta($J$2:J67)-countifs($J$2:J67,"")+1,if(counta($J$2:J67)-countifs($J$2:J67,"")+1<=99,"0"&counta($J$2:J67)-countifs($J$2:J67,"")+1,counta($J$2:J67)-countifs($J$2:J67,"")+1)),"")
A69: 45383 | B69: MMS660222 | C69: นายอดิพงษ์ วงศ์จันลา | D69: วิศวกรไฟฟ้า | E69: เสนา แกรนด์ โฮม บางนา กม.29 | F69: 45383 | G69: 2024-069 | J69: =if(IF(OR(LEFT(B69,3)="SSE",LEFT(B69,3)="ESE",LEFT(B69,3)="SGA",LEFT(B69,3)="SRF",LEFT(B69,3)="SSG",LEFT(B69,3)="SGE"),"SGE")="SGE","SG2024-"&if(counta($J$2:J68)-countifs($J$2:J68,"")+1<=9,"00"&counta($J$2:J68)-countifs($J$2:J68,"")+1,if(counta($J$2:J68)-countifs($J$2:J68,"")+1<=99,"0"&counta($J$2:J68)-countifs($J$2:J68,"")+1,counta($J$2:J68)-countifs($J$2:J68,"")+1)),"")
A70: 45426 | B70: VMS660082 | C70: นายรินทร์ลภัทร เพ็งจันทร์ | F70: 45426 | G70: 2024-070 | I70: SX-VMS2024-018 | J70: =if(IF(OR(LEFT(B70,3)="SSE",LEFT(B70,3)="ESE",LEFT(B70,3)="SGA",LEFT(B70,3)="SRF",LEFT(B70,3)="SSG",LEFT(B70,3)="SGE"),"SGE")="SGE","SG2024-"&if(counta($J$2:J69)-countifs($J$2:J69,"")+1<=9,"00"&counta($J$2:J69)-countifs($J$2:J69,"")+1,if(counta($J$2:J69)-countifs($J$2:J69,"")+1<=99,"0"&counta($J$2:J69)-countifs($J$2:J69,"")+1,counta($J$2:J69)-countifs($J$2:J69,"")+1)),"")
A71: 45413 | B71: MMS660379 | C71: นายสุทธิพงษ์ บุญล้ำเลิศ | D71: 4401 หัวหน้างานขายและสินเชื่อ | E71: เสนา เวล่า เทพารักษ์-บางบ่อ | F71: 45413 | G71: 2024-071 | J71: =if(IF(OR(LEFT(B71,3)="SSE",LEFT(B71,3)="ESE",LEFT(B71,3)="SGA",LEFT(B71,3)="SRF",LEFT(B71,3)="SSG",LEFT(B71,3)="SGE"),"SGE")="SGE","SG2024-"&if(counta($J$2:J70)-countifs($J$2:J70,"")+1<=9,"00"&counta($J$2:J70)-countifs($J$2:J70,"")+1,if(counta($J$2:J70)-countifs($J$2:J70,"")+1<=99,"0"&counta($J$2:J70)-countifs($J$2:J70,"")+1,counta($J$2:J70)-countifs($J$2:J70,"")+1)),"")
A72: 45428 | B72: MMS650233 | C72: นางสาวดวงชีวัน กลิ่นเกษร | D72: 7501 โฟร์แมนควบคุมงาน | E72: เสนา วิลล์ รามอินทรา กม.8 | F72: 45428 | G72: 2024-072 | J72: =if(IF(OR(LEFT(B72,3)="SSE",LEFT(B72,3)="ESE",LEFT(B72,3)="SGA",LEFT(B72,3)="SRF",LEFT(B72,3)="SSG",LEFT(B72,3)="SGE"),"SGE")="SGE","SG2024-"&if(counta($J$2:J71)-countifs($J$2:J71,"")+1<=9,"00"&counta($J$2:J71)-countifs($J$2:J71,"")+1,if(counta($J$2:J71)-countifs($J$2:J71,"")+1<=99,"0"&counta($J$2:J71)-countifs($J$2:J71,"")+1,counta($J$2:J71)-countifs($J$2:J71,"")+1)),"")
A73: 45413 | B73: ELR660006 | C73: นายเกียรติกูล แก้วภูมิแห | D73: พนักงานต้อนรับ | E73: โครงการ ปีติ สุขุมวิท101 | F73: 45413 | G73: 2024-073 | I73: SX-ELR2024-002 | J73: =if(IF(OR(LEFT(B73,3)="SSE",LEFT(B73,3)="ESE",LEFT(B73,3)="SGA",LEFT(B73,3)="SRF",LEFT(B73,3)="SSG",LEFT(B73,3)="SGE"),"SGE")="SGE","SG2024-"&if(counta($J$2:J72)-countifs($J$2:J72,"")+1<=9,"00"&counta($J$2:J72)-countifs($J$2:J72,"")+1,if(counta($J$2:J72)-countifs($J$2:J72,"")+1<=99,"0"&counta($J$2:J72)-countifs($J$2:J72,"")+1,counta($J$2:J72)-countifs($J$2:J72,"")+1)),"")
A74: 45423 | B74: SX660028 | C74: น.ส.ศศิธร โชติกุล | D74: เจ้าหน้าที่บัญชีเจ้าหนี้ | E74: แผนกบัญชีเจ้าหนี้ | F74: 45423 | G74: 2024-074 | I74: SX-2024-007 | J74: =if(IF(OR(LEFT(B74,3)="SSE",LEFT(B74,3)="ESE",LEFT(B74,3)="SGA",LEFT(B74,3)="SRF",LEFT(B74,3)="SSG",LEFT(B74,3)="SGE"),"SGE")="SGE","SG2024-"&if(counta($J$2:J73)-countifs($J$2:J73,"")+1<=9,"00"&counta($J$2:J73)-countifs($J$2:J73,"")+1,if(counta($J$2:J73)-countifs($J$2:J73,"")+1<=99,"0"&counta($J$2:J73)-countifs($J$2:J73,"")+1,counta($J$2:J73)-countifs($J$2:J73,"")+1)),"")
A75: 45413 | B75: BK650234 | C75: นายพิชา ปานรักษา | D75: ผู้อำนวยการอาวุโส | E75: สายงานกลยุทธ์ธุรกิจ | F75: 45413 | G75: 2024-075 | J75: =if(IF(OR(LEFT(B75,3)="SSE",LEFT(B75,3)="ESE",LEFT(B75,3)="SGA",LEFT(B75,3)="SRF",LEFT(B75,3)="SSG",LEFT(B75,3)="SGE"),"SGE")="SGE","SG2024-"&if(counta($J$2:J74)-countifs($J$2:J74,"")+1<=9,"00"&counta($J$2:J74)-countifs($J$2:J74,"")+1,if(counta($J$2:J74)-countifs($J$2:J74,"")+1<=99,"0"&counta($J$2:J74)-countifs($J$2:J74,"")+1,counta($J$2:J74)-countifs($J$2:J74,"")+1)),"")
A76: 45413 | B76: BK660071 | C76: ลักษณพร เอี่ยมสำอางค์ | D76: 7751 เจ้าหน้าที่บัญชีจ่าย | E76: ฝ่ายบัญชีจ่าย-เจ้าหนี้ | F76: 45413 | G76: 2024-076 | J76: =if(IF(OR(LEFT(B76,3)="SSE",LEFT(B76,3)="ESE",LEFT(B76,3)="SGA",LEFT(B76,3)="SRF",LEFT(B76,3)="SSG",LEFT(B76,3)="SGE"),"SGE")="SGE","SG2024-"&if(counta($J$2:J75)-countifs($J$2:J75,"")+1<=9,"00"&counta($J$2:J75)-countifs($J$2:J75,"")+1,if(counta($J$2:J75)-countifs($J$2:J75,"")+1<=99,"0"&counta($J$2:J75)-countifs($J$2:J75,"")+1,counta($J$2:J75)-countifs($J$2:J75,"")+1)),"")
A77: 45444 | B77: MMS650522 | C77: นายวิทยา สาที | D77: ผูู้จัดการโครงการ | E77: ก่อสร้างเสนาคิทท์ ศรีนครินทร์ – ศรีด่าน | F77: 45444 | G77: - | H77: SD2024-001 | J77: =if(IF(OR(LEFT(B77,3)="SSE",LEFT(B77,3)="ESE",LEFT(B77,3)="SGA",LEFT(B77,3)="SRF",LEFT(B77,3)="SSG",LEFT(B77,3)="SGE"),"SGE")="SGE","SG2024-"&if(counta($J$2:J76)-countifs($J$2:J76,"")+1<=9,"00"&counta($J$2:J76)-countifs($J$2:J76,"")+1,if(counta($J$2:J76)-countifs($J$2:J76,"")+1<=99,"0"&counta($J$2:J76)-countifs($J$2:J76,"")+1,counta($J$2:J76)-countifs($J$2:J76,"")+1)),"")
A78: 45444 | B78: MMS660200 | C78: นายพงศ์พิสุทธิ์ ก้อนแก้ว | D78: 7501 โฟร์แมนควบคุมงาน | E78: เฟล็กซี่ สุขสวัสดิ์ | F78: 45444 | G78: - | H78: SD2024-002 | J78: =if(IF(OR(LEFT(B78,3)="SSE",LEFT(B78,3)="ESE",LEFT(B78,3)="SGA",LEFT(B78,3)="SRF",LEFT(B78,3)="SSG",LEFT(B78,3)="SGE"),"SGE")="SGE","SG2024-"&if(counta($J$2:J77)-countifs($J$2:J77,"")+1<=9,"00"&counta($J$2:J77)-countifs($J$2:J77,"")+1,if(counta($J$2:J77)-countifs($J$2:J77,"")+1<=99,"0"&counta($J$2:J77)-countifs($J$2:J77,"")+1,counta($J$2:J77)-countifs($J$2:J77,"")+1)),"")
A79: 45292 | B79: AR670109 | C79: ธนบัตร สนิท | D79: ช่างเทคนิค | E79: นิติฯ เบลกราเวีย เรสซิเดนซ์ | F79: 45292 | I79: SX-AR2024-001 | J79: =if(IF(OR(LEFT(B79,3)="SSE",LEFT(B79,3)="ESE",LEFT(B79,3)="SGA",LEFT(B79,3)="SRF",LEFT(B79,3)="SSG",LEFT(B79,3)="SGE"),"SGE")="SGE","SG2024-"&if(counta($J$2:J78)-countifs($J$2:J78,"")+1<=9,"00"&counta($J$2:J78)-countifs($J$2:J78,"")+1,if(counta($J$2:J78)-countifs($J$2:J78,"")+1<=99,"0"&counta($J$2:J78)-countifs($J$2:J78,"")+1,counta($J$2:J78)-countifs($J$2:J78,"")+1)),"")
A80: 24476 | B80: AR670099 | C80: ศุภนีพร ลางคุลเสน | D80: ผู้จัดการอาคาร | E80: นิติฯ เบลกราเวีย เรสซิเดนซ์ | F80: 24476 | I80: SX-AR2024-005 | J80: =if(IF(OR(LEFT(B80,3)="SSE",LEFT(B80,3)="ESE",LEFT(B80,3)="SGA",LEFT(B80,3)="SRF",LEFT(B80,3)="SSG",LEFT(B80,3)="SGE"),"SGE")="SGE","SG2024-"&if(counta($J$2:J79)-countifs($J$2:J79,"")+1<=9,"00"&counta($J$2:J79)-countifs($J$2:J79,"")+1,if(counta($J$2:J79)-countifs($J$2:J79,"")+1<=99,"0"&counta($J$2:J79)-countifs($J$2:J79,"")+1,counta($J$2:J79)-countifs($J$2:J79,"")+1)),"")
A81: 45302 | B81: AR670155 | C81: ฉัตรชัย เกสลาม | D81: ช่างเทคนิค | E81: นิติฯ แมเนอร์ สนามบินน้ำ | F81: 45302 | I81: SX-AR2024-006 | J81: =if(IF(OR(LEFT(B81,3)="SSE",LEFT(B81,3)="ESE",LEFT(B81,3)="SGA",LEFT(B81,3)="SRF",LEFT(B81,3)="SSG",LEFT(B81,3)="SGE"),"SGE")="SGE","SG2024-"&if(counta($J$2:J80)-countifs($J$2:J80,"")+1<=9,"00"&counta($J$2:J80)-countifs($J$2:J80,"")+1,if(counta($J$2:J80)-countifs($J$2:J80,"")+1<=99,"0"&counta($J$2:J80)-countifs($J$2:J80,"")+1,counta($J$2:J80)-countifs($J$2:J80,"")+1)),"")
A82: 45312 | B82: AR670126 | C82: ณัฐวุฒิ เจริญวงค์ | D82: ช่างเทคนิค | E82: นิติฯ แมเนอร์ สนามบินน้ำ | F82: 45312 | I82: SX-AR2024-007 | J82: =if(IF(OR(LEFT(B82,3)="SSE",LEFT(B82,3)="ESE",LEFT(B82,3)="SGA",LEFT(B82,3)="SRF",LEFT(B82,3)="SSG",LEFT(B82,3)="SGE"),"SGE")="SGE","SG2024-"&if(counta($J$2:J81)-countifs($J$2:J81,"")+1<=9,"00"&counta($J$2:J81)-countifs($J$2:J81,"")+1,if(counta($J$2:J81)-countifs($J$2:J81,"")+1<=99,"0"&counta($J$2:J81)-countifs($J$2:J81,"")+1,counta($J$2:J81)-countifs($J$2:J81,"")+1)),"")
A83: 45312 | B83: AR670207 | C83: นายบุญฤทธิ์ ทองห่อ | D83: ช่างเทคนิค | E83: นิติฯ เดอะเชดด์ สาทร 1 | F83: 45312 | I83: SX-AR2024-008 | J83: =if(IF(OR(LEFT(B83,3)="SSE",LEFT(B83,3)="ESE",LEFT(B83,3)="SGA",LEFT(B83,3)="SRF",LEFT(B83,3)="SSG",LEFT(B83,3)="SGE"),"SGE")="SGE","SG2024-"&if(counta($J$2:J82)-countifs($J$2:J82,"")+1<=9,"00"&counta($J$2:J82)-countifs($J$2:J82,"")+1,if(counta($J$2:J82)-countifs($J$2:J82,"")+1<=99,"0"&counta($J$2:J82)-countifs($J$2:J82,"")+1,counta($J$2:J82)-countifs($J$2:J82,"")+1)),"")
A84: 45310 | B84: AR670165 | C84: ณัฐวุฒิ พุ่มหมัน | D84: ช่างเทคนิค | E84: นิติฯ แมเนอร์ สนามบินน้ำ | F84: 45310 | I84: SX-AR2024-009 | J84: =if(IF(OR(LEFT(B84,3)="SSE",LEFT(B84,3)="ESE",LEFT(B84,3)="SGA",LEFT(B84,3)="SRF",LEFT(B84,3)="SSG",LEFT(B84,3)="SGE"),"SGE")="SGE","SG2024-"&if(counta($J$2:J83)-countifs($J$2:J83,"")+1<=9,"00"&counta($J$2:J83)-countifs($J$2:J83,"")+1,if(counta($J$2:J83)-countifs($J$2:J83,"")+1<=99,"0"&counta($J$2:J83)-countifs($J$2:J83,"")+1,counta($J$2:J83)-countifs($J$2:J83,"")+1)),"")
A85: 45316 | B85: AR670187 | C85: วงศ์วิช ธันยวาท | D85: ช่างเทคนิค | E85: นิติฯ เบลกราเวีย เรสซิเดนซ์ | F85: 45316 | I85: SX-AR2024-010 | J85: =if(IF(OR(LEFT(B85,3)="SSE",LEFT(B85,3)="ESE",LEFT(B85,3)="SGA",LEFT(B85,3)="SRF",LEFT(B85,3)="SSG",LEFT(B85,3)="SGE"),"SGE")="SGE","SG2024-"&if(counta($J$2:J84)-countifs($J$2:J84,"")+1<=9,"00"&counta($J$2:J84)-countifs($J$2:J84,"")+1,if(counta($J$2:J84)-countifs($J$2:J84,"")+1<=99,"0"&counta($J$2:J84)-countifs($J$2:J84,"")+1,counta($J$2:J84)-countifs($J$2:J84,"")+1)),"")
A86: 45323 | B86: AR670133 | C86: พัชรพงษ์ ดีโท | D86: ช่างเทคนิค | E86: นิติฯ พลัมคอนโด รังสิต อไลฟ์ 2 | F86: 45323 | I86: SX-AR2024-011 | J86: =if(IF(OR(LEFT(B86,3)="SSE",LEFT(B86,3)="ESE",LEFT(B86,3)="SGA",LEFT(B86,3)="SRF",LEFT(B86,3)="SSG",LEFT(B86,3)="SGE"),"SGE")="SGE","SG2024-"&if(counta($J$2:J85)-countifs($J$2:J85,"")+1<=9,"00"&counta($J$2:J85)-countifs($J$2:J85,"")+1,if(counta($J$2:J85)-countifs($J$2:J85,"")+1<=99,"0"&counta($J$2:J85)-countifs($J$2:J85,"")+1,counta($J$2:J85)-countifs($J$2:J85,"")+1)),"")
A87: 45323 | B87: AR670141 | C87: พงศธร คำวันดี | D87: ช่างเทคนิค | E87: นิติฯ พลัมคอนโด รังสิต อไลฟ์ 2 | F87: 45323 | I87: SX-AR2024-012 | J87: =if(IF(OR(LEFT(B87,3)="SSE",LEFT(B87,3)="ESE",LEFT(B87,3)="SGA",LEFT(B87,3)="SRF",LEFT(B87,3)="SSG",LEFT(B87,3)="SGE"),"SGE")="SGE","SG2024-"&if(counta($J$2:J86)-countifs($J$2:J86,"")+1<=9,"00"&counta($J$2:J86)-countifs($J$2:J86,"")+1,if(counta($J$2:J86)-countifs($J$2:J86,"")+1<=99,"0"&counta($J$2:J86)-countifs($J$2:J86,"")+1,counta($J$2:J86)-countifs($J$2:J86,"")+1)),"")
A88: 45323 | B88: AR670130 | C88: กิตติ นพตะนา | D88: ช่างเทคนิค | E88: นิติฯ พลัมคอนโด รังสิต อไลฟ์ 2 | F88: 45323 | I88: SX-AR2024-013 | J88: =if(IF(OR(LEFT(B88,3)="SSE",LEFT(B88,3)="ESE",LEFT(B88,3)="SGA",LEFT(B88,3)="SRF",LEFT(B88,3)="SSG",LEFT(B88,3)="SGE"),"SGE")="SGE","SG2024-"&if(counta($J$2:J87)-countifs($J$2:J87,"")+1<=9,"00"&counta($J$2:J87)-countifs($J$2:J87,"")+1,if(counta($J$2:J87)-countifs($J$2:J87,"")+1<=99,"0"&counta($J$2:J87)-countifs($J$2:J87,"")+1,counta($J$2:J87)-countifs($J$2:J87,"")+1)),"")
A89: 45330 | B89: AR670156 | C89: อนันต์ หมัดสะและห์ | D89: ผู้ช่วยช่างอาคาร | E89: นิติฯ แมเนอร์ สนามบินน้ำ | F89: 45330 | I89: SX-AR2024-015 | J89: =if(IF(OR(LEFT(B89,3)="SSE",LEFT(B89,3)="ESE",LEFT(B89,3)="SGA",LEFT(B89,3)="SRF",LEFT(B89,3)="SSG",LEFT(B89,3)="SGE"),"SGE")="SGE","SG2024-"&if(counta($J$2:J88)-countifs($J$2:J88,"")+1<=9,"00"&counta($J$2:J88)-countifs($J$2:J88,"")+1,if(counta($J$2:J88)-countifs($J$2:J88,"")+1<=99,"0"&counta($J$2:J88)-countifs($J$2:J88,"")+1,counta($J$2:J88)-countifs($J$2:J88,"")+1)),"")
A90: 45329 | B90: AR670119 | C90: เอกนรินทร์ ศรีศักดิ์นอก | D90: ช่างเทคนิค | E90: นิติฯ พลัมคอนโด รามคำแหง 60 สเตชั่น | F90: 45329 | I90: SX-AR2024-016 | J90: =if(IF(OR(LEFT(B90,3)="SSE",LEFT(B90,3)="ESE",LEFT(B90,3)="SGA",LEFT(B90,3)="SRF",LEFT(B90,3)="SSG",LEFT(B90,3)="SGE"),"SGE")="SGE","SG2024-"&if(counta($J$2:J89)-countifs($J$2:J89,"")+1<=9,"00"&counta($J$2:J89)-countifs($J$2:J89,"")+1,if(counta($J$2:J89)-countifs($J$2:J89,"")+1<=99,"0"&counta($J$2:J89)-countifs($J$2:J89,"")+1,counta($J$2:J89)-countifs($J$2:J89,"")+1)),"")
... A119: 45338 | B119: AU670036 | C119: อรพรรณ เอี่ยมสอาด | D119: 7403 เจ้าหน้าที่ขาย | E119: แผนกขายโครงการ | F119: 45338 | I119: SX-AU2024-005 | J119: =if(IF(OR(LEFT(B119,3)="SSE",LEFT(B119,3)="ESE",LEFT(B119,3)="SGA",LEFT(B119,3)="SRF",LEFT(B119,3)="SSG",LEFT(B119,3)="SGE"),"SGE")="SGE","SG2024-"&if(counta($J$2:J118)-countifs($J$2:J118,"")+1<=9,"00"&counta($J$2:J118)-countifs($J$2:J118,"")+1,if(counta($J$2:J118)-countifs($J$2:J118,"")+1<=99,"0"&counta($J$2:J118)-countifs($J$2:J118,"")+1,counta($J$2:J118)-countifs($J$2:J118,"")+1)),"")
A120: 45413 | B120: MMS660129 | C120: น.ส.วรางคณา ศรีวัฒนกุล | D120: 7401 เจ้าหน้าที่ขายและสินเชื่อ | E120: ปีติ สุขุมวิท 101 | F120: 45413 | H120: SD-2024-003 | J120: =if(IF(OR(LEFT(B120,3)="SSE",LEFT(B120,3)="ESE",LEFT(B120,3)="SGA",LEFT(B120,3)="SRF",LEFT(B120,3)="SSG",LEFT(B120,3)="SGE"),"SGE")="SGE","SG2024-"&if(counta($J$2:J119)-countifs($J$2:J119,"")+1<=9,"00"&counta($J$2:J119)-countifs($J$2:J119,"")+1,if(counta($J$2:J119)-countifs($J$2:J119,"")+1<=99,"0"&counta($J$2:J119)-countifs($J$2:J119,"")+1,counta($J$2:J119)-countifs($J$2:J119,"")+1)),"")
A121: 45413 | B121: MMS660364 | C121: นายอาทิตย์ สนธิกุล | D121: 5501 วิศวกรสนาม | E121: เสนา เวล่า รามอินทรา | F121: 45413 | H121: SD-2024-004 | J121: =if(IF(OR(LEFT(B121,3)="SSE",LEFT(B121,3)="ESE",LEFT(B121,3)="SGA",LEFT(B121,3)="SRF",LEFT(B121,3)="SSG",LEFT(B121,3)="SGE"),"SGE")="SGE","SG2024-"&if(counta($J$2:J120)-countifs($J$2:J120,"")+1<=9,"00"&counta($J$2:J120)-countifs($J$2:J120,"")+1,if(counta($J$2:J120)-countifs($J$2:J120,"")+1<=99,"0"&counta($J$2:J120)-countifs($J$2:J120,"")+1,counta($J$2:J120)-countifs($J$2:J120,"")+1)),"")
A122: 45414 | B122: SX670059 | C122: นายชินดนัย ภู่บุญ | D122: 5501 วิศวกรสนาม | E122: 5301020501 ส่วนเสนา วีว่า ศรีราชา - อัสสัมชัญ | F122: 45414 | I122: SX-2024-008 | J122: =if(IF(OR(LEFT(B122,3)="SSE",LEFT(B122,3)="ESE",LEFT(B122,3)="SGA",LEFT(B122,3)="SRF",LEFT(B122,3)="SSG",LEFT(B122,3)="SGE"),"SGE")="SGE","SG2024-"&if(counta($J$2:J121)-countifs($J$2:J121,"")+1<=9,"00"&counta($J$2:J121)-countifs($J$2:J121,"")+1,if(counta($J$2:J121)-countifs($J$2:J121,"")+1<=99,"0"&counta($J$2:J121)-countifs($J$2:J121,"")+1,counta($J$2:J121)-countifs($J$2:J121,"")+1)),"")
A123: 45413 | B123: SX660009 | C123: นายพิชิตพล ตนานนท์ | D123: 23 ผู้อำนวยการ | E123: แผนกการตลาดโครงการปีติ 101 | F123: 45413 | I123: SX-2024-014 | J123: =if(IF(OR(LEFT(B123,3)="SSE",LEFT(B123,3)="ESE",LEFT(B123,3)="SGA",LEFT(B123,3)="SRF",LEFT(B123,3)="SSG",LEFT(B123,3)="SGE"),"SGE")="SGE","SG2024-"&if(counta($J$2:J122)-countifs($J$2:J122,"")+1<=9,"00"&counta($J$2:J122)-countifs($J$2:J122,"")+1,if(counta($J$2:J122)-countifs($J$2:J122,"")+1<=99,"0"&counta($J$2:J122)-countifs($J$2:J122,"")+1,counta($J$2:J122)-countifs($J$2:J122,"")+1)),"")
A124: 45414 | B124: SX670101 | C124: นางสาวเมธิยา ตันติ๊บ | D124: 7401 เจ้าหน้าที่ขายและสินเชื่อ | E124: แผนกการขายโซนศรีราชา - บ่อวิน | F124: 45414 | I124: SX-2024-015 | J124: =if(IF(OR(LEFT(B124,3)="SSE",LEFT(B124,3)="ESE",LEFT(B124,3)="SGA",LEFT(B124,3)="SRF",LEFT(B124,3)="SSG",LEFT(B124,3)="SGE"),"SGE")="SGE","SG2024-"&if(counta($J$2:J123)-countifs($J$2:J123,"")+1<=9,"00"&counta($J$2:J123)-countifs($J$2:J123,"")+1,if(counta($J$2:J123)-countifs($J$2:J123,"")+1<=99,"0"&counta($J$2:J123)-countifs($J$2:J123,"")+1,counta($J$2:J123)-countifs($J$2:J123,"")+1)),"")
A125: 45414 | B125: SX670114 | C125: นายทรงสิทธิ์ เวธิตะ | D125: 7401 เจ้าหน้าที่ขายและสินเชื่อ | E125: แผนกการขายโซนวงแหวน - บางบัวทอง | F125: 45414 | I125: SX-2024-016 | J125: =if(IF(OR(LEFT(B125,3)="SSE",LEFT(B125,3)="ESE",LEFT(B125,3)="SGA",LEFT(B125,3)="SRF",LEFT(B125,3)="SSG",LEFT(B125,3)="SGE"),"SGE")="SGE","SG2024-"&if(counta($J$2:J124)-countifs($J$2:J124,"")+1<=9,"00"&counta($J$2:J124)-countifs($J$2:J124,"")+1,if(counta($J$2:J124)-countifs($J$2:J124,"")+1<=99,"0"&counta($J$2:J124)-countifs($J$2:J124,"")+1,counta($J$2:J124)-countifs($J$2:J124,"")+1)),"")
A126: 45415 | B126: JSA670004 | C126: นางสาวสุภาพร มิ่งสำพาง | D126: 7154 เจ้าหน้าที่ลูกค้าสัมพันธ์ | E126: แผนกบริหารอาคารศูนย์การค้าเสนาเฟสท์ | F126: 45415 | I126: SX-JSA2024-002 | J126: =if(IF(OR(LEFT(B126,3)="SSE",LEFT(B126,3)="ESE",LEFT(B126,3)="SGA",LEFT(B126,3)="SRF",LEFT(B126,3)="SSG",LEFT(B126,3)="SGE"),"SGE")="SGE","SG2024-"&if(counta($J$2:J125)-countifs($J$2:J125,"")+1<=9,"00"&counta($J$2:J125)-countifs($J$2:J125,"")+1,if(counta($J$2:J125)-countifs($J$2:J125,"")+1<=99,"0"&counta($J$2:J125)-countifs($J$2:J125,"")+1,counta($J$2:J125)-countifs($J$2:J125,"")+1)),"")
A127: 45407 | B127: AR670241 | C127: นางสาวฟาริดาห์ เซ็นติยานนท์ | D127: จ้าหน้าที่ธุรการ | E127: โมทีฟ คอนโด | F127: 45407 | I127: SX-AR2024-044 | J127: =if(IF(OR(LEFT(B127,3)="SSE",LEFT(B127,3)="ESE",LEFT(B127,3)="SGA",LEFT(B127,3)="SRF",LEFT(B127,3)="SSG",LEFT(B127,3)="SGE"),"SGE")="SGE","SG2024-"&if(counta($J$2:J126)-countifs($J$2:J126,"")+1<=9,"00"&counta($J$2:J126)-countifs($J$2:J126,"")+1,if(counta($J$2:J126)-countifs($J$2:J126,"")+1<=99,"0"&counta($J$2:J126)-countifs($J$2:J126,"")+1,counta($J$2:J126)-countifs($J$2:J126,"")+1)),"")
A128: 45403 | B128: AR670237 | C128: นายกวิน นันทเดชะ | D128: ช่างเทคนิค | E128: คาซ่า24 | F128: 45403 | I128: SX-AR2024-045 | J128: =if(IF(OR(LEFT(B128,3)="SSE",LEFT(B128,3)="ESE",LEFT(B128,3)="SGA",LEFT(B128,3)="SRF",LEFT(B128,3)="SSG",LEFT(B128,3)="SGE"),"SGE")="SGE","SG2024-"&if(counta($J$2:J127)-countifs($J$2:J127,"")+1<=9,"00"&counta($J$2:J127)-countifs($J$2:J127,"")+1,if(counta($J$2:J127)-countifs($J$2:J127,"")+1<=99,"0"&counta($J$2:J127)-countifs($J$2:J127,"")+1,counta($J$2:J127)-countifs($J$2:J127,"")+1)),"")
...

Sheet รายชื่อพนักงานย้ายสังกัด
E1: สังกัดเดิม | G1: --> | K1: สังกัดใหม่
A2: รหัสพนักงาน | B2: ชื่อ - สกุล | C2: ตำแหน่ง | D2: แผนก | E2: บริษัท | F2: E-Mail | H2: รหัสพนักงาน | I2: ตำแหน่ง | J2: แผนก | K2: บริษัท | L2: E-Mail | M2: วันที่มีผล
A3: SD640001 | B3: นางสาวอุมาพร ธัญลักษณ์ภาคย์ | C3: ผู้อำนวยการอาวุโส | D3: สายงาน SENA IDEA | E3: Sena Idea | F3: Umapornt@senaidea.com | H3: BK680004 | I3: ผู้อำนวยการอาวุโส | J3: สายงาน SENA IDEA | K3: Sena Development | L3: umapornt@sena.co.th
A4: SD650004 | B4: นางสาวมรรษณา แสนคำลือ | C4: เจ้าหน้าที่ประสานงานทั่วไป | D4: สายงาน SENA IDEA | E4: Sena Idea | F4: munsanas@senaidea.com | H4: BK680005 | I4: เจ้าหน้าที่ประสานงานทั่วไป | J4: สายงาน SENA IDEA | K4: Sena Development | L4: munsanas@sena.co.th
A5: SD660014 | B5: นายภาคิไนย จิตติธำรง | C5: ผู้อำนวยการอาวุโส | D5: สายงาน Digital Marketing และ Communications | E5: Sena Idea | F5: pakinain@senaidea.com | H5: BK680006 | I5: ผู้อำนวยการอาวุโส | J5: สายงาน Digital Marketing และ Communications | K5: Sena Development | L5: pakinain@sena.co.th
A6: SD670006 | B6: นางสาวอิพภา พวงหัตถ์ | C6: ผู้จัดการ | D6: ฝ่าย Digital Marketing | E6: Sena Idea | F6: ippap@senaidea.com | H6: BK680007 | I6: ผู้จัดการ | J6: ฝ่าย Digital Marketing | K6: Sena Development | L6: ippap@sena.co.th
A7: SD640021 | B7: นางสาวนัฐธิกา พรประเสริฐผล | C7: ผู้ช่วยหัวหน้าแผนก | D7: แผนก Online Media | E7: Sena Idea | F7: Nuttikap@senaidea.com | H7: BK680008 | I7: ผู้ช่วยหัวหน้าแผนก | J7: แผนก Online Media | K7: Sena Development | L7: nuttikap@sena.co.th
A8: SD640019 | B8: นางสาวสิรรัณดา จุณณะภาต | C8: ผู้ช่วยหัวหน้าแผนก | D8: แผนก Social Media Communication | E8: Sena Idea | F8: Sirarandac@senaidea.com | H8: BK680009 | I8: ผู้ช่วยหัวหน้าแผนก | J8: แผนก Social Media Communication | K8: Sena Development | L8: sirarandac@sena.co.th
A9: SD640017 | B9: นายสุรชัย พัฒเท | C9: ผู้ช่วยหัวหน้าแผนก | D9: แผนก Digital Channel และ MKT Tech | E9: Sena Idea | F9: Surachaip@senaidea.com | H9: BK680010 | I9: ผู้ช่วยหัวหน้าแผนก | J9: แผนก Digital Channel และ MKT Tech | K9: Sena Development | L9: surachaip@sena.co.th
A10: SD650003 | B10: นางสาวพรพรรณ สุทธิมล | C10: เจ้าหน้าที่ออกแบบเว็บไซด์อาวุโส | D10: แผนก Digital Channel และ MKT Tech | E10: Sena Idea | F10: pornpans@senaidea.com | H10: BK680011 | I10: เจ้าหน้าที่ออกแบบเว็บไซด์อาวุโส | J10: แผนก Digital Channel และ MKT Tech | K10: Sena Development | L10: pornpans@sena.co.th
A11: SD660010 | B11: นางสาวรัตนา ธนดำรงสิทธิ์ | C11: เจ้าหน้าที่การตลาดออนไลน์ | D11: แผนก Online Media | E11: Sena Idea | F11: rattanat@senaidea.com | H11: BK680012 | I11: เจ้าหน้าที่การตลาดออนไลน์ | J11: แผนก Online Media | K11: Sena Development | L11: rattanat@sena.co.th
A12: SD670009 | B12: นางสาววริศรา แสงคำ | C12: เจ้าหน้าที่การตลาดออนไลน์ | D12: แผนก Online Media | E12: Sena Idea | F12: warissaras@senaidea.com | H12: BK680013 | I12: เจ้าหน้าที่การตลาดออนไลน์ | J12: แผนก Online Media | K12: Sena Development | L12: warissaras@sena.co.th
A13: SDJ651002 | B13: นางสาวขนิษฐา เมืองนาค | C13: เจ้าหน้าที่การตลาดออนไลน์ | D13: แผนก Online Media | E13: Sena Idea | F13: khanittam@senaidea.com | H13: BK680014 | I13: เจ้าหน้าที่การตลาดออนไลน์ | J13: แผนก Online Media | K13: Sena Development | L13: khanittam@sena.co.th
A14: SD670010 | B14: นางสาวอภิญญา เลิศพงดี | C14: เจ้าหน้าที่ Social Media Content | D14: แผนก Social Media Communication | E14: Sena Idea | F14: apinyal@senaidea.com | H14: BK680015 | I14: เจ้าหน้าที่ Social Media Content | J14: แผนก Social Media Communication | K14: Sena Development | L14: apinyale@sena.co.th
... A44: BK670069 | B44: นางสาวลัดดาวัลย์ ปัดพรม | C44: 6660 เจ้าหน้าที่ประชาสัมพันธ์อาวุโส | D44: แผนกบริการสำนักงาน | E44: Sena Development | F44: Laddawanp@sena.co.th | H44: SX680006 | I44: 6757 เจ้าหน้าที่การเงินอาวุโส | J44: แผนกการเงิน | K44: Sen-X | L44: Laddawanp@senxgroup.com
A45: SX670044 | B45: นางสาวนันทิภา รัตนมาตย์ | C45: 7504 เจ้าหน้าที่ธุรการโครงการ | D45: เสนา วิลเลจ ติวานนท์ - บางกะดี | E45: Sen-X | F45: nuntipar@senxgroup.com | H45: BK680590 | I45: 7504 เจ้าหน้าที่ธุรการโครงการ | J45: เสนาคิทท์ ศรีนครินทร์ - ศรีด่าน | K45: Sena Development | L45: nuntipar@sena.co.th | M45: 45717
A46: SX670037 | B46: นางสาวพิมพ์ผกา วิโรจน์รัญจวน | C46: 5501 วิศวกรสนาม | D46: เสนา เวล่า รังสิต - คลอง 1 | E46: Sen-X | F46: pimpakaw@senxgroup.com | H46: BK680597 | I46: 5556 วิศวกรประมาณราคา | J46: ฝ่ายประมาณราคา และงบประมาณ | K46: Sena Development | L46: pimpakaw@sena.co.th | M46: 45748
A47: SGE660020 | B47: นายสิทธิ รัตนราษี | C47: 25 ผู้ช่วยผู้อำนวยการ | D47: สายงานบริหารทรัพยากรบุคคล | E47: Solarenergy | F47: sittir@senasolarenergy.com | H47: BK680598 | I47: 25 ผู้ช่วยผู้อำนวยการ | J47: สายงานบริหารทรัพยากรบุคคล | K47: Sena Development | L47: sittir@sena.co.th | M47: 45748
A48: BK680129 | B48: นายชัยพจน์ ช่างแต่ง | C48: 34 ผู้จัดการโครงการ | D48: สายงานจัดการระบบคุณภาพ QM | E48: Sena Development | F48: chaiyapotc@sena.co.th | H48: VMS680135 | I48: 33 ผู้จัดการ | J48: ฝ่าย Engineering | K48: Sen-X | L48: chaiyapotc@senxgroup.com | M48: 45662
A49: SSG680002 | B49: นายภูวสิษฏ์ ดอกจันทร์ | C49: 25 ผู้ช่วยผู้อำนวยการ | D49: สายงานติดตั้งและซ่อมบำรุง | E49: Solarenergy | F49: phuwasitd@senasolarenergy.com | H49: VMS680136 | I49: 25 ผู้ช่วยผู้อำนวยการ | J49: สายงาน Engineering | K49: Sen-X | L49: phuwasitd@senxgroup.com | M49: 45662
A50: SPS670030 | B50: นางสาวกัลยาณี ชุติมากุล | C50: 23 ผู้อำนวยการ | D50: สายงานขายคอนโด 2 | E50: Sen-X | F50: kanlayaneec@senxgroup.com | H50: BK680110 | I50: 23 ผู้อำนวยการ | J50: สายงานขายคอนโด 2 | K50: Sena Development | L50: kanlayaneec@sena.co.th | M50: 45658
A51: SPS670029 | B51: นางสาวอรจิรา ปัญญายง | C51: 31.1 ผู้จัดการอาวุโส | D51: นิช ไพร์ด เอกมัย | E51: Sen-X | F51: ongirap@senxgroup.com | H51: BK680111 | I51: 31.1 ผู้จัดการอาวุโส | J51: นิช ไพร์ด เอกมัย | K51: Sena Development | L51: ongirap@sena.co.th | M51: 45658 | N51: รบกวนใส่วันที่มีผลด้วยนะครับ เนื่องจากจะมีการส่ง Email แจ้งผู้ใหญ่ครับ
A52: SPS670037 | B52: นายภาณุพงศ น้อยดอนไพร | C52: 36 ผู้ช่วยผู้จัดการ | D52: นิช ไพร์ด เอกมัย | E52: Sen-X | F52: panupongn@senxgroup.com | H52: BK680112 | I52: 36 ผู้ช่วยผู้จัดการ | J52: นิช ไพร์ด เอกมัย | K52: Sena Development | L52: panupongn@sena.co.th | M52: 45658
A53: SPS670038 | B53: นางสาวธนัชชา ประทยศ | C53: 7401 เจ้าหน้าที่ขายและสินเชื่อ | D53: นิช ไพร์ด เอกมัย | E53: Sen-X | F53: thanatchap@senxgroup.com | H53: BK680113 | I53: 7401 เจ้าหน้าที่ขายและสินเชื่อ | J53: นิช ไพร์ด เอกมัย | K53: Sena Development | L53: thanatchap@sena.co.th | M53: 45658
A54: MMS660138 | B54: นายนพสิทธิ์ เตโช | C54: 23 ผู้อำนวยการ | D54: สำนักบริหารโครงการ 5 (งานก่อสร้าง) | E54: Sena MMS | F54: noppasitt@sena.co.th | H54: SX670046 | I54: 23 ผู้อำนวยการ | J54: สำนักบริหารโครงการคอนโด และบ้าน 1 (ก่อสร้าง) | K54: Sen-X | L54: noppasitt@senxgroup.com | M54: 45298
A55: BK680399 | B55: อำพล ตาเตียว | C55: ผู้ช่วยหัวหน้าแผนก | D55: เสนาคิทท์ รังสิต – คลอง 4 | E55: Sena Development | F55: ampont@sena.co.th | H55: VMS680156 | I55: ผู้ช่วยหัวหน้าแผนก | J55: สำนัักงานใหญ่ | K55: Sen-X | L55: ampont@senxgroup.com | M55: 45809
A56: BK680363 | B56: นางสาวเพ็ญนภา ชุ่มหยวก | C56: 7508 เจ้าหน้าที่สโตร์ | D56: โคซี่ รามฯ 189 สเตชั่น | E56: Sena Development | F56: pennapac@sena.co.th | H56: SGE680001 | I56: 7757 เจ้าหน้าที่การเงิน | J56: สำนัักงานใหญ่ | K56: Solarenergy | L56: pennapac@senasolarenergy.com | M56: 45809
A57: BK670027 | B57: นายภานุวัฒน์ เพชรรุ่งศักดิ์ | C57: 7804 โฟร์แมนบริการหลังการขาย | D57: ฝ่าย Sena We Care | E57: Sena Development | F57: Panuwatp@sena.co.th | H57: TK680004 | I57: 7804 โฟร์แมนบริการหลังการขาย | J57: โครงการ | K57: ทีเค นวกิจ จำกัด | L57: Panuwatp@sena.co.th | M57: 45824
A58: BK680491 | B58: นายสุภาพ ศิริวัฒนกุลวงศ์ | C58: 5505 ผู้ช่วยหัวหน้าโฟร์แมน | D58: เสนา แกรนด์โฮม บางนา กม.29 | E58: Sena Development | F58: Suphaps@sena.co.th | H58: TK680003 | I58: 5505 ผู้ช่วยหัวหน้าโฟร์แมน | J58: โครงการ | K58: ทีเค นวกิจ จำกัด | L58: Suphaps@sena.co.th | M58: 45824
A59: BK680536 | B59: นายพีรพัฒน์ อภัยพิพัฒน์ | C59: 7501 โฟร์แมนควบคุมงาน | D59: เสนา วิลเลจ บางนา - กม.29 | E59: Sena Development | F59: peerapata@sena.co.th | H59: VMS680183 | I59: 8855 ช่างประจำอาคาร | J59: แผนกอาคารชุด เดอะนิช ไพรด์ ทองหล่อ-เพชรบุรี | K59: Sen-X | L59: peerapata@senxgroup.com | M59: 45824
A60: BK680535 | B60: นายพะเยาว์ พุทธสีมา | C60: 7501 โฟร์แมนควบคุมงาน | D60: เสนา วิลเลจ บางนา - กม.29 | E60: Sena Development | F60: payaop@sena.co.th | H60: VMS680184 | I60: 8855 ช่างประจำอาคาร | J60: แผนกอาคารชุด นิช โมโน รามคำแหง | K60: Sen-X | L60: payaop@senxgroup.com | M60: 45824
A61: BK680342 | B61: นายชัยวัฒน์ ทองจำปา | C61: 7501 โฟร์แมนควบคุมงาน | D61: โคซี่ รามอินทรา - คู้บอน | E61: Sena Development | F61: chaiwatt@sena.co.th | H61: VMS680187 | I61: 8855 ช่างประจำอาคาร | J61: แผนกอาคารชุด เดอะคิทท์ พลัส พหลโยธิน-คูคต เฟส 2 | K61: Sen-X | L61: chaiwatt@senxgroup.com | M61: 45664
A62: BK680351 | B62: นายปฐมพงษ์ ด้วงนิล | C62: 7501 โฟร์แมนควบคุมงาน | D62: โคซี่ รามฯ 189 สเตชั่น | E62: Sena Development | F62: pathompongd@sena.co.th | H62: VMS680186 | I62: 8855 ช่างประจำอาคาร | J62: แผนกอาคารชุด เดอะคิทท์ พลัส พหลโยธิน-คูคต เฟส 2 | K62: Sen-X | L62: pathompongd@senxgroup.com | M62: 45664
A63: BK680438 | B63: นายวิเศษศักดิ์ พิลารักษ์ | C63: 7501 โฟร์แมนควบคุมงาน | D63: เสนา วีว่า ฉลองกรุง – ลาดกระบัง | E63: Sena Development | F63: wisetsakp@sena.co.th | H63: VMS680219 | I63: 8855 ช่างประจำอาคาร | J63: แผนกอาคารชุด นิช โมโน รามคำแหง | K63: Sen-X | L63: wisetsakp@senxgroup.com | M63: 45870
... A66: BK650192 | B66: นายชาตรี วงศ์พันธุ์ | C66: 8855 ช่างประจำอาคาร | D66: แผนกอาคารชุด เฟล็กซี่ เตาปูน อินเตอร์เชนจ์ | E66: Sena Development | F66: chatreew@sena.co.th | H66: VMS680307 | I66: 8855 ช่างประจำอาคาร | J66: แผนกวิศวกรรมโยธา | K66: Sen-X | L66: chatreewo@senxgroup.com | M66: 45931
A67: SSG680006 | B67: นายพัทธนันท์ เกตุแก้ว | C67: 7659 เจ้าหน้าที่ประสานงานทั่วไป | D67: ฝ่ายขายและการตลาด | E67: Solarenergy | F67: pattanank@senasolarenergy.com | H67: BK680661 | I67: 7659 เจ้าหน้าที่ประสานงานทั่วไปกลุ่มประธานเจ้าหน้าที่บริหาร | K67: Sena Development | L67: pattanank@sena.co.th | M67: 45962
A68: BK680634 | B68: นางสาวลลิตา ปัญสุวรรณ์ | C68: 7755 เจ้าหน้าที่บัญชีต้นทุน | D68: แผนกบัญชีต้นทุน | E68: Sena Development | F68: lalitap@sena.co.th | H68: SX680023 | I68: 7755 เจ้าหน้าที่บัญชีต้นทุน | J68: แผนกบัญชีต้นทุน | K68: Sen-X | L68: lalitap@senxgroup.com | M68: 45992
A69: VMS680307 | B69: นายชาตรี วงศ์พันธุ์ | C69: 8855 ช่างประจำอาคาร | D69: แผนกวิศวกรรมโยธา | E69: Sen-X | F69: chatreewo@senxgroup.com | H69: BK690014 | I69: 7555 โฟร์แมนตรวจคุณภาพงาน | K69: Sena Development | L69: chatreewo@sena.co.th | M69: 46023
A70: VMS680279 | B70: นายสันติภูมิ พัดทอง | C70: 7855 หัวหน้าช่างประจำอาคาร | D70: แผนกอาคารชุด นิช โมโน รามคำแหง | E70: Sen-X | F70: santiphump@senxgroup.com | H70: BK690013 | I70: 5555 วิศวกรไฟฟ้า | J70: แผนก QC | K70: Sena Development | L70: santiphump@sena.co.th | M70: 46023
A71: VT670001 | B71: นางณัฐชยา อรุณเรืองสวัสดิ์ | C71: 23 ผู้อำนวยการ | D71: สายงานบริหารธุรกิจเช่ารายย่อย (Service Apartment) | E71: เดอะ เซอร์วิส เรสซิเดนซ์ จำกัด | F71: natchayaa@sena.co.th | H71: SPS690002 | I71: 23 ผู้อำนวยการ | J71: สายงานบริหารธุรกิจเช่ารายย่อย (Service Apartment) | K71: Sen-X | L71: natchayaa@senxgroup.com | M71: 46054
A72: VT670007 | B72: นางสาวโสรยา เตชวิทูล | C72: 4971 หัวหน้าแผนกต้อนรับและบริการ | D72: แผนกเสนาเฮ้าส์ ลำลูกกา คลอง 2 | E72: เดอะ เซอร์วิส เรสซิเดนซ์ จำกัด | F72: sorayat@sena.co.th | H72: SPS690003 | I72: 4971 หัวหน้าแผนกต้อนรับและบริการ | J72: แผนกเสนาเฮ้าส์ ลำลูกกา คลอง 2 | K72: Sen-X | L72: sorayat@senxgroup.com | M72: 46054
A73: VT670002 | B73: นายเอกนรินทร์ ทองเงา | C73: 7971 เจ้าหน้าที่ต้อนรับและบริการ | D73: แผนกเสนาเฮ้าส์ สาขาพหลโยธิน 30 | E73: เดอะ เซอร์วิส เรสซิเดนซ์ จำกัด | F73: eaknarint@sena.co.th | H73: SPS690004 | I73: 7971 เจ้าหน้าที่ต้อนรับและบริการ | J73: แผนกเสนาเฮ้าส์ สาขาพหลโยธิน 30 | K73: Sen-X | L73: eaknarint@senxgroup.com | M73: 46054
A74: VT670004 | B74: นางสาวกนกนวรัตน์ มามาตร | C74: 7971 เจ้าหน้าที่ต้อนรับและบริการ | D74: แผนกเสนาเฮ้าส์ สาขาพหลโยธิน 30 | E74: เดอะ เซอร์วิส เรสซิเดนซ์ จำกัด | F74: kanoknawaratm@sena.co.th | H74: SPS690005 | I74: 7971 เจ้าหน้าที่ต้อนรับและบริการ | J74: แผนกเสนาเฮ้าส์ สาขาพหลโยธิน 30 | K74: Sen-X | L74: kanoknawaratm@senxgroup.com | M74: 46054 | O74: คุณโสรยาและคุณสุธาวรรณ ต้องการใช้ Email เดิมเพราะใช้ใในการติดต่อ vender ภายนอก
A75: VT670006 | B75: นางสาวสุธาวรรณ เมฆลอย | C75: 7971 เจ้าหน้าที่ต้อนรับและบริการ | D75: แผนกเสนาเฮ้าส์ ลำลูกกา คลอง 2 | E75: เดอะ เซอร์วิส เรสซิเดนซ์ จำกัด | F75: sutawanm@sena.co.th | H75: SPS690006 | I75: 7971 เจ้าหน้าที่ต้อนรับและบริการ | J75: แผนกเสนาเฮ้าส์ ลำลูกกา คลอง 2 | K75: Sen-X | L75: sutawanm@senxgroup.com | M75: 46054
A76: VT670005 | B76: นางสาวหยาดดาว เรือนปัญจะ | C76: 6504 เจ้าหน้าที่ธุรการโครงการอาวุโส | D76: แผนกเสนาเฮ้าส์ สาขาพหลโยธิน 30 | E76: เดอะ เซอร์วิส เรสซิเดนซ์ จำกัด | F76: yhaddaowr@sena.co.th | H76: SPS690007 | I76: 6504 เจ้าหน้าที่ธุรการโครงการอาวุโส | J76: แผนกเสนาเฮ้าส์ สาขาพหลโยธิน 30 | K76: Sen-X | L76: yhaddaowr@senxgroup.com | M76: 46054
A77: VT670003 | B77: นายใจเพชร ตั้งศักดาดิษฐ์ | C77: 6856 หัวหน้าช่างประจำอาคารอาวุโส | D77: แผนกเสนาเฮ้าส์ สาขาพหลโยธิน 30 | E77: เดอะ เซอร์วิส เรสซิเดนซ์ จำกัด | F77: jaipetcht@sena.co.th | H77: SPS690008 | I77: 6856 หัวหน้าช่างประจำอาคารอาวุโส | J77: แผนกเสนาเฮ้าส์ สาขาพหลโยธิน 30 | K77: Sen-X | L77: jaipetcht@senxgroup.com | M77: 46054
A78: VMS680156 | B78: นายอำพล ตาเตียว | C78: 5101 ผู้ช่วยหัวหน้าแผนก | D78: แผนกวิศวกรรมงานระบบ | E78: Sen-X | F78: ampont@senxgroup.com | H78: BK690023 | I78: 5555 วิศวกรไฟฟ้า | J78: เสนา คิทท์ เทพารักษ์ - บางบ่อ 2 | K78: Sena Development | L78: ampont@sena.co.th | M78: 46054
A79: BK650064 | B79: นางสาวศิลาพร ชลคงคา | C79: 6352 เจ้าหน้าที่ประสานงานโครงการอาวุโส | D79: แผนก Project Support | E79: Sena Development | F79: silapornc@sena.co.th | H79: SSG690003 | I79: 6352 เจ้าหน้าที่ประสานงานโครงการอาวุโส | J79: แผนกบริการลูกค้า | K79: Solarenergy | L79: silapornc@senasolarenergy.com | M79: 46143
A80: BK680318 | B80: นายวุฒิชัย ยิ่งยงค์ | C80: 5555 วิศวกรไฟฟ้า | D80: เฟล็กซี่ สุขสวัสดิ์ | E80: Sena Development | F80: Wutthichaiy@sena.co.th | H80: SSG690004 | I80: 5555 วิศวกรไฟฟ้า | J80: ฝ่ายติดตั้ง | K80: Solarenergy | L80: wutthichaiy@senasolarenergy.com | M80: 46143
A81: SX690005 | B81: นายโกวิท รอรั้ง | C81: 33 ผู้จัดการ | D81: ฝ่าย Graphic Design | E81: Sen-X | F81: kowitr@senxgroup.com | H81: BK690046 | I81: 33 ผู้จัดการ | J81: ฝ่าย Creative และ Design Management | K81: Sena Development | L81: kowitr@sena.co.th | M81: 46143

Sheet พนักงานลาออกพ้นสภาพ(2567-2568)
A1: ลำดับ | B1: รหัสพนักงาน | C1: ชื่อ - สกุล | D1: ตำแหน่ง | E1: แผนก | F1: E-Mail | G1: ทำงานวันสุดท้าย ( ปี-เดือน-วัน ) | H1: วันที่พ้นสภาพ ( ปี-เดือน-วัน ) | I1: สถานะการลาออก/พ้นสภาพ | J1: สถานะการตรวจสอบเอกสาร | K1: สถานะการปิดลาออกจาก HR Online | L1: ปัจจัยการลาออก (For Report) | M1: เหตุผลการลาออก | N1: ลบข้อมูล Email | O1: ลบข้อมูลระบบ REM | P1: ลบข้อมูลระบบ CMS
A2: 1 | B2: MMS660105 | C2: นายธีระชัย ทาทอง | D2: 4501 วิศวกรโครงการ | E2: เสนา คิทท์ บางนา กม.29 | F2: theerachait@sena.co.th | G2: 45291 | H2: 45292 | I2: ลาออกไม่ครบ 30 วัน | J2: ยื่น Online | K2: ปิดลาออกแล้ว | L2: ปัจจัยที่ 1 ผลตอบแทนการทำงาน | N2: ลบข้อมูลแล้ว
A3: 2 | B3: MMS650434 | C3: นางสาวสุภารัตน์ กุลทะโสม | D3: 6401 เจ้าหน้าที่ขายและสินเชื่ออาวุโส | E3: นิช โมโน เมกะ สเปซ บางนา | F3: suparatk@sena.co.th | G3: 45291 | H3: 45292 | I3: ลาออก | J3: ยื่น Online | K3: ปิดลาออกแล้ว | N3: ลบข้อมูลแล้ว
A4: 3 | B4: VMS660048 | C4: นางสาวเปมิกา กระแสงแก้ว | D4: 6759 เจ้าหน้าที่บัญชีปิดงบอาวุโส | E4: ฝ่ายบัญชีนิติบุคคล 1 (คอนโด) | F4: paemikak@sena.co.th | G4: 45291 | H4: 45292 | I4: ลาออก | J4: ยื่น Online | K4: ปิดลาออกแล้ว | N4: ลบข้อมูลแล้ว
A5: 4 | B5: SP18660002 | C5: นางสาวหฤทัยรัตน์ ขวัญทอง | D5: 4101 หัวหน้าแผนก | E5: ฝ่ายบัญชีลูกหนี้ (ร่วมทุน) | F5: Haruthairatk@sena.co.th | G5: 45291 | H5: 45292 | I5: ยกเลิกลาออก | J5: ยกเลิกเอกสาร | K5: ยังไม่ปิดลาออก
A6: 5 | B6: VMS660095 | C6: นางนงนุช แสนยาสมุทร์ | D6: 5859 ผู้จัดการอาคาร | E6: นิติบุคคล เฟล็กซี่ สาทร/เจริญนคร เฟส 1 | F6: nongnuchs@sena.co.th | G6: 45291 | H6: 45292 | I6: ลาออก | J6: ยื่น Online | K6: ปิดลาออกแล้ว | N6: ลบข้อมูลแล้ว
A7: 6 | B7: SX660040 | C7: นางสาวสิริวัฒนา วิไลรัตน์ | D7: 4401 หัวหน้างานขายและสินเชื่อ | E7: ได้งานใหม่ | F7: siriwattanaw@senxgroup.com | G7: 45291 | H7: 45292 | I7: ลาออก | J7: ยื่น Online | K7: ปิดลาออกแล้ว | N7: ลบข้อมูลแล้ว
A8: 7 | B8: MMS660255 | C8: นางสาวกฤษณี คลังทรัพย์ | D8: 4401 หัวหน้างานขายและสินเชื่อ | E8: เฟล็กซี่ สำโรง อินเตอร์เชนจ์ | F8: krisneek@sena.co.th | G8: 45291 | H8: 45292 | I8: ลาออก | J8: ยื่น Online | K8: ปิดลาออกแล้ว | N8: ลบข้อมูลแล้ว
A9: 8 | B9: VMS650141 | C9: นางสาวนุศรา มะมิง | D9: 7854 เจ้าหน้าที่นิติบุคคล | E9: นิติบุคคล นิช โมโน รามคำแหง | F9: nusram@sena.co.th | G9: 45291 | H9: 45292 | I9: ลาออก | J9: ยื่น Online | K9: ปิดลาออกแล้ว | N9: ลบข้อมูลแล้ว
A10: 9 | B10: MMS660425 | C10: นางสาวอนันต์ธินี เหมือนท่าไม้ | D10: 7352 เจ้าหน้าที่ประสานงานโครงการ | E10: สำนักบริหารโครงการ 2 | F10: anantineem@sena.co.th | G10: 45291 | H10: 45292 | I10: ลาออกไม่ครบ 30 วัน | J10: ต้นสังกัดแจ้งทางเมล์ | K10: ปิดลาออกแล้ว | N10: ลบข้อมูลแล้ว
A11: 10 | B11: MMS650027 | C11: นางสำรอง ทองประเสริฐ | D11: 8656 แม่บ้านโครงการ | E11: เสนา คิทท์ พหลโยธิน/คูคต | F11: Somrongt@sena.co.th | G11: 45291 | H11: 45292 | I11: เกษียณ | J11: ไม่มีเอกสารให้ตรวจสอบ | K11: ปิดลาออกแล้ว | N11: ลบข้อมูลแล้ว
A12: 11 | B12: BK650033 | C12: นายชูเกียรติ จูมทอง | D12: 18 ผู้ช่วยกรรมการผู้จัดการ | E12: สำนักกฎหมายและนิติกรรมสัญญา | F12: chookiatj@sena.co.th | G12: 45291 | H12: 45292 | I12: ลาออก | J12: ไม่มีเอกสารให้ตรวจสอบ | K12: ปิดลาออกแล้ว | N12: ลบข้อมูลแล้ว
A13: 12 | B13: SX660052 | C13: นางสาวพิศสิณี พงษ์พิทักษ์กุล | D13: 25 ผู้ช่วยผู้อำนวยการ | E13: สายงาน Inter Sale | F13: pitsineep@senxgroup.com | G13: 45291 | H13: 45292 | I13: ลาออก | J13: ยื่น Online | K13: ปิดลาออกแล้ว | N13: ลบข้อมูลแล้ว
A14: 13 | B14: TK660011 | C14: นางสาวอรวรรณ ม่วงศรี | D14: 7804 โฟร์แมนบริการหลังการขาย | E14: แผนกซ่อมบำรุงหลังการขาย | F14: orawanm@sena.co.th | G14: 45291 | H14: 45292 | I14: ปลดออก | J14: ไม่มีเอกสารให้ตรวจสอบ | K14: ปิดลาออกแล้ว | N14: ลบข้อมูลแล้ว
A15: 14 | B15: BK650001 | C15: นายกฤษฏิ์ วัฒนโยธิน | D15: 7551 สถาปนิก | E15: แผนกพัฒนาโครงการแนวราบ | F15: kristiw@sena.co.th | G15: 45296 | H15: 45297 | I15: ลาออก | J15: ส่งเอกสารกลับไปแก้ไข | K15: ปิดลาออกแล้ว | N15: ลบข้อมูลแล้ว
A16: 15 | B16: BK650260 | C16: นายวิทยา รัตนสร้อย | D16: 7451 เจ้าหน้าที่สินเชื่อ | E16: แผนกสินเชื่อ 2 | F16: wittayar@sena.co.th | G16: 45298 | H16: 45299 | I16: ลาออก | J16: ยื่น Online | K16: ปิดลาออกแล้ว | N16: ลบข้อมูลแล้ว
A17: 16 | B17: SX670091 | C17: นางสาวกัญจน์ชญา กิติคู้จึงพัฒนา | D17: 6401 เจ้าหน้าที่ขายและสินเชื่ออาวุโส | E17: เสนา เวล่า สิริโสธร | F17: - | G17: 45299 | H17: 45300 | I17: ปลดออก | J17: ไม่มีเอกสารให้ตรวจสอบ | K17: ปิดลาออกแล้ว | N17: ลบข้อมูลแล้ว
... A34: 33 | B34: AR670187 | C34: วงศ์วิช ธันยวาท | D34: ช่างเทคนิค | E34: นิติฯ เบลกราเวีย เรสซิเดนซ์ | F34: wongwich2547@gmail.com | G34: 45315 | H34: 45316 | I34: ลาออกไม่ครบ 30 วัน | J34: ไม่มีเอกสารให้ตรวจสอบ | K34: ปิดลาออกแล้ว | N34: ลบข้อมูลแล้ว
A35: 34 | B35: AU670034 | C35: นางสาวภัคณภัทร เหมพนม | D35: 7403 เจ้าหน้าที่ขาย | E35: แผนกขายโครงการ | G35: 45296 | H35: 45297 | I35: ลาออก | J35: ได้รับเอกสารแล้ว | K35: ปิดลาออกแล้ว | N35: ลบข้อมูลแล้ว
A36: 35 | B36: AU670038 | C36: นางสาวธนภรณ์ เชิดชู | D36: 7403 เจ้าหน้าที่ขาย | E36: ฝ่ายขายและให้เช่าทั่วไป | F36: tanapron@acuterealty.com | G36: 45316 | H36: 45317 | I36: ลาออก | J36: ได้รับเอกสารแล้ว | K36: ปิดลาออกแล้ว | N36: ลบข้อมูลแล้ว
A37: 36 | B37: MMS660315 | C37: นางสาวเพียงฤทัย พรมศรี | D37: 31 ผู้จัดการอาวุโส | E37: ฝ่ายขายธุรกิจ 22 | F37: phiangruthaip@sena.co.th | G37: 45322 | H37: 45323 | I37: ลาออก | J37: ยื่น Online | K37: ปิดลาออกแล้ว | N37: ลบข้อมูลแล้ว
A38: 37 | B38: MMS660280 | C38: นางสาวสายรุ้ง แม่นวงค์ | D38: 6401 เจ้าหน้าที่ขายและสินเชื่ออาวุโส | E38: เฟล็กซี่ สาทร/เจริญนคร เฟส 1 | F38: sairungm@sena.co.th | G38: 45322 | H38: 45323 | I38: ยกเลิกลาออก | J38: ยกเลิกเอกสาร | K38: ยังไม่ปิดลาออก
A39: 38 | B39: SX670050 | C39: นายธวัช สินสิงห์ | D39: 34 ผู้จัดการโครงการ | E39: ฝ่ายก่อสร้าง 52C | F39: tawats@sena.co.th | G39: 45322 | H39: 45323 | I39: ลาออก | J39: ได้รับเอกสารแล้ว | K39: ปิดลาออกแล้ว | N39: ลบข้อมูลแล้ว
A40: 39 | B40: MMS660335 | C40: นางสาวนฤมล ภูมิสถาน | D40: 5401 ผู้ช่วยหัวหน้างานขาย | E40: เฟล็กซี่ สาทร/เจริญนคร เฟส 1 | F40: naruemonp@sena.co.th | G40: 45322 | H40: 45323 | I40: ลาออก | J40: ยื่น Online | K40: ปิดลาออกแล้ว | N40: ลบข้อมูลแล้ว
A41: 40 | B41: SX670086 | C41: นางสาวมธุรส สุรรัตน์ | D41: 6401 เจ้าหน้าที่ขายและสินเชื่ออาวุโส | E41: เสนา เวล่า สิริโสธร | F41: mathuross@sena.co.th | G41: 45322 | H41: 45323 | I41: ลาออก | J41: ยื่น Online | K41: ปิดลาออกแล้ว | N41: ลบข้อมูลแล้ว
A42: 41 | B42: VMS660037 | C42: นายสุรศักดิ์ ทองบ่อ | D42: 7855 หัวหน้าช่างประจำอาคาร | E42: นิติบุคคล เดอะคิทท์ ฉลองกรุง/ลาดกระบัง | F42: surasakt@sena.co.th | G42: 45322 | H42: 45323 | I42: ลาออก | J42: ยื่น Online | K42: ปิดลาออกแล้ว | N42: ลบข้อมูลแล้ว
A43: 42 | B43: VMS650001 | C43: นายสิทธรัตน์ นุ่มเรือง | D43: 7855 หัวหน้าช่างประจำอาคาร | E43: สายงานบริหารนิติบุคคล | F43: sittaratn@sena.co.th | G43: 45322 | H43: 45323 | I43: ลาออก | J43: ยื่น Online | K43: ปิดลาออกแล้ว | N43: ลบข้อมูลแล้ว
A44: 43 | B44: VMS660046 | C44: นายคมริกรณ์ ธัญมีไชยฉัตร | D44: 7855 หัวหน้าช่างประจำอาคาร | E44: นิติบุคคล คิทท์ ติวานนท์ เฟส 1 | F44: kimrikornt@sena.co.th | G44: 45322 | H44: 45323 | I44: ลาออก | J44: ยื่น Online | K44: ปิดลาออกแล้ว | N44: ลบข้อมูลแล้ว
A45: 44 | B45: MMS660125 | C45: นายภาณุพงษ์ พัวภวเวช | D45: 25 ผู้ช่วยผู้อำนวยการ | E45: สำนักบริหารโครงการ 5 | F45: panupongp@sena.co.th | G45: 45322 | H45: 45323 | I45: ลาออกไม่ครบ 30 วัน | J45: ได้รับเอกสารแล้ว | K45: ปิดลาออกแล้ว | N45: ลบข้อมูลแล้ว
A46: 45 | B46: SX660046 | C46: นายพิสูจน์ สิทธิพรวัฒนากุล | D46: 23 ผู้อำนวยการ | E46: แผนกการขาย | F46: pisuths@senxgroup.com | G46: 45322 | H46: 45323 | I46: ลาออก | J46: ได้รับเอกสารแล้ว | K46: ปิดลาออกแล้ว | N46: ลบข้อมูลแล้ว
A47: 46 | B47: SGA660005 | C47: ว่าที่ ร.ต.เชาวลิต มณีพฤกษ์ | D47: 33 ผู้จัดการ | E47: บริษัท เสนา กรีน ออโตโมทีฟ จำกัด | F47: chaovalitm@sena.co.th | G47: 45322 | H47: 45323 | I47: ลาออก | J47: ได้รับเอกสารแล้ว | K47: ปิดลาออกแล้ว | N47: ลบข้อมูลแล้ว
A48: 47 | B48: MMS660342 | C48: นางสาวจิณัฐตา ทองเดช | D48: 7504 เจ้าหน้าที่ธุรการโครงการ | E48: เสนา วิลล์ บรมราชชนนี สาย 5 | F48: jinattat@sena.co.th | G48: 45322 | H48: 45323 | I48: ลาออกไม่ครบ 30 วัน | J48: ยื่น Online | K48: ปิดลาออกแล้ว | N48: ลบข้อมูลแล้ว
A49: 48 | B49: SD660015 | C49: นางสาวอาทิตยา คุสิตา | D49: 33 ผู้จัดการ | E49: แผนก PR & Media Buy | F49: artitayak@senaidea.com | G49: 45322 | H49: 45323 | I49: ลาออกไม่ครบ 30 วัน | J49: ยื่น Online | K49: ปิดลาออกแล้ว | N49: ลบข้อมูลแล้ว
A50: 49 | B50: SX670089 | C50: นางสาวชณันภัสร์ วิทยมงคลพัชร์ | D50: 7401 เจ้าหน้าที่ขายและสินเชื่อ | E50: เสนา วิลล์ วงแหวน/บางบัวทอง | F50: chananpasw@sena.co.th | G50: 45322 | H50: 45323 | I50: ลาออกไม่ครบ 30 วัน | J50: ยื่น Online | K50: ปิดลาออกแล้ว | N50: ลบข้อมูลแล้ว
A51: 50 | B51: SGA660023 | C51: นางสาวอรวรรณ แสงวัฒนา | D51: 7982 ที่ปรึกษางานด้านการขาย | E51: บริษัท เสนา กรีน ออโตโมทีฟ จำกัด | G51: 45322 | H51: 45323 | I51: ลาออก | J51: ได้รับเอกสารแล้ว | K51: ปิดลาออกแล้ว | N51: ลบข้อมูลแล้ว
A52: 51 | B52: SX670088 | C52: นางสาวรอยพิมพ์ คชาโภชน์ | D52: 6401 เจ้าหน้าที่ขายและสินเชื่ออาวุโส | E52: เสนา วิลล์ วงแหวน/บางบัวทอง | F52: roypimk@sena.co.th | G52: 45326 | H52: 45327 | I52: ลาออกไม่ครบ 30 วัน | J52: ยื่น Online | K52: ปิดลาออกแล้ว | N52: ลบข้อมูลแล้ว
A53: 52 | B53: VMS660040 | C53: นายสมพร ปากดี | D53: 8855 ช่างประจำอาคาร | E53: นิติบุคคล เดอะคิทท์ ฉลองกรุง/ลาดกระบัง | F53: sompronp@sena.co.th | G53: 45327 | H53: 45328 | I53: ลาออกไม่ครบ 30 วัน | J53: ยื่น Online | K53: ปิดลาออกแล้ว | N53: ลบข้อมูลแล้ว
A54: 53 | B54: SX670070 | C54: นางสาวจัสมิน วิศิษฐสงคราม | D54: 7401 เจ้าหน้าที่ขายและสินเชื่อ | E54: เสนา วีว่า ศรีราชา/อัสสัมชัญ | F54: jasminev@sena.co.th | G54: 45330 | H54: 45331 | I54: ลาออกไม่ครบ 30 วัน | J54: ยื่น Online | K54: ปิดลาออกแล้ว | N54: ลบข้อมูลแล้ว
A55: 54 | B55: MMS670030 | C55: นางสาวจุฑามาศ มะกล่ำทอง | D55: 7352 เจ้าหน้าที่ประสานงานโครงการ | E55: สำนักบริหารโครงการ 2 (ก่อสร้าง) | G55: 45330 | H55: 45331 | I55: ปลดออก | J55: ไม่มีเอกสารให้ตรวจสอบ | K55: ปิดลาออกแล้ว | N55: ลบข้อมูลแล้ว
A56: 55 | B56: MMS660056 | C56: นายเอกรัตน์ แก้วศรี | D56: 7502 ช่างสำรวจ | E56: เสนา เวล่า เทพารักษ์/บางบ่อ | F56: ekkaratk@sena.co.th | G56: 45333 | H56: 45334 | I56: ลาออก | J56: ยื่น Online | K56: ปิดลาออกแล้ว | N56: ลบข้อมูลแล้ว
A57: 56 | B57: MMS650243 | C57: นางสาวพนมมาศ ราชพรรณา | D57: 6352 เจ้าหน้าที่ประสานงานโครงการอาวุโส | E57: สำนักบริหารโครงการ 2 | F57: Panommasr@sena.co.th | G57: 45333 | H57: 45334 | I57: ลาออกไม่ครบ 30 วัน | J57: ยื่น Online | K57: ปิดลาออกแล้ว | N57: ลบข้อมูลแล้ว
A58: 57 | B58: MMS660407 | C58: นางสาวชิณณปะภา ปิ่นประภากุล | D58: 4401 หัวหน้างานขายและสินเชื่อ | E58: สำนักบริหารโครงการ 1 (งานขายและการตลาด) | G58: 45334 | H58: 45335 | I58: ยกเลิกลาออก | J58: ยกเลิกเอกสาร | K58: ยังไม่ปิดลาออก
A59: 58 | B59: VMS660123 | C59: นายโชติพัฒน์ งามเนตร | D59: 8855 ช่างประจำอาคาร | E59: นิติบุคคล นิช ไอดี แอท ปากเกร็ด สเตชั่น | F59: chotipatn@sena.co.th | G59: 45334 | H59: 45335 | I59: ลาออกไม่ครบ 30 วัน | J59: ยื่น Online | K59: ปิดลาออกแล้ว | N59: ลบข้อมูลแล้ว
A60: 59 | B60: MMS660405 | C60: นางสาวจุรีรัตน์ พันเดช | D60: 7401 เจ้าหน้าที่ขายและสินเชื่อ | E60: โคซี่ เอ็มอาร์ที เพชรเกษม 48 | F60: jureeratp@sena.co.th | G60: 45334 | H60: 45335 | I60: ลาออกไม่ครบ 30 วัน | J60: ไม่มีเอกสารให้ตรวจสอบ | K60: ปิดลาออกแล้ว | N60: ลบข้อมูลแล้ว
A61: 60 | B61: MMS660079 | C61: นายปฏิพัทธ์ เมฆมูสิก | D61: 5501 วิศวกรสนาม | E61: เสนา คิทท์ พหลโยธิน/นวนคร | F61: patiphatm@sena.co.th | G61: 45337 | H61: 45338 | I61: ลาออก | J61: ยื่น Online | K61: ปิดลาออกแล้ว | N61: ลบข้อมูลแล้ว
A62: 61 | B62: MMS660301 | C62: นายปพน พิสิฐไพศาลกุล | D62: 7401 เจ้าหน้าที่ขายและสินเชื่อ | E62: เสนาคิทท์ ฉลองกรุง/ลาดกระบัง | F62: paponp@sena.co.th | G62: 45337 | H62: 45338 | I62: ลาออกไม่ครบ 30 วัน | J62: ยื่น Online | K62: ปิดลาออกแล้ว | N62: ลบข้อมูลแล้ว
A63: 62 | B63: VMS660002 | C63: นายวัตรธิชัย ดุลฮีม | D63: 8855 ช่างประจำอาคาร | E63: นิติบุคคล เสนาคิทท์ MRT/บางแค | F63: wattichaid@sena.co.th | G63: 45341 | H63: 45342 | I63: ลาออก | J63: ยื่น Online | K63: ปิดลาออกแล้ว | N63: ลบข้อมูลแล้ว
A64: 63 | B64: AR670133 | C64: พัชรพงษ์ ดีโท | D64: ช่างเทคนิค | E64: นิติฯ พลัมคอนโด รังสิต อไลฟ์ 2 | F64: patcharanon61@gmail.com | G64: 45322 | H64: 45323 | I64: ลาออก | J64: ได้รับเอกสารแล้ว | K64: ปิดลาออกแล้ว | N64: ลบข้อมูลแล้ว
A65: 64 | B65: AR670141 | C65: พงศธร คำวันดี | D65: ช่างเทคนิค | E65: นิติฯ พลัมคอนโด รังสิต อไลฟ์ 2 | F65: Pongsathon5960@gmail.com | G65: 45322 | H65: 45323 | I65: ลาออก | J65: ได้รับเอกสารแล้ว | K65: ปิดลาออกแล้ว | N65: ลบข้อมูลแล้ว
A66: 65 | B66: AR670130 | C66: กิตติ นพตะนา | D66: ช่างเทคนิค | E66: นิติฯ พลัมคอนโด รังสิต อไลฟ์ 2 | F66: kittinoptana@gmail.com | G66: 45322 | H66: 45323 | I66: ลาออก | J66: ได้รับเอกสารแล้ว | K66: ปิดลาออกแล้ว | N66: ลบข้อมูลแล้ว
A67: 66 | B67: AR670077 | C67: กมลวรรณ ปรุงผล | D67: ผู้ช่วยผู้จัดการอาคาร | E67: นิติฯ พลัมคอนโด มิกซ์ แจ้งวัฒนะ | F67: kamonwanprungphon@gmail.com | G67: 45322 | H67: 45323 | I67: ลาออก | K67: ปิดลาออกแล้ว | N67: ลบข้อมูลแล้ว
A68: 67 | B68: AR670156 | C68: อนันต์ หมัดสะและห์ | D68: ผู้ช่วยช่างอาคาร | E68: นิติฯ แมเนอร์ สนามบินน้ำ | F68: nunnavy02@gmail.com | G68: 45329 | H68: 45330 | I68: ลาออกไม่ครบ 30 วัน | J68: ได้รับเอกสารแล้ว | K68: ปิดลาออกแล้ว | N68: ลบข้อมูลแล้ว
A69: 68 | B69: AR670119 | C69: เอกนรินทร์ ศรีศักดิ์นอก | D69: ช่างเทคนิค | E69: นิติฯ พลัมคอนโด รามคำแหง 60 สเตชั่น | F69: kawin0895323636@gmail.com | G69: 45328 | H69: 45329 | I69: ลาออก | J69: ได้รับเอกสารแล้ว | K69: ปิดลาออกแล้ว | N69: ลบข้อมูลแล้ว
A70: 69 | B70: AR670179 | C70: มณีรัตน์ วงศ์ริน | D70: เจ้าหน้าที่ธุรการ | E70: นิติฯ เลทีเซีย | F70: bew.160835@gmail.com | G70: 45332 | H70: 45333 | I70: ลาออก | J70: ได้รับเอกสารแล้ว | K70: ปิดลาออกแล้ว | N70: ลบข้อมูลแล้ว
A71: 70 | B71: AR670061 | C71: กิตติกร ปวงบุผา | D71: ช่างเทคนิค | E71: นิติฯ พลัมคอนโด รังสิต อไลฟ์ 2 | F71: puangbupha_4238@outlook.com | G71: 45333 | H71: 45334 | I71: ลาออก | J71: ได้รับเอกสารแล้ว | K71: ปิดลาออกแล้ว | N71: ลบข้อมูลแล้ว
A72: 71 | B72: AR670208 | C72: ลาภิสลา เจริญสุข | D72: ผู้จัดการอาคาร | E72: นิติฯ เอชทู | F72: parnvarn.r@gmail.com | G72: 45337 | H72: 45338 | I72: ลาออก | J72: ได้รับเอกสารแล้ว | K72: ปิดลาออกแล้ว | N72: ลบข้อมูลแล้ว
A73: 72 | B73: AR670209 | C73: ทรงฉัตร เนาวราช | D73: หัวหน้าช่างเทคนิค | E73: นิติฯ เอชทู | F73: wan1992naowarach@gmail.com | G73: 45337 | H73: 45338 | I73: ลาออก | J73: ได้รับเอกสารแล้ว | K73: ปิดลาออกแล้ว | N73: ลบข้อมูลแล้ว
A74: 73 | B74: AR670169 | C74: ธนายุทธ บุตรมณี | D74: ช่างเทคนิค | E74: นิติฯ ศุภาลัย ซิตี้ รีสอร์ท ระยอง | F74: thanayut200936@gmail.com | G74: 45338 | H74: 45339 | I74: ลาออก | J74: ได้รับเอกสารแล้ว | K74: ปิดลาออกแล้ว | N74: ลบข้อมูลแล้ว
A75: 74 | B75: AR670186 | C75: สันติภาพ ตระการจันทร์ | D75: ช่างเทคนิค | E75: นิติฯ โมทีฟ คอนโด | F75: jason634722@gmail.com | G75: 45338 | H75: 45339 | I75: ลาออกไม่ครบ 30 วัน | J75: ได้รับเอกสารแล้ว | K75: ปิดลาออกแล้ว | N75: ลบข้อมูลแล้ว
A76: 75 | B76: AU670032 | C76: อุมาวดี สัตตัง | D76: 7403 เจ้าหน้าที่ขาย | E76: ฝ่ายขายและให้เช่าทั่วไป | F76: aumawadee@acuterealty.com | G76: 45322 | H76: 45323 | I76: ลาออก | J76: ได้รับเอกสารแล้ว | K76: ปิดลาออกแล้ว | N76: ลบข้อมูลแล้ว
A77: 76 | B77: AU670039 | C77: ขวัญฤทัย แยบไพคำ | D77: 7403 เจ้าหน้าที่ขาย | E77: ฝ่ายขายและให้เช่าทั่วไป | F77: kwanruetai@acuterealty.com | G77: 45334 | H77: 45335 | I77: ลาออก | J77: ได้รับเอกสารแล้ว | K77: ปิดลาออกแล้ว | N77: ลบข้อมูลแล้ว
A78: 77 | B78: AU670036 | C78: อรพรรณ เอี่ยมสอาด | D78: 7403 เจ้าหน้าที่ขาย | E78: แผนกขายโครงการ | G78: 45337 | H78: 45338 | I78: ลาออก | J78: ได้รับเอกสารแล้ว | K78: ปิดลาออกแล้ว | N78: ลบข้อมูลแล้ว
A79: 78 | B79: MMS660203 | C79: นายภัทรสรรพ์ วงศ์นิธิรักษ์ | D79: 23 ผู้อำนวยการ | E79: สายงานก่อสร้าง 42 | F79: phatsanw@sena.co.th | G79: 45351 | H79: 45352 | I79: ลาออกไม่ครบ 30 วัน | J79: ยื่น Online | K79: ปิดลาออกแล้ว | N79: ลบข้อมูลแล้ว
A80: 79 | B80: MMS660395 | C80: นางสาววรรณา สุนทอง | D80: 7401 เจ้าหน้าที่ขายและสินเชื่อ | E80: เสนา คิทท์ เทพารักษ์/บางบ่อ | F80: wannasu@sena.co.th | G80: 45351 | H80: 45352 | I80: ลาออก | J80: ยื่น Online | K80: ปิดลาออกแล้ว | N80: ลบข้อมูลแล้ว
A81: 80 | B81: SX670006 | C81: นายรังสรรค์ ทรงศิลป์ | D81: 23 ผู้อำนวยการ | E81: สายงานก่อสร้าง 51 | F81: rungsuns@sena.co.th | G81: 45351 | H81: 45352 | I81: ลาออก | J81: ไม่มีเอกสารให้ตรวจสอบ | K81: ปิดลาออกแล้ว | N81: ลบข้อมูลแล้ว
A82: 81 | B82: VMS660118 | C82: นายณัฐวุฒิ สุดาโมกข์ | D82: 7854 เจ้าหน้าที่นิติบุคคล | E82: ส่วนงานดูแลอาคาร | F82: nattawats@sena.co.th | G82: 45351 | H82: 45352 | I82: ลาออก | J82: ยื่น Online | K82: ปิดลาออกแล้ว | N82: ลบข้อมูลแล้ว
A83: 82 | B83: MMS660381 | C83: นางสาวพรพรรณ สุเหร็น | D83: 7401 เจ้าหน้าที่ขายและสินเชื่อ | E83: โคซี่ เอ็มอาร์ที เพชรเกษม 48 | F83: pornphans@sena.co.th | G83: 45351 | H83: 45352 | I83: ลาออก | J83: ยื่น Online | K83: ปิดลาออกแล้ว | N83: ลบข้อมูลแล้ว
A84: 83 | B84: BK660069 | C84: นายศรัญย์ แก้วตา | D84: 7451 เจ้าหน้าที่สินเชื่อ | E84: แผนกสินเชื่อ 1 | F84: sarank@sena.co.th | G84: 45351 | H84: 45352 | I84: ลาออก | J84: ยื่น Online | K84: ปิดลาออกแล้ว | N84: ลบข้อมูลแล้ว
A85: 84 | B85: VMS650023 | C85: นายจตุภูมิ สูนศรี | D85: 8855 ช่างประจำอาคาร | E85: ส่วนงานวิศวกรรม | F85: chatuphums@sena.co.th | G85: 45351 | H85: 45352 | I85: ยกเลิกลาออก | J85: ยกเลิกเอกสาร | K85: ยังไม่ปิดลาออก
A86: 85 | B86: SX670077 | C86: นายสุรพล บุตรกระจ่าง | D86: 4402 หัวหน้าการตลาด | E86: ฝ่ายการตลาดธุรกิจ 51B | F86: suraphonb@sena.co.th | G86: 45351 | H86: 45352 | I86: ลาออกไม่ครบ 30 วัน | J86: ยื่น Online | K86: ปิดลาออกแล้ว | N86: ลบข้อมูลแล้ว
A87: 86 | B87: SGA660028 | C87: นางสาวสุจิตรา พรหมเดช | D87: 7353 เจ้าหน้าที่ประสานงานขายและการตลาด | E87: บริษัท เสนา กรีน ออโตโมทีฟ จำกัด | F87: sujitrap@sena.co.th | G87: 45351 | H87: 45352 | I87: ลาออกไม่ครบ 30 วัน | J87: ยื่น Online | K87: ปิดลาออกแล้ว | N87: ลบข้อมูลแล้ว
A88: 87 | B88: MMS660386 | C88: นางสาวณภัค แพงศรี | D88: 7401 เจ้าหน้าที่ขายและสินเชื่อ | E88: เสนา วิลเลจ บางนา กม.29 | F88: naphakp@sena.co.th | G88: 45351 | H88: 45352 | I88: ลาออกไม่ครบ 30 วัน | J88: ยื่น Online | K88: ปิดลาออกแล้ว | N88: ลบข้อมูลแล้ว
A89: 88 | B89: MMS660302 | C89: นางภนิชษากุญ ชนะชัยวิบูลวัฒน์ | D89: 6401 เจ้าหน้าที่ขายและสินเชื่ออาวุโส | E89: เสนา แกรนด์โฮม บางนา กม.29 | F89: phanichsakulc@sena.co.th | G89: 45351 | H89: 45352 | I89: ลาออกไม่ครบ 30 วัน | J89: ยื่น Online | K89: ปิดลาออกแล้ว | N89: ลบข้อมูลแล้ว
A90: 89 | B90: SGA670001 | C90: นายวีรภัทร แซ่โง้ว | D90: 8981 ช่างยนต์ | E90: บริษัท เสนา กรีน ออโตโมทีฟ จำกัด | F90: wirapats@sena.co.th | G90: 45351 | H90: 45352 | I90: ลาออกไม่ครบ 30 วัน | J90: ยื่น Online | K90: ปิดลาออกแล้ว | N90: ลบข้อมูลแล้ว
A91: 90 | B91: BK660105 | C91: นางสาวกฤติยา พวงปัญญา | D91: 7759 เจ้าหน้าที่บัญชีปิดงบ | E91: แผนกบัญชีต้นทุน | F91: kittiyap@sena.co.th | G91: 45351 | H91: 45352 | I91: ลาออกไม่ครบ 30 วัน | J91: ได้รับเอกสารแล้ว | K91: ปิดลาออกแล้ว | N91: ลบข้อมูลแล้ว
A92: 91 | B92: SGA660019 | C92: นางสาวอิ่มทิพย์ ประเสริฐกุล | D92: 7982 ที่ปรึกษางานด้านการขาย | E92: บริษัท เสนา กรีน ออโตโมทีฟ จำกัด | F92: imthipp@sena.co.th | G92: 45351 | H92: 45352 | I92: ลาออกไม่ครบ 30 วัน | J92: ได้รับเอกสารแล้ว | K92: ปิดลาออกแล้ว | N92: ลบข้อมูลแล้ว
A93: 92 | B93: BK660151 | C93: นายอนุศร สุวรรณขำ | D93: 8658 พนักงานขับรถผู้บริหาร | E93: แผนกยานพาหนะ | F93: anusorns@sena.co.th | G93: 45351 | H93: 45352 | I93: ปลดออก | J93: ไม่มีเอกสารให้ตรวจสอบ | K93: ปิดลาออกแล้ว | N93: ลบข้อมูลแล้ว
A94: 93 | B94: MMS670011 | C94: นางสาวนริสรา ช้างสำลี | D94: 6401 เจ้าหน้าที่ขายและสินเชื่ออาวุโส | E94: เสนาคิทท์ รังสิต / ติวานนท์ | F94: narisrac@sena.co.th | G94: 45351 | H94: 45352 | I94: ลาออกไม่ครบ 30 วัน | J94: ไม่มีเอกสารให้ตรวจสอบ | K94: ปิดลาออกแล้ว | N94: ลบข้อมูลแล้ว
A95: 94 | B95: VMS670015 | C95: นางสาวจิรวดี สมสวย | D95: 7854 เจ้าหน้าที่นิติบุคคล | E95: แผนกหมู่บ้านจัดสรร โครงการ บ้านบูรพา พราวทาวน์ บ่อวิน | F95: jirawadees@senxgroup.com | G95: 45351 | H95: 45352 | I95: ลาออกไม่ครบ 30 วัน | J95: ไม่มีเอกสารให้ตรวจสอบ | K95: ปิดลาออกแล้ว | N95: ลบข้อมูลแล้ว
A96: 95 | B96: ELR670002 | C96: ชยากร เอกสินเสริม | D96: 7855 หัวหน้าช่างประจำอาคาร | E96: แผนกอาคารชุด ปีติ สุขุมวิท 101 | F96: chayakora@senxgroup.com | G96: 45351 | H96: 45352 | I96: ลาออกไม่ครบ 30 วัน | J96: ได้รับเอกสารแล้ว | K96: ปิดลาออกแล้ว | N96: ลบข้อมูลแล้ว
A97: 96 | B97: BK660130 | C97: นางสาวปนัดดา ศรีมาตย์ | D97: 7451 เจ้าหน้าที่สินเชื่อ | E97: แผนกสนับสนุนงาน 1 | F97: panaddas@sena.co.th | G97: 45351 | H97: 45352 | I97: ลาออกไม่ครบ 30 วัน | J97: ได้รับเอกสารแล้ว | K97: ปิดลาออกแล้ว | N97: ลบข้อมูลแล้ว
... A117: 116 | B117: VMS650135 | C117: นายพุฒ กกกลิ่น | D117: 8855 ช่างประจำอาคาร | E117: แผนกอาคารชุด นิช ไพรด์ เตาปูน/อินเตอร์เชนจ์ | F117: putk@sena.co.th | G117: 45379 | H117: 45380 | I117: ลาออก | J117: ได้รับเอกสารแล้ว | K117: ปิดลาออกแล้ว | N117: ลบข้อมูลแล้ว
A118: 117 | B118: AR670194 | C118: มานพ แก้วเนตร | D118: ช่างเทคนิค | E118: นิติฯ เดอะซีเครซ หัวหิน | G118: 45380 | H118: 45352 | I118: ลาออก | J118: ได้รับเอกสารแล้ว | K118: ปิดลาออกแล้ว | N118: ลบข้อมูลแล้ว
A119: 118 | B119: AR670168 | C119: จินดามาศ ต่ายเทศ | D119: เจ้าหน้าที่อาคาร | E119: นิติฯ แมเนอร์ สนามบินน้ำ | F119: beejada5284@gmail.com | G119: 45380 | H119: 45352 | I119: ลาออก | J119: ได้รับเอกสารแล้ว | K119: ปิดลาออกแล้ว | N119: ลบข้อมูลแล้ว
A120: 119 | B120: AR670110 | C120: สารัช ศรีบูรณ์ | D120: ช่างเทคนิค | E120: นิติฯ ศุภาลัย มอนเต้ 1 | F120: Nutno1993@gmail.com | G120: 45380 | H120: 45352 | I120: ลาออกไม่ครบ 30 วัน | J120: ได้รับเอกสารแล้ว | K120: ปิดลาออกแล้ว | N120: ลบข้อมูลแล้ว
A121: 120 | B121: AR670215 | C121: ภาคิไนย ชัยสุวยรรณ์ | D121: ผู้จัดการหมู่บ้าน | E121: หมู่บ้านจัดสรรศุภาลัย มณฑลา ปิ่นเกล้า/พุทธมณฑลสาย 1 | F121: Phakinaichaisawan@gmail.com | G121: 45380 | H121: 45352 | I121: ลาออกไม่ครบ 30 วัน | J121: ได้รับเอกสารแล้ว | K121: ปิดลาออกแล้ว | N121: ลบข้อมูลแล้ว
A122: 121 | B122: AR670074 | C122: วิษณุ คงยิ้ม | D122: ช่างเทคนิค | E122: นิติฯ เลทีเซีย | F122: witsanukam1137@gmail.com | G122: 45352 | H122: 45353 | I122: ลาออกไม่ครบ 30 วัน | J122: ได้รับเอกสารแล้ว | K122: ปิดลาออกแล้ว | N122: ลบข้อมูลแล้ว
A123: 122 | B123: AR670214 | C123: มนัส ดีขาย | D123: ช่างเทคนิค | E123: นิติฯ แมเนอร์ สนามบินน้ำ | F123: manatdeekay9@gmail.com | G123: 45354 | H123: 45355 | I123: ลาออกไม่ครบ 30 วัน | J123: ไม่มีเอกสารให้ตรวจสอบ | K123: ปิดลาออกแล้ว | N123: ลบข้อมูลแล้ว
A124: 123 | B124: AR670212 | C124: พนิตา มารศรี | D124: เจ้าหน้าที่ธุรการ | E124: นิติฯ ศุภาลัย ซิตี้ รีสอร์ท ระยอง | F124: Panitamarasri@hotmail.com | G124: 45355 | H124: 45356 | I124: ลาออกไม่ครบ 30 วัน | J124: ได้รับเอกสารแล้ว | K124: ปิดลาออกแล้ว | N124: ลบข้อมูลแล้ว
A125: 124 | B125: AR670148 | C125: วิรัช ติระนิ่ว | D125: ช่างเทคนิค | E125: นิติฯ เดอะทรี อินเตอร์เชนจ์ | F125: joeytvs50@gmail.com | G125: 45365 | H125: 45366 | I125: ลาออกไม่ครบ 30 วัน | J125: ได้รับเอกสารแล้ว | K125: ปิดลาออกแล้ว | N125: ลบข้อมูลแล้ว
A126: 125 | B126: AR670189 | C126: สุพิชฌาย์ วิชัยโย | D126: เจ้าหน้าที่ธุรการการเงิน | E126: นิติฯ แมเนอร์ สนามบินน้ำ | F126: giftsupicha1101@gmail.com | G126: 45366 | H126: 45367 | I126: ลาออก | J126: ได้รับเอกสารแล้ว | K126: ปิดลาออกแล้ว | N126: ลบข้อมูลแล้ว
A127: 126 | B127: AR670203 | C127: ศิวะกร พงศ์ธนัชชานน | D127: ช่างเทคนิค | E127: นิติฯ เลทีเซีย | F127: siwakorn0869736255@gmail.com | G127: 45371 | H127: 45372 | I127: ลาออก | J127: ได้รับเอกสารแล้ว | K127: ปิดลาออกแล้ว | N127: ลบข้อมูลแล้ว
A128: 127 | B128: AR670225 | C128: รักสิทธิ์ วงค์ยอด | D128: ช่างเทคนิค | E128: อาคารชุด มิว | F128: Ruck/sit@hotmail.com | G128: 45379 | H128: 45380 | I128: ลาออกไม่ครบ 30 วัน | J128: ไม่มีเอกสารให้ตรวจสอบ | K128: ปิดลาออกแล้ว | N128: ลบข้อมูลแล้ว
A129: 128 | B129: BK650039 | C129: นางสาวเพ็ญพิชชา แซ่หลี | D129: 7759 เจ้าหน้าที่บัญชีปิดงบ | E129: แผนกบัญชีต้นทุน | F129: penpitchas@sena.co.th | G129: 45382 | H129: 45383 | I129: ลาออก | J129: ได้รับเอกสารแล้ว | K129: ปิดลาออกแล้ว | N129: ลบข้อมูลแล้ว
A130: 129 | B130: VMS660042 | C130: นายนิธิพล คัมภีรพันธ์ | D130: 8855 ช่างประจำอาคาร | E130: แผนกอาคารชุด นิช ไพรด์ เตาปูน/อินเตอร์เชนจ์ | F130: nithiphonk@sena.co.th | G130: 45382 | H130: 45383 | I130: ลาออก | J130: ได้รับเอกสารแล้ว | K130: ปิดลาออกแล้ว | N130: ลบข้อมูลแล้ว
... A159: 158 | B159: BK610009 | C159: นายศุภกร ศรีวิเศษ | D159: 7551 สถาปนิก | E159: แผนก DESIGN DEVELOP | F159: suphakorns@sena.co.th | G159: 45397 | H159: 45398 | I159: ลาออกไม่ครบ 30 วัน | J159: ได้รับเอกสารแล้ว | K159: ปิดลาออกแล้ว | N159: ลบข้อมูลแล้ว
A160: 159 | B160: MMS660219 | C160: นางสาวธนัชภรณ์ พรมวาด | D160: 4401 หัวหน้างานขายและสินเชื่อ | E160: เสนาคิทท์ สาทร/กัลปพฤกษ์ | F160: thanatpornp@sena.co.th | G160: 45397 | H160: 45398 | I160: ยกเลิกลาออก | J160: ยกเลิกเอกสาร | K160: ยังไม่ปิดลาออก
A161: 160 | B161: BK620192 | C161: นางสาวอนุศรา สิงห์สา | D161: 31 ผู้จัดการอาวุโส | E161: ฝ่ายจัดสรรเงินทุน | F161: anusaras@sena.co.th | G161: 45398 | H161: 45399 | I161: ลาออก | J161: ได้รับเอกสารแล้ว | K161: ปิดลาออกแล้ว | N161: ลบข้อมูลแล้ว
A162: 161 | B162: MMS660312 | C162: นางสาวปาลญา อัศวะลาภา | D162: 6401 เจ้าหน้าที่ขายและสินเชื่ออาวุโส | E162: เสนาคิทท์ สาทร/กัลปพฤกษ์ | F162: palayaa@sena.co.th | G162: 45399 | H162: 45400 | I162: ลาออกไม่ครบ 30 วัน | J162: ได้รับเอกสารแล้ว | K162: ปิดลาออกแล้ว | N162: ลบข้อมูลแล้ว
A163: 162 | B163: BK660021 | C163: นายเสกสม จิรวรรณสกุล | D163: 23 ผู้อำนวยการ | E163: สายงานบริหารทรัพยากรบุคคล | F163: seksomj@sena.co.th | G163: 45399 | H163: 45400 | I163: ลาออก | J163: ได้รับเอกสารแล้ว | K163: ปิดลาออกแล้ว | N163: ลบข้อมูลแล้ว
...

Sheet ผู้ใช้งานคอมพิวเตอร์สำนักงานใหญ
G1: Sena ตึก 448
B2: สถานที่ (Site) : อาคารธัญลักษณ์ภาคย์ 448 | C2: Sena Development | D2: Sen-X | G2: ลำดับ | H2: บริษัท | I2: สถานที่ | J2: ชั้น | K2: รหัสพนักงาน | L2: คำนำหน้า (ไทย) | M2: ชื่อ- สกุล (ไทย) | N2: แผนก | O2: PC/NB | P2: Asset Name | Q2: จอ | R2: Asset name
B3: 1 | C3: 2 | G3: 1 | H3: บริษัท เสนาดีเวลลอปเม้นท์ จำกัด (มหาชน) | I3: สถานที่ (Site) : อาคารธัญลักษณ์ภาคย์ (ทรัพย์สินอาคารส่วนกลาง) | J3: 1 | K3: BK620035 | L3: นางสาว | M3: เครือมาศ อินทองปาน | N3: แผนกบริการสำนักงาน | O3: HO0027072C0005 | P3: ชุดคอมพิวเตอร์ All in one
B4: M | C4: 8 | G4: 2 | H4: บริษัท เสนาดีเวลลอปเม้นท์ จำกัด (มหาชน) | I4: สถานที่ (Site) : อาคารธัญลักษณ์ภาคย์ (ทรัพย์สินอาคารส่วนกลาง) | J4: 1 | K4: BK670069 | L4: นางสาว | M4: ลัดดาวัลย์ ปัดพรม | N4: แผนกบริการสำนักงาน | O4: CONHO012C0102 | P4: ชุดคอมพิวเตอร์ CASE (ไม่รวมจอ) | Q4: COMMHO012C0026 | R4: MONITOR LCD 20"
B5: 2 | C5: 41 | D5: 3 | G5: 3 | H5: บริษัท เสนาดีเวลลอปเม้นท์ จำกัด (มหาชน) | I5: สถานที่ (Site) : อาคารธัญลักษณ์ภาคย์ (ฝ่าย IT Support) | J5: 2 | K5: BK650137 | L5: นาย | M5: วรวุฒิ รัตน์นันต์ | N5: สายงานเทคโนโลยีสารสนเทศ | O5: ICTHO012C0444 | P5: NoteBook | Q5: STKICT01000001 | R5: MONITOR LCD 27"
B6: 3 | C6: 56 | G6: 4 | H6: บริษัท เสนาดีเวลลอปเม้นท์ จำกัด (มหาชน) | I6: สถานที่ (Site) : อาคารธัญลักษณ์ภาคย์ (ฝ่ายพัฒนาระบบสารสนเทศ) | J6: 2 | K6: BK650280 | L6: นาย | M6: มลเชียร ทันนาเขตต์ | N6: สายงานเทคโนโลยีสารสนเทศ | O6: HO0007072A0001 | P6: Apple MAC Mini M2 | Q6: HO0007073M0002 | R6: จอคอมพิวเตอร์ FHD HP 27"
B7: 4 | C7: 41 | D7: 1 | G7: 5 | H7: บริษัท เสนาดีเวลลอปเม้นท์ จำกัด (มหาชน) | I7: สถานที่ (Site) : อาคารธัญลักษณ์ภาคย์ (ฝ่าย IT Support) | J7: 2 | K7: BK650136 | L7: นาย | M7: เอกพล ทรัพย์ทวีกานต์ | N7: ฝ่ายพัฒนาระบบสารสนเทศ | O7: HO0033072C0012 | P7: NoteBook | Q7: HO0033073C0057 | R7: จอคอมพิวเตอร์ LED HP 27 นิ้ว
B8: 5 | C8: 35 | D8: 26 | G8: 6 | H8: บริษัท เสนาดีเวลลอปเม้นท์ จำกัด (มหาชน) | I8: สถานที่ (Site) : อาคารธัญลักษณ์ภาคย์ (ฝ่ายพัฒนาระบบสารสนเทศ) | J8: 2 | K8: BK650141 | L8: นาย | M8: สิทธิชัย ดาดาษ | N8: แผนกพัฒนาระบบสารสนเทศ | O8: HO0007072C0038 | P8: Notebook DELL Inspiron 5502 15.6 นิ้ว | Q8: HO2C03021ACC | R8: MONITOR LCD 20"
B9: 6 | C9: 53 | G9: 7 | H9: บริษัท เสนาดีเวลลอปเม้นท์ จำกัด (มหาชน) | I9: สถานที่ (Site) : อาคารธัญลักษณ์ภาคย์ (ฝ่ายพัฒนาระบบสารสนเทศ) | J9: 2 | K9: BK650145 | L9: นาย | M9: วิเชฐ แจ้งดี | N9: ฝ่ายบริหารและสนับสนุนระบบดิจิทัล | O9: CONHO012C0021 | P9: NoteBook | Q9: HO0009072C0014 | R9: MONITOR LCD 27"
B10: 7 | C10: 35 | D10: 1 | G10: 8 | H10: บริษัท เสนาดีเวลลอปเม้นท์ จำกัด (มหาชน) | I10: สถานที่ (Site) : อาคารธัญลักษณ์ภาคย์ (ฝ่าย IT Support) | J10: 2 | K10: BK650143 | L10: นางสาว | M10: รุจิรา น้ำทอง | N10: แผนกบริหารและสนับสนุนระบบดิจิทัล | O10: ICTHO012C0540 | P10: NoteBook | Q10: HO0006073C0004 | R10: จอคอมพิวเตอร์ LED HP 24 นิ้ว
B11: 8 | C11: 40 | G11: 9 | H11: บริษัท เสนาดีเวลลอปเม้นท์ จำกัด (มหาชน) | I11: สถานที่ (Site) : อาคารธัญลักษณ์ภาคย์ (ฝ่ายพัฒนาระบบสารสนเทศ) | J11: 2 | K11: BK650146 | L11: นาย | M11: ธนิสร เย็นประยูรสวัสดิ์ | N11: แผนกบริหารและสนับสนุนระบบดิจิทัล | O11: SALCHANK072C0004 | P11: ชุดคอมพิวเตอร์ CASE (ไม่รวมจอ) | Q11: CONPR2012C0001 | R11: MONITOR LCD 20"
B12: 9 | C12: 70 | G12: 10 | H12: บริษัท เสนาดีเวลลอปเม้นท์ จำกัด (มหาชน) | I12: สถานที่ (Site) : อาคารธัญลักษณ์ภาคย์ (ฝ่ายพัฒนาระบบสารสนเทศ) | J12: 2 | K12: BK650174 | L12: นางสาว | M12: รัชช์ศิร์ บางเจริญพรพงค์ | N12: ฝ่าย Technology และ Analytics | O12: HO0036072N0006 | P12: Notebook DELL Inspiron 3511 15.6" | Q12: HO0007073M0001 | R12: จอคอมพิวเตอร์ FHD HP 27"
B13: 10 | C13: 48 | G13: 11 | H13: บริษัท เสนาดีเวลลอปเม้นท์ จำกัด (มหาชน) | I13: สถานที่ (Site) : อาคารธัญลักษณ์ภาคย์ (ฝ่ายพัฒนาระบบสารสนเทศ) | J13: 2 | K13: BK650283 | L13: นาย | M13: ธนศักดิ์ ซ่อนกลิ่น | N13: ฝ่าย Technology และ Analytics | O13: HO0007072C0039 | P13: Apple MAC Mini M1 | Q13: HO0006073C0005 | R13: จอคอมพิวเตอร์ LED HP 27 นิ้ว
B14: 11 | C14: 12 | G14: 12 | H14: บริษัท เสนาดีเวลลอปเม้นท์ จำกัด (มหาชน) | I14: สถานที่ (Site) : อาคารธัญลักษณ์ภาคย์ (ฝ่ายพัฒนาระบบสารสนเทศ) | J14: 2 | K14: BK650309 | L14: นาย | M14: ณัฐพงศ์ ไหมพรม | N14: ฝ่าย Technology และ Analytics | O14: HO0036072N0044 | P14: Notebook Lenovo ThinkPad E14 Gen2 14" | Q14: HO0007073M0003 | R14: จอคอมพิวเตอร์ FHD HP 27"
B15: 12 | C15: 3 | G15: 13 | H15: บริษัท เสนาดีเวลลอปเม้นท์ จำกัด (มหาชน) | I15: สถานที่ (Site) : อาคารธัญลักษณ์ภาคย์ (ฝ่ายพัฒนาระบบสารสนเทศ) | J15: 2 | K15: BK660107 | L15: นาย | M15: มานิตย์ ศรีคงแก้ว | N15: ฝ่าย Technology และ Analytics | O15: SN:MP2EHAD9 | P15: Notebook Lenovo Thinkbook G3 14" | Q15: SN:9XQD7P3 | R15: จอคอมพิวเตอร์ FHD DELL 27"
B16: รวม | C16: 444 | D16: 31 | G16: 14 | H16: บริษัท เสนาดีเวลลอปเม้นท์ จำกัด (มหาชน) | I16: สถานที่ (Site) : อาคารธัญลักษณ์ภาคย์ (ฝ่ายพัฒนาระบบสารสนเทศ) | J16: 2 | K16: BK660131 | L16: นาย | M16: อดินันท์ อติพิศาลกุล | N16: ฝ่าย Technology และ Analytics | O16: SN:MP2EHW11 | P16: Notebook Lenovo Thinkbook G3 14" | Q16: HO0007073M0004 | R16: จอคอมพิวเตอร์ FHD HP 27"
G17: 15 | H17: บริษัท เสนาดีเวลลอปเม้นท์ จำกัด (มหาชน) | I17: สถานที่ (Site) : อาคารธัญลักษณ์ภาคย์ (ฝ่ายพัฒนาระบบสารสนเทศ) | J17: 2 | K17: BK650139 | L17: นาย | M17: ศุภณัฐ สุขอร่าม | N17: แผนก Technology และ Analytics | O17: SN:PF39GMY4 | P17: Notebook Lenovo V14 GEN2 14" | Q17: CONCKL012C0004 | R17: MONITOR LCD 20"
B18: สถานที่ (Site) : สำนักงานใหญ่ ตึก 522 | C18: Sena Development | D18: Sen-X | G18: 16 | H18: บริษัท เสนาดีเวลลอปเม้นท์ จำกัด (มหาชน) | I18: สถานที่ (Site) : อาคารธัญลักษณ์ภาคย์ (ฝ่ายพัฒนาระบบสารสนเทศ) | J18: 2 | K18: BK660094 | L18: นางสาว | M18: วัชรินทร์ กรพิมาย | N18: แผนก Technology และ Analytics | O18: SN:MP2EJ0P7 | P18: Notebook Lenovo Thinkbook G3 14" | Q18: SN:6M6W3P3 | R18: จอคอมพิวเตอร์ DELL FHD 24"
B19: 1 | C19: 1 | G19: 17 | H19: บริษัท เสนาดีเวลลอปเม้นท์ จำกัด (มหาชน) | I19: สถานที่ (Site) : อาคารธัญลักษณ์ภาคย์ (ฝ่าย IT Support) | J19: 2 | K19: BK650142 | L19: นาย | M19: พลวิทย์ ศรีสุวรรณกุล | N19: ฝ่ายคอมพิวเตอร์ และเครือข่าย | O19: HO0033072C0014 | P19: ชุดคอมพิวเตอร์ Case - ไม่รวมจอ | Q19: HO0033073M0002 | R19: จอคอมพิวเตอร์ FHD SAMSUNG 24"
B20: 2 | C20: 13 | G20: 18 | H20: บริษัท เสนาดีเวลลอปเม้นท์ จำกัด (มหาชน) | I20: สถานที่ (Site) : อาคารธัญลักษณ์ภาคย์ (ฝ่าย IT Support) | J20: 2 | K20: BK650140 | L20: นาย | M20: สุขสันต์ บุตรนามรักษ์ | N20: แผนกคอมพิวเตอร์ และเครือข่าย | O20: CONHO072C0013 | P20: CPU Intel I7-2400 | Q20: HO0098073C0001 | R20: จอคอมพิวเตอร์ ASUS TUF Gaming 24.5 นิ้ว
B21: 3 | C21: 25 | D21: 1 | G21: 19 | H21: บริษัท เสนาดีเวลลอปเม้นท์ จำกัด (มหาชน) | I21: สถานที่ (Site) : อาคารธัญลักษณ์ภาคย์ (ฝ่าย IT Support) | J21: 2 | K21: BK650144 | L21: นาย | M21: วรรณิก สิมาลัย | N21: แผนกคอมพิวเตอร์ และเครือข่าย | O21: HO0033072C0013 | P21: ชุดคอมพิวเตอร์ Case - ไม่รวมจอ | Q21: HO0014073M0002 | R21: จอคอมพิวเตอร์ FHD HP 22"
B22: 4 | C22: 23 | D22: 1 | G22: 20 | H22: บริษัท เสนาดีเวลลอปเม้นท์ จำกัด (มหาชน) | I22: สถานที่ (Site) : อาคารธัญลักษณ์ภาคย์ (ฝ่าย IT Support) | J22: 2 | K22: BK650147 | L22: นาย | M22: ชยพล ศิรินุพงษ์ | N22: แผนกคอมพิวเตอร์ และเครือข่าย | O22: ICTHO072C0003 | P22: ชุดคอมพิวเตอร์ CASE (ไม่รวมจอ) | Q22: HO0022073M0007 | R22: จอคอมพิวเตอร์ LED LG 29"
B23: 5 | C23: 6 | G23: 21 | H23: บริษัท เสนาดีเวลลอปเม้นท์ จำกัด (มหาชน) | I23: สถานที่ (Site) : อาคารธัญลักษณ์ภาคย์ (ฝ่าย IT Support) | J23: 2 | K23: BK650316 | L23: นาย | M23: ปรเมศวร์ กาญจนธวัช | N23: แผนกคอมพิวเตอร์ และเครือข่าย | O23: SALSV50A012C0007 | P23: ชุดคอมพิวเตอร์ CASE (ไม่รวมจอ) | Q23: HO0028073C0008 | R23: จอคอมพิวเตอร์ LED HP 24 นิ้ว
B24: 6 | C24: 12 | D24: 1 | G24: 22 | H24: บริษัท เสนาดีเวลลอปเม้นท์ จำกัด (มหาชน) | I24: สถานที่ (Site) : อาคารธัญลักษณ์ภาคย์ (ฝ่าย IT Support) | J24: 2 | K24: BK660018 | L24: นาย | M24: ชานนท์ ขันอาษา | N24: แผนกคอมพิวเตอร์ และเครือข่าย | O24: HO0013072C0001 | P24: ชุดคอมพิวเตอร์ CASE (ไม่รวมจอ) | Q24: HO2C03027ACC | R24: MONITOR LCD 20"
B25: รวม | C25: 80 | D25: 3 | G25: 23 | H25: บริษัท เสนาดีเวลลอปเม้นท์ จำกัด (มหาชน) | I25: สถานที่ (Site) : อาคารธัญลักษณ์ภาคย์ (ฝ่าย IT Support) | J25: 2 | K25: BK660122 | L25: นาย | M25: จรัส วงษ์โห้ | N25: แผนกคอมพิวเตอร์ และเครือข่าย | O25: SN:FCD0HY3 | P25: ชุดคอมพิวเตอร์ Dell 7010SFF i5-13500 | Q25: SN:C7GNYV3 | R25: จอคอมพิวเตอร์ FHD DELL 24"
G26: 24 | H26: บริษัท เสนาดีเวลลอปเม้นท์ จำกัด (มหาชน) | I26: สถานที่ (Site) : อาคารธัญลักษณ์ภาคย์ (ฝ่าย IT Support) | J26: 2 | K26: BK670049 | L26: นางสาว | M26: ศิริพร ตรีพิพิธ | N26: แผนกคอมพิวเตอร์ และเครือข่าย | O26: LAWHO012C0017 | P26: ชุดคอมพิวเตอร์ CASE (ไม่รวมจอ) | Q26: HO0009072C0015 | R26: MONITOR LCD 22"
B27: สถานที่ (Site) : สำนักงานใหญ่ ตึก 524 | C27: Sena Development | D27: Sen-X | G27: 25 | H27: บริษัท เสนาดีเวลลอปเม้นท์ จำกัด (มหาชน) | I27: สถานที่ (Site) : หน่วยงาน SenX Digital (SenX Digital) | J27: 2 | K27: BK670082 | L27: นาย | M27: พสิษฐ์ เหลืองอำพล | N27: ฝ่าย Digital Platform & Integration | O27: SN:XFKYPXD4DR | P27: Apple Macbook 13.6" M2 Chip/8C CPU
B28: 1 | C28: 13 | G28: 26 | H28: บริษัท เสนาดีเวลลอปเม้นท์ จำกัด (มหาชน) | I28: สถานที่ (Site) : หน่วยงาน SenX Digital (SenX Digital) | J28: 2 | K28: BK670085 | L28: นาย | M28: กานต์ เชาว์วิจิตร | N28: ฝ่าย Digital Platform & Integration | O28: SN:MP2E0NAA | P28: Notebook Lenovo Thinkbook G3 14"
B29: 2 | C29: 8 | G29: 27 | H29: บริษัท เสนาดีเวลลอปเม้นท์ จำกัด (มหาชน) | I29: สถานที่ (Site) : หน่วยงาน SenX Digital (SenX Digital) | J29: 2 | K29: BK670081 | L29: นางสาว | M29: สรัญญา ตั้งโซ๊ะ | N29: แผนก Digital Platform & Integration | O29: SN:MP2ET26N | P29: Notebook Lenovo Thinkbook 15.6"
B30: 3 | C30: 28 | G30: 28 | H30: บริษัท เสนาดีเวลลอปเม้นท์ จำกัด (มหาชน) | I30: สถานที่ (Site) : อาคารธัญลักษณ์ภาคย์ (แผนก Smartify) | J30: 2 | K30: BK670083 | L30: นาย | M30: ทนงศักดิ์ นิราศ | N30: แผนก Digital Platform & Integration | O30: SN:MP2ESVB1 | P30: Notebook Lenovo Thinkbook 15.6"
B31: 4 | C31: 10 | G31: 29 | H31: บริษัท เสนาดีเวลลอปเม้นท์ จำกัด (มหาชน) | I31: สถานที่ (Site) : หน่วยงาน SenX Digital (SenX Digital) | J31: 2 | K31: BK670084 | L31: นาย | M31: ชเนษฎ์ วิชชจุฑากุล | N31: แผนก Digital Platform & Integration | O31: SN:P3KP62F25T | P31: Apple Macbook 13.6" M2 Chip/8C CPU
B32: รวม | C32: 59 | D32: 0 | G32: 30 | H32: บริษัท เสนาดีเวลลอปเม้นท์ จำกัด (มหาชน) | I32: สถานที่ (Site) : อาคารธัญลักษณ์ภาคย์ (ฝ่าย IT Support) | J32: 2 | K32: BK680365 | L32: นาย | M32: ธานินทร์ สีน้ำอ้อม | N32: สายงานบริหารโครงการคอนโดและบ้าน 11 | O32: CONT5072C0001 | P32: Notebook Asus Vivobook 14 นิ้ว
G33: 31 | H33: บริษัท เสนาดีเวลลอปเม้นท์ จำกัด (มหาชน) | I33: สถานที่ (Site) : อาคารธัญลักษณ์ภาคย์ (ฝ่าย IT Support) | J33: 2 | K33: BK680366 | L33: นาย | M33: ปริพัตร ตริตรอง | N33: สายงานบริหารโครงการคอนโดและบ้าน 12 | O33: CONT4072C0001 | P33: Notebook Asus Vivobook 14 นิ้ว
G34: 32 | H34: บริษัท เสนาดีเวลลอปเม้นท์ จำกัด (มหาชน) | I34: สถานที่ (Site) : อาคารธัญลักษณ์ภาคย์ (ฝ่ายพัฒนาระบบสารสนเทศ) | J34: 2 | K34: BK670038 | L34: นาย | M34: อรรถพล เทียนเจริญ | N34: สายงานบริหารทรัพยากรบุคคล | O34: SN:MP2831NN | P34: Notebook Lenovo Thinkbook G3 14"
B35: รวม | C35: 583 | D35: 34 | E35: 617 | G35: 33 | H35: บริษัท เสนาดีเวลลอปเม้นท์ จำกัด (มหาชน) | I35: สถานที่ (Site) : อาคารธัญลักษณ์ภาคย์ (ฝ่ายพัฒนาระบบสารสนเทศ) | J35: 2 | K35: BK650252 | L35: นางสาว | M35: สนิฎา หาญกำเนิดพงศ์ | N35: แผนก Compensation และ Benefit | O35: HO0036072C0031 | P35: ชุดคอมพิวเตอร์ CASE i5-10500 พร้อมอุปกรณ์ | Q35: HO0036073M0043 | R35: จอคอมพิวเตอร์ FHD HP 22"
G36: 34 | H36: บริษัท เสนาดีเวลลอปเม้นท์ จำกัด (มหาชน) | I36: สถานที่ (Site) : อาคารธัญลักษณ์ภาคย์ (ฝ่ายพัฒนาระบบสารสนเทศ) | J36: 2 | K36: BK680570 | L36: นางสาว | M36: เสาวลักษณ์ ภักดีพงษ์ | N36: แผนก Compensation และ Benefit | O36: HO0036072C0031 | Q36: HO0036073M0043
G37: 35 | H37: บริษัท เสนาดีเวลลอปเม้นท์ จำกัด (มหาชน) | I37: สถานที่ (Site) : อาคารธัญลักษณ์ภาคย์ (ฝ่ายพัฒนาระบบสารสนเทศ) | J37: 2 | K37: BK560045 | L37: ว่าที่ ร.ต. | M37: ฐิตินันท์ อินทาปัจ | N37: แผนก Learning & Development | O37: PESHO012C0049 | P37: NoteBook | Q37: PESHO012C0047 | R37: MONITOR LCD 20"
G38: 36 | H38: บริษัท เสนาดีเวลลอปเม้นท์ จำกัด (มหาชน) | I38: สถานที่ (Site) : อาคารธัญลักษณ์ภาคย์ (ฝ่ายพัฒนาระบบสารสนเทศ) | J38: 2 | K38: BK680562 | L38: นางสาว | M38: ระวีพร ประทีปพรศักดิ์ | N38: แผนก Learning & Development | O38: HO0021072C0001 | P38: Notebook Asus Vivobook 14 นิ้ว
G39: 37 | H39: บริษัท เสนาดีเวลลอปเม้นท์ จำกัด (มหาชน) | I39: สถานที่ (Site) : อาคารธัญลักษณ์ภาคย์ (ฝ่ายพัฒนาระบบสารสนเทศ) | J39: 2 | K39: BK660083 | L39: นางสาว | M39: สุภาภรณ์ สุขคำมี | N39: แผนก HR Project & System | O39: HO0026072C0001 | P39: ชุดคอมพิวเตอร์ CASE (ไม่รวมจอ) | Q39: SN:B3732Y3 | R39: จอคอมพิวเตอร์ FHD DELL 24"
G40: 38 | H40: บริษัท เสนาดีเวลลอปเม้นท์ จำกัด (มหาชน) | I40: สถานที่ (Site) : อาคารธัญลักษณ์ภาคย์ (ฝ่ายพัฒนาระบบสารสนเทศ) | J40: 2 | K40: BK670005 | L40: นาย | M40: อนุสรณ์ เชือนเชื้อ | N40: แผนก HR Project & System | O40: SN:7QRKQ04 | P40: ชุดคอมพิวเตอร์ Dell 7010SFF i5-13500 | Q40: SN:9F27XY3 | R40: จอคอมพิวเตอร์ DELL FHD 24"
G41: 39 | H41: บริษัท เสนาดีเวลลอปเม้นท์ จำกัด (มหาชน) | I41: สถานที่ (Site) : อาคารธัญลักษณ์ภาคย์ (ฝ่ายพัฒนาระบบสารสนเทศ) | J41: 2 | K41: BK670050 | L41: นางสาว | M41: ปพัชญา คนใหญ่ | N41: แผนก HR Project & System | O41: HO0026072C0014 | P41: ชุดคอมพิวเตอร์ CASE i5-9400 พร้อมอุปกรณ์
G42: 40 | H42: บริษัท เสนาดีเวลลอปเม้นท์ จำกัด (มหาชน) | I42: สถานที่ (Site) : อาคารธัญลักษณ์ภาคย์ (ฝ่ายพัฒนาระบบสารสนเทศ) | J42: 2 | K42: BK650231 | L42: นาย | M42: ฐานะพงษ์ สงนวน | N42: แผนก Talent Acquisition & Employee Branding | O42: HO0026072N0001 | P42: Notebook acer TravelMate P214 15" | Q42: ACCHO012C0010 | R42: MONITOR LCD 20"
G43: 41 | H43: บริษัท เสนาดีเวลลอปเม้นท์ จำกัด (มหาชน) | I43: สถานที่ (Site) : อาคารธัญลักษณ์ภาคย์ (ฝ่าย IT Support) | J43: 2 | K43: BK670060 | L43: นางสาว | M43: กัลยา จันทุลาง | N43: แผนกบริการและสนับสนุนด้านเทคนิค | O43: SN:2V8BXW3 | P43: ชุดคอมพิวเตอร์ Dell 7010SFF i5-13500 | Q43: SN:FYM6KT3 | R43: จอคอมพิวเตอร์ FHD DELL 24"
G44: 42 | H44: บริษัท เสนา กรีน เอนเนอร์ยี่ จำกัด | I44: สถานที่ (Site) : อาคารธัญลักษณ์ภาคย์ (ฝ่ายพัฒนาระบบสารสนเทศ) | J44: 2 | K44: SGE660020 | L44: นาย | M44: สิทธิ รัตนราษี | N44: สายงานบริหารทรัพยากรบุคคล | O44: SN:MP2ESZZ5 | P44: Notebook Lenovo Thinkbook 15.6"
G45: 43 | H45: บริษัท เสนาดีเวลลอปเม้นท์ จำกัด (มหาชน) | I45: สถานที่ (Site) : อาคารธัญลักษณ์ภาคย์ (ฝ่ายพัฒนาระบบสารสนเทศ) | J45: 2 | K45: BK530073 | L45: นางสาว | M45: วิไล สายสิทธิ์ | N45: แผนก Compensation และ Benefit | O45: PESHO072C0003 | P45: ชุดคอมพิวเตอร์ CASE (ไม่รวมจอ) | Q45: SN:DL1J8X3 | R45: จอคอมพิวเตอร์ FHD DELL 24"
G46: 44 | H46: บริษัท เสนาดีเวลลอปเม้นท์ จำกัด (มหาชน) | I46: สถานที่ (Site) : อาคารธัญลักษณ์ภาคย์ (ฝ่ายตรวจสอบภายใน (IA)) | J46: 3 | K46: BK620048 | L46: นางสาว | M46: ภาวิพัชร มณีนิล | N46: ฝ่ายตรวจสอบภายใน | O46: SN:MP2ET3QQ | P46: Notebook Lenovo Thinkbook 15.6" | Q46: HO0025073C0002 | R46: จอคอมพิวเตอร์ LED HP 22 นิ้ว
G47: 45 | H47: บริษัท เสนาดีเวลลอปเม้นท์ จำกัด (มหาชน) | I47: สถานที่ (Site) : อาคารธัญลักษณ์ภาคย์ (ฝ่ายตรวจสอบภายใน (IA)) | J47: 3 | K47: BK640044 | L47: นาย | M47: ชูวิทย์ ปรีชาศุทธิ์ | N47: แผนกตรวจสอบภายใน | O47: HO0038072C0001 | P47: ชุดคอมพิวเตอร์ CASE i5-9400 พร้อมอุปกรณ์ | Q47: HO0036073C0011 | R47: จอคอมพิวเตอร์ LED HP 22 นิ้ว
G48: 46 | H48: บริษัท เสนาดีเวลลอปเม้นท์ จำกัด (มหาชน) | I48: สถานที่ (Site) : อาคารธัญลักษณ์ภาคย์ (ฝ่ายตรวจสอบภายใน (IA)) | J48: 3 | K48: BK640131 | L48: นางสาว | M48: สุวภัทร ขวัญเมือง | N48: แผนกตรวจสอบภายใน | O48: HO0036072C0013 | P48: ชุดคอมพิวเตอร์ CASE i5-8500 (ไม่มีอุปกรณ์ต่อพ่วง) | Q48: HO0038073C0001 | R48: จอคอมพิวเตอร์ LED HP 22 นิ้ว
G49: 47 | H49: บริษัท เสนาดีเวลลอปเม้นท์ จำกัด (มหาชน) | I49: สถานที่ (Site) : อาคารธัญลักษณ์ภาคย์ (ฝ่ายตรวจสอบภายใน (IA)) | J49: 3 | K49: BK640132 | L49: นาย | M49: ธราเทพ ตราชู | N49: แผนกตรวจสอบภายใน | O49: HO0038072C0004 | P49: ชุดคอมพิวเตอร์ All in one Lennovo | Q49: HO0038073M0001 | R49: จอคอมพิวเตอร์ FHD HP 22"
G50: 48 | H50: บริษัท เสนาดีเวลลอปเม้นท์ จำกัด (มหาชน) | I50: สถานที่ (Site) : อาคารธัญลักษณ์ภาคย์ (ฝ่ายตรวจสอบภายใน (IA)) | J50: 3 | K50: BK650278 | L50: นาย | M50: ภาวิศ พ่วงทองคำ | N50: แผนกตรวจสอบภายใน | O50: HO0026072C0004 | P50: ชุดคอมพิวเตอร์ CASE (ไม่รวมจอ) | Q50: CONHO012C0065 | R50: MONITOR LCD 20"
G51: 49 | H51: บริษัท เสนาดีเวลลอปเม้นท์ จำกัด (มหาชน) | I51: สถานที่ (Site) : อาคารธัญลักษณ์ภาคย์ (ฝ่ายตรวจสอบภายใน (IA)) | J51: 3 | K51: BK650317 | L51: นางสาว | M51: อนงค์วรรณ ดวงศรี | N51: แผนกตรวจสอบภายใน | O51: HO0038072C0003 | P51: ชุดคอมพิวเตอร์ CASE i5-11400 พร้อมอุปกรณ์ | Q51: HO0038073M0002 | R51: จอคอมพิวเตอร์ FHD HP 22"
G52: 50 | H52: บริษัท เสนาดีเวลลอปเม้นท์ จำกัด (มหาชน) | I52: สถานที่ (Site) : อาคารธัญลักษณ์ภาคย์ (ฝ่ายตรวจสอบภายใน (IA)) | J52: 3 | K52: BK660123 | L52: นางสาว | M52: ณรดา จันทร์สุริย์ | N52: แผนกตรวจสอบภายใน | O52: FINRHO072C0001 | P52: ชุดคอมพิวเตอร์ CASE (ไม่รวมจอ) | Q52: HO0008073C0002 | R52: จอคอมพิวเตอร์ LED HP 22 นิ้ว
G53: 51 | H53: บริษัท เสนาดีเวลลอปเม้นท์ จำกัด (มหาชน) | I53: สถานที่ (Site) : อาคารธัญลักษณ์ภาคย์ (สายงานจัดซื้อ) | J53: 3 | K53: BK000040 | L53: นาย | M53: ทัศนัย มั่นยวน | N53: สายงานจัดซื้อ | O53: PURHO072C0001 | P53: ชุดคอมพิวเตอร์ CASE (ไม่รวมจอ) | Q53: HO0036073C0001 | R53: จอคอมพิวเตอร์ LED SAMSUNG 27 นิ้ว
G54: 52 | H54: บริษัท เสนาดีเวลลอปเม้นท์ จำกัด (มหาชน) | I54: สถานที่ (Site) : อาคารธัญลักษณ์ภาคย์ (สายงานจัดซื้อ) | J54: 3 | K54: BK620115 | L54: นางสาว | M54: ชุติมา อิทธิรัตนะโกมล | N54: ฝ่ายจัดซื้อ | O54: PURHO072C0002 | P54: ชุดคอมพิวเตอร์ CASE (ไม่รวมจอ) | Q54: PURHO072C0004 | R54: MONITOR LCD 24"
G55: 53 | H55: บริษัท เสนาดีเวลลอปเม้นท์ จำกัด (มหาชน) | I55: สถานที่ (Site) : อาคารธัญลักษณ์ภาคย์ (สายงานจัดซื้อ) | J55: 3 | K55: BK660087 | L55: นาย | M55: บุญญฤทธิ์ ชุนเจริญ | N55: ฝ่ายจัดซื้อ | O55: HO2C01004PUR | P55: ชุดคอมพิวเตอร์ CASE (ไม่รวมจอ) | Q55: HO2C03004PUR | R55: MONITOR LCD 20"
G56: 54 | H56: บริษัท เสนาดีเวลลอปเม้นท์ จำกัด (มหาชน) | I56: สถานที่ (Site) : อาคารธัญลักษณ์ภาคย์ (สายงานจัดซื้อ) | J56: 3 | K56: BK660135 | L56: นางสาว | M56: ขวัญชนก มุขตวาภัย | N56: ฝ่ายจัดซื้อ | O56: PURHO012C0014 | P56: ชุดคอมพิวเตอร์ CASE (ไม่รวมจอ) | Q56: HO0023072C0003 | R56: MONITOR LCD 22"
... G59: 57 | H59: บริษัท เสนาดีเวลลอปเม้นท์ จำกัด (มหาชน) | I59: สถานที่ (Site) : อาคารธัญลักษณ์ภาคย์ (สายงานจัดซื้อ) | J59: 3 | K59: BK660020 | L59: นางสาว | M59: ศิรินภา ชมประเสริฐ | N59: แผนกจัดซื้อ | O59: HO0036072C0068 | P59: ชุดคอมพิวเตอร์ CASE i5-11400 พร้อมอุปกรณ์ | Q59: HO0036073M0049 | R59: จอคอมพิวเตอร์ FHD HP 22"
G60: 58 | H60: บริษัท เสนาดีเวลลอปเม้นท์ จำกัด (มหาชน) | I60: สถานที่ (Site) : อาคารธัญลักษณ์ภาคย์ (สายงานจัดซื้อ) | J60: 3 | K60: BK670045 | L60: นางสาว | M60: ประภัสสร ปิยะวัติ | N60: แผนกจัดซื้อ | O60: HO0036072C00088 | P60: ชุดคอมพิวเตอร์ CASE (ไม่รวมจอ)
G61: 59 | H61: บริษัท เสนาดีเวลลอปเม้นท์ จำกัด (มหาชน) | I61: สถานที่ (Site) : อาคารธัญลักษณ์ภาคย์ (สายงานจัดซื้อ) | J61: 3 | K61: BK670091 | L61: นางสาว | M61: สมใจ ปิ่นเพชร | N61: แผนกจัดซื้อ | O61: SN:6ZYNPY3 | P61: ชุดคอมพิวเตอร์ Dell 7010SFF i5-13500 | Q61: SN:C7LNYV3 | R61: จอคอมพิวเตอร์ FHD DELL 24"
G62: 60 | H62: บริษัท เสนาดีเวลลอปเม้นท์ จำกัด (มหาชน) | I62: สถานที่ (Site) : อาคารธัญลักษณ์ภาคย์ (สายงานจัดซื้อ) | J62: 3 | K62: BK670092 | L62: นางสาว | M62: ภัทรธิดา พิริยะรุ่งโรจน์ | N62: แผนกจัดซื้อ | O62: HO0036072C0060 | P62: ชุดคอมพิวเตอร์ CASE i5-11400 พร้อมอุปกรณ์ | Q62: HO0036073M0034 | R62: จอคอมพิวเตอร์ FHD HP 22"
G63: 61 | H63: บริษัท เสนาดีเวลลอปเม้นท์ จำกัด (มหาชน) | I63: สถานที่ (Site) : อาคารธัญลักษณ์ภาคย์ (สายงานจัดซื้อ) | J63: 3 | K63: BK610108 | L63: นางสาว | M63: นรีรัตน์ ครองตน | N63: แผนกจัดซื้อแนวราบ | O63: FINRHO012C0003 | P63: ชุดคอมพิวเตอร์ CASE (ไม่รวมจอ) | Q63: HO2C03006PUR | R63: MONITOR LCD 20"
G64: 62 | H64: บริษัท เสนาดีเวลลอปเม้นท์ จำกัด (มหาชน) | I64: สถานที่ (Site) : อาคารธัญลักษณ์ภาคย์ (สายงานจัดซื้อ) | J64: 3 | K64: BK630020 | L64: นาย | M64: วรเทพ บุญอยู่ | N64: แผนกจัดซื้อแนวราบ | O64: ADMHO012C0031 | P64: ชุดคอมพิวเตอร์ CASE (ไม่รวมจอ) | Q64: HO2C03003PUR | R64: MONITOR LCD 20"
G65: 63 | H65: บริษัท เสนาดีเวลลอปเม้นท์ จำกัด (มหาชน) | I65: สถานที่ (Site) : อาคารธัญลักษณ์ภาคย์ (สายงานจัดซื้อ) | J65: 3 | K65: BK660045 | L65: นางสาว | M65: ลัดดา จงปัตนา | N65: แผนกจัดซื้อแนวราบ | O65: HO0023072C0005 | P65: ชุดคอมพิวเตอร์ CASE i5-10500 พร้อมอุปกรณ์ | Q65: HO0023073M0004 | R65: จอคอมพิวเตอร์ FHD HP 22"
G66: 64 | H66: บริษัท เสนาดีเวลลอปเม้นท์ จำกัด (มหาชน) | I66: สถานที่ (Site) : อาคารธัญลักษณ์ภาคย์ (สายงานจัดซื้อ) | J66: 3 | K66: BK660086 | L66: นางสาว | M66: อนุสรา แก้วบัวดี | N66: แผนกจัดซื้อแนวราบ | O66: HO0023072C0002 | P66: ชุดคอมพิวเตอร์ CASE (ไม่รวมจอ) | Q66: HO0023073M0001 | R66: จอคอมพิวเตอร์ FHD HP 22"
G67: 65 | H67: บริษัท เสนาดีเวลลอปเม้นท์ จำกัด (มหาชน) | I67: สถานที่ (Site) : อาคารธัญลักษณ์ภาคย์ (สายงานจัดซื้อ) | J67: 3 | K67: BK550012 | L67: นางสาว | M67: ศิริลักษณ์ ทะวงค์ศรี | N67: แผนกจัดซื้อแนวสูง | O67: HK2C01001SAL | P67: ชุดคอมพิวเตอร์ CASE (ไม่รวมจอ)
G68: 66 | H68: บริษัท เสนาดีเวลลอปเม้นท์ จำกัด (มหาชน) | I68: สถานที่ (Site) : อาคารธัญลักษณ์ภาคย์ (สายงานจัดซื้อ) | J68: 3 | K68: BK620090 | L68: นางสาว | M68: นิตยา นวลจอน | N68: แผนกจัดซื้อแนวสูง | O68: CONHO012C0089 | P68: ชุดคอมพิวเตอร์ CASE (ไม่รวมจอ) | Q68: HO0005073C0016 | R68: จอคอมพิวเตอร์ LED HP 22 นิ้ว
G69: 67 | H69: บริษัท เสนาดีเวลลอปเม้นท์ จำกัด (มหาชน) | I69: สถานที่ (Site) : อาคารธัญลักษณ์ภาคย์ (สายงานจัดซื้อ) | J69: 3 | K69: BK650177 | L69: นางสาว | M69: ลีลาวดี อุทัยรังษี | N69: แผนกจัดซื้อแนวสูง | O69: HO0023072C0007 | P69: ชุดคอมพิวเตอร์ CASE i5-10500 พร้อมอุปกรณ์ | Q69: CONHO012C0060 | R69: MONITOR LCD 20"
G70: 68 | H70: บริษัท เสนาดีเวลลอปเม้นท์ จำกัด (มหาชน) | I70: สถานที่ (Site) : อาคารธัญลักษณ์ภาคย์ (สายงานจัดซื้อ) | J70: 3 | K70: BK660078 | L70: นางสาว | M70: บัวแก้ว ศรีสร้อย | N70: แผนกจัดซื้อแนวสูง | O70: PURHO012C0013 | P70: ชุดคอมพิวเตอร์ CASE (ไม่รวมจอ) | Q70: HO2C03003A/C | R70: MONITOR LCD 20"
G71: 69 | H71: บริษัท เสนาดีเวลลอปเม้นท์ จำกัด (มหาชน) | I71: สถานที่ (Site) : อาคารธัญลักษณ์ภาคย์ (สายงานจัดซื้อ) | J71: 3 | K71: BK660152 | L71: นาง | M71: วิรงรอง เพชรสะแก | N71: ฝ่าย Supply Chain Planning | O71: SN:MP2ET64A | P71: Notebook Lenovo Thinkbook 15.6" | Q71: SCM1073M0001 | R71: จอคอมพิวเตอร์ LCD AOC 24"
G72: 70 | H72: บริษัท เสนาดีเวลลอปเม้นท์ จำกัด (มหาชน) | I72: สถานที่ (Site) : อาคารธัญลักษณ์ภาคย์ (สายงานจัดซื้อ) | J72: 3 | K72: BK670016 | L72: นาย | M72: วินัย พลายด้วง | N72: ฝ่าย Supply Chain Planning | O72: SN:MP2M8JL3 | P72: Notebook Lenovo Thinkbook G4 14"
G73: 71 | H73: บริษัท เสนาดีเวลลอปเม้นท์ จำกัด (มหาชน) | I73: สถานที่ (Site) : อาคารธัญลักษณ์ภาคย์ (สายงานจัดซื้อ) | J73: 3 | K73: BK670065 | L73: นาย | M73: วันชัย กล่ำบุญ | N73: ฝ่าย Supply Chain Planning | O73: CONSKN072C0001 | P73: Notebook DELL Inspiron | Q73: HOS010073M0004 | R73: จอคอมพิวเตอร์ FHD SAMSUNG 24"
G74: 72 | H74: บริษัท เสนาดีเวลลอปเม้นท์ จำกัด (มหาชน) | I74: สถานที่ (Site) : อาคารธัญลักษณ์ภาคย์ (สายงานธุรกิจ 21) ( Supply Chain) | J74: 3 | K74: BK670040 | L74: นางสาว | M74: ยุวเทวี กลางบุรัมย์ | N74: แผนก Supply Chain Planning | O74: JPSHO072C0025 | P74: ชุดคอมพิวเตอร์ CASE i5-8500 พร้อมอุปกรณ์ | Q74: SN:DMZH8X3 | R74: จอคอมพิวเตอร์ FHD DELL 24"
G75: 73 | H75: บริษัท เสนา กรีน ออโตโมทีฟ จำกัด | I75: สถานที่ (Site) : อาคารธัญลักษณ์ภาคย์ (เอท โซลาร์) | J75: 3 | K75: SGA670016 | L75: นาย | M75: ชัยรัตน์ พุดพิมเสน | N75: บริษัท เสนา กรีน ออโตโมทีฟ จำกัด | O75: คอมส่วนตัว
G76: 74 | H76: บริษัท เสนา กรีน เอนเนอร์ยี่ จำกัด | I76: สถานที่ (Site) : อาคารธัญลักษณ์ภาคย์ (เอท โซลาร์) | J76: 3 | K76: SGE660026 | L76: นางสาว | M76: อังคณา ใจการ | N76: ฝ่ายบัญชีการเงิน | O76: SN:PF3A18G4 | P76: Notebook Lenovo V14 GEN2 14" | Q76: CONK2K012C0016 | R76: MONITOR LCD 20"
G77: 75 | H77: บริษัท เสนา กรีน เอนเนอร์ยี่ จำกัด | I77: สถานที่ (Site) : อาคารธัญลักษณ์ภาคย์ (เอท โซลาร์) | J77: 3 | K77: SGE670027 | L77: นางสาว | M77: อมรรัตน์ กันดี | N77: แผนกบัญชีการเงิน | O77: SN:BSRKQ04 | P77: ชุดคอมพิวเตอร์ Dell 7010SFF i5-13500 | Q77: SN:8ZY7XY3 | R77: จอคอมพิวเตอร์ DELL FHD 24"
G78: 76 | H78: บริษัท เสนา กรีน เอนเนอร์ยี่ จำกัด | I78: สถานที่ (Site) : อาคารธัญลักษณ์ภาคย์ (เอท โซลาร์) | J78: 3 | K78: SGE670032 | L78: นางสาว | M78: วรรณิกา หมื่นไธสง | N78: แผนกบัญชีการเงิน | O78: SN:JJ6MBZ3 | P78: ชุดคอมพิวเตอร์ Dell 7010SFF i5-13500 | Q78: SN:90N8XY3 | R78: จอคอมพิวเตอร์ FHD DELL 24"
G79: 77 | H79: บริษัท เสนา กรีน เอนเนอร์ยี่ จำกัด | I79: สถานที่ (Site) : อาคารธัญลักษณ์ภาคย์ (เอท โซลาร์) | J79: 3 | K79: SGE670034 | L79: นางสาว | M79: อุไรวรรณ สายแวว | N79: แผนกบัญชีการเงิน | O79: SN:BRRKQ04 | P79: ชุดคอมพิวเตอร์ Dell 7010SFF i5-13500 | Q79: SN:91X6XY3 | R79: จอคอมพิวเตอร์ DELL FHD 24"
G80: 78 | H80: บริษัท เสนา โซลาร์ เอนเนอร์ยี่ จำกัด | I80: สถานที่ (Site) : กลุ่มธุรกิจเช่าอสังหาริมทรัพย์ SK Asset (สำนักงาน SK Asset) | J80: 3 | K80: SSG680001 | L80: นาย | M80: จตุรงค์ สัจจะนรพันธ์ | N80: กลุ่มงานบริหาร SENA Solar Energy | O80: SN:MP2EJ2XP | P80: Notebook Lenovo Thinkbook G3 14"
G81: 79 | H81: บริษัท เสนา โซลาร์ เอนเนอร์ยี่ จำกัด | I81: สถานที่ (Site) : อาคารธัญลักษณ์ภาคย์ (สายงานพัฒนาโครงการและพัฒนาผลิตภัณฑ์) | J81: 3 | K81: SSG670017 | L81: นาย | M81: อำนาจ พิบูลย์ | N81: ฝ่ายออกแบบและประมาณราคา | O81: HO0022072C0029 | P81: ชุดคอมพิวเตอร์ CASE (ไม่รวมจอ) | Q81: HO2C03019CON | R81: MONITOR LCD 20"
G82: 80 | H82: บริษัท เสนา โซลาร์ เอนเนอร์ยี่ จำกัด | I82: สถานที่ (Site) : สายงานบริษัท เสนา กรีน เอนเนอร์ยี่ จำกัด (สายงาน เอท โซลาร์) | J82: 3 | K82: SSG640008 | L82: นาย | M82: พงศ์พัฒน์ ไตรประวัติ | N82: ฝ่ายออกแบบและประมาณราคา | O82: HO0002072C0011 | P82: ชุดคอมพิวเตอร์ CASE i5-11500 พร้อมอุปกรณ์ | Q82: HO0002073C0008 | R82: จอคอมพิวเตอร์ LED SAMSUNG 24 นิ้ว
G83: 81 | H83: บริษัท เสนา โซลาร์ เอนเนอร์ยี่ จำกัด | I83: สถานที่ (Site) : อาคารธัญลักษณ์ภาคย์ (เอท โซลาร์) | J83: 3 | K83: SSG650005 | L83: นาย | M83: อาทิตย์ ชาญเดช | N83: ฝ่ายออกแบบและประมาณราคา | O83: 8SOLA072C0004 | P83: NoteBook | Q83: HO0002073C0009 | R83: จอคอมพิวเตอร์ LED SAMSUNG 24 นิ้ว
G84: 82 | H84: บริษัท เสนา โซลาร์ เอนเนอร์ยี่ จำกัด | I84: สถานที่ (Site) : อาคารธัญลักษณ์ภาคย์ (เอท โซลาร์) | J84: 3 | K84: SSG660007 | L84: นาย | M84: ศักดินันท์ สอนวงษ์ | N84: ฝ่ายขายและการตลาด | O84: SN:16F7LS3 | P84: Notebook DELL Precision M3591 | Q84: HO0002073M0002 | R84: จอคอมพิวเตอร์ LED Lenovo 24"
G85: 83 | H85: บริษัท เสนา โซลาร์ เอนเนอร์ยี่ จำกัด | I85: สถานที่ (Site) : อาคารธัญลักษณ์ภาคย์ (เอท โซลาร์) | J85: 3 | K85: SSG660008 | L85: นาย | M85: จักรพันธ์ ศิริสุนทรชัย | N85: ฝ่ายขายและการตลาด | O85: MP2EHCN6
G86: 84 | H86: บริษัท เสนา โซลาร์ เอนเนอร์ยี่ จำกัด | I86: สถานที่ (Site) : อาคารธัญลักษณ์ภาคย์ (เอท โซลาร์) | J86: 3 | K86: SSG610019 | L86: นาย | M86: วัชชนะศักดิ์ ศักดิ์สมวาสน์ | N86: ฝ่ายสนับสนุน | O86: PTH2C13002SAL | P86: NoteBook | Q86: HO0002073M0005 | R86: จอคอมพิวเตอร์ FHD HP 24"
G87: 85 | H87: บริษัท เสนา โซลาร์ เอนเนอร์ยี่ จำกัด | I87: สถานที่ (Site) : อาคารธัญลักษณ์ภาคย์ (เอท โซลาร์) | J87: 3 | K87: SSG610002 | L87: นางสาว | M87: สายสุณี ชาติบูรณะ | N87: แผนกคลังสินค้าและจัดส่ง | O87: PTH2C13008SAL | P87: NoteBook | Q87: COMMHO012C0001 | R87: MONITOR LCD 20"
G88: 86 | H88: บริษัท เสนา โซลาร์ เอนเนอร์ยี่ จำกัด | I88: สถานที่ (Site) : อาคารธัญลักษณ์ภาคย์ (เอท โซลาร์) | J88: 3 | K88: SSG610020 | L88: นาย | M88: รุ่งศักดิ์ นิธิลาภพูล | N88: แผนกประสานงานราชการ | O88: SN:MP2EHMN1 | P88: Notebook Lenovo Thinkbook G3 14"
G89: 87 | H89: บริษัท เสนา โซลาร์ เอนเนอร์ยี่ จำกัด | I89: สถานที่ (Site) : อาคารธัญลักษณ์ภาคย์ (เอท โซลาร์) | J89: 3 | K89: SSG660009 | L89: นาย | M89: วารินทร์ เพ็ชร์ภักดี | N89: แผนกประสานงานราชการ | O89: SN:FDD0HY3 | P89: ชุดคอมพิวเตอร์ Dell 7010SFF i5-13500 | Q89: SN:C7FNYV3 | R89: จอคอมพิวเตอร์ FHD DELL 24"
G90: 88 | H90: บริษัท เสนา โซลาร์ เอนเนอร์ยี่ จำกัด | I90: สถานที่ (Site) : สายงานบริษัท เสนา กรีน เอนเนอร์ยี่ จำกัด (สายงาน เอท โซลาร์) | J90: 3 | K90: SSG670002 | L90: นางสาว | M90: ณฐมน แสนยะมูล | N90: แผนกประสานงานราชการ | O90: ADMHO012C0018 | P90: ชุดคอมพิวเตอร์ CASE (ไม่รวมจอ) | Q90: HOM09157XY3 | R90: จอคอมพิวเตอร์ FHD DELL 24"
G91: 89 | H91: บริษัท เสนา โซลาร์ เอนเนอร์ยี่ จำกัด | I91: สถานที่ (Site) : อาคารธัญลักษณ์ภาคย์ (เอท โซลาร์) | J91: 3 | K91: SSG680002 | L91: นาย | M91: ภูวสิษฏ์ ดอกจันทร์ | N91: สายงานติดตั้งและซ่อมบำรุง | O91: คอมส่วนตัว
G92: 90 | H92: บริษัท เสนา โซลาร์ เอนเนอร์ยี่ จำกัด | I92: สถานที่ (Site) : อาคารธัญลักษณ์ภาคย์ (เอท โซลาร์) | J92: 3 | K92: SSG650001 | L92: นาย | M92: กีรติ อับดุลย์ | N92: ฝ่ายติดตั้ง | O92: HO0002072N0005 | P92: Notebook Lenovo V14 GEN2 14"
G93: 91 | H93: บริษัท เสนา โซลาร์ เอนเนอร์ยี่ จำกัด | I93: สถานที่ (Site) : อาคารธัญลักษณ์ภาคย์ (เอท โซลาร์) | J93: 3 | K93: SSG670018 | L93: นาย | M93: สุเปียน เด็งระกีนา | N93: ฝ่ายติดตั้ง | O93: HO0002072C0010 | P93: Notebook ASUS ROG Strix G 15.6 นิ้ว
G94: 92 | H94: บริษัท เสนา โซลาร์ เอนเนอร์ยี่ จำกัด | I94: สถานที่ (Site) : อาคารธัญลักษณ์ภาคย์ (เอท โซลาร์) | J94: 3 | K94: SSG660005 | L94: นาย | M94: สุพัฒนพงศ์ วงษ์กิจวิเชียร | N94: ฝ่ายบำรุงรักษา | O94: SN:MP2EJ2XV | P94: Notebook Lenovo Thinkbook G3 14" | Q94: HO0002073M0001 | R94: จอคอมพิวเตอร์ FHD HP 27"
G95: 93 | H95: บริษัท เสนา โซลาร์ เอนเนอร์ยี่ จำกัด | I95: สถานที่ (Site) : อาคารธัญลักษณ์ภาคย์ (เอท โซลาร์) | J95: 3 | K95: SSG670005 | L95: นาย | M95: สุทธิโชติ มั่งคั่ง | N95: ฝ่ายบำรุงรักษา | O95: SN:MP2EHHQL | P95: Notebook Lenovo Thinkbook G3 14"
G96: 94 | H96: บริษัท เสนา กรีน เอนเนอร์ยี่ จำกัด | I96: สถานที่ (Site) : อาคารธัญลักษณ์ภาคย์ (เสนา โซลาร์) | J96: 3 | K96: SGE660024 | L96: นางสาว | M96: สุภาวดี คาพิจารณ์ | N96: ฝ่ายจัดสรรเงินทุน | O96: SN:MP2EJ2WV | P96: Notebook Lenovo Thinkbook G3 14" | Q96: HO2C03025ACC | R96: MONITOR CRT/CTX 17"
G97: 95 | H97: บริษัท เสนาดีเวลลอปเม้นท์ จำกัด (มหาชน) | I97: สถานที่ (Site) : อาคารธัญลักษณ์ภาคย์ (สายงานพัฒนาโครงการและพัฒนาผลิตภัณฑ์) | J97: 3 | K97: BK680581 | L97: นางสาว | M97: สมัชญา บุญผ่อง | N97: สายงานบัญชี 3 (กลุ่มธุรกิจโซลาร์) | O97: HO0022072C0029 | P97: ชุดคอมพิวเตอร์ CASE (ไม่รวมจอ) | Q97: HO2C03019CON | R97: MONITOR LCD 20"
G98: 96 | H98: บริษัท เสนา โซลาร์ เอนเนอร์ยี่ จำกัด | I98: สถานที่ (Site) : อาคารธัญลักษณ์ภาคย์ (เอท โซลาร์) | J98: 3 | K98: SSG610007 | L98: นางสาว | M98: มณฑาทิพย์ เทศเล็ก | N98: กลุ่มบริหารธุรกิจโซลาร์ | O98: HO2C01006GPH | P98: ชุดคอมพิวเตอร์ CASE (ไม่รวมจอ) | Q98: HO0002073M0003 | R98: จอคอมพิวเตอร์ FHD HP 22"
G99: 97 | H99: บริษัท เสนา กรีน เอนเนอร์ยี่ จำกัด | I99: สถานที่ (Site) : อาคารธัญลักษณ์ภาคย์ (เอท โซลาร์) | J99: 3 | K99: SGE660023 | L99: นางสาว | M99: พิชยา พุฒพันธ์ | N99: ฝ่ายบัญชีการเงิน-โซลาร์ | O99: ADMHO012C0025 | P99: ชุดคอมพิวเตอร์ CASE (ไม่รวมจอ) | Q99: SN:7PMVGZ3 | R99: จอคอมพิวเตอร์ DELL FHD 24"
G100: 98 | H100: บริษัท เสนา กรีน เอนเนอร์ยี่ จำกัด | I100: สถานที่ (Site) : อาคารธัญลักษณ์ภาคย์ (เอท โซลาร์) | J100: 3 | K100: SGE660025 | L100: นางสาว | M100: นพสร สุดใจ | N100: แผนกการเงิน | O100: TTREHO012C0001 | P100: ชุดคอมพิวเตอร์ CASE (ไม่รวมจอ) | Q100: CONHO012C0048 | R100: MONITOR LCD 20"
G101: 99 | H101: บริษัท เสนา โซลาร์ เอนเนอร์ยี่ จำกัด | I101: สถานที่ (Site) : อาคารธัญลักษณ์ภาคย์ (เอท โซลาร์) | J101: 3 | K101: SSG620003 | L101: นาย | M101: วริศ บวรรัตนสุภา | N101: แผนกออกแบบ | O101: SN:MP2E0P8R | P101: Notebook Lenovo Thinkbook Gen2 14"
G102: 100 | H102: บริษัท เสนาดีเวลลอปเม้นท์ จำกัด (มหาชน) | I102: สถานที่ (Site) : อาคารธัญลักษณ์ภาคย์ (ฝ่ายธุรกิจต่างประเทศ) | J102: 4 | K102: BK600084 | L102: นางสาว | M102: ปณิตา บุญญาศิริ | N102: แผนกกลยุทธ์การลงทุน | O102: HO0031072C0001 | P102: ชุดคอมพิวเตอร์ CASE (ไม่รวมจอ) | Q102: HO0097073M0001 | R102: จอคอมพิวเตอร์ FHD HP 27"
...

Sheet พนักงานที่ทำงานอยู่ปัจจุบัน
A1: Update เมื่อ : | B1: 46014 | D1: Next Update : | F1: 46023 | M1: A = พนักงานประจำ
M2: V = ทดลองงาน
A3: No. | B3: Employee ID | C3: Company | D3: วันที่เริ่มงาน | E3: Prefix | F3: Name | G3: Surname | H3: ชื่อเล่น | I3: Email | J3: Workarea | K3: Position | L3: Department | M3: สถานะ | N3: ลาออก | O3: ถือครองเครื่องเช่า
A4: 1 | B4: NN630002 | C4: บริษัท 99 แอสเซ็ท เมเนจเม้นท์ จำกัด | D4: 09-03-2018 | E4: นาย | F4: สุเมทย์ | G4: พิทยาธนาสกุล | H4: โต้ง | I4: Sumetp@sena.co.th | J4: โครงการ | K4: เจ้าหน้าที่อาคารอาวุโส | L4: ฝ่ายบริการสำนักงานและอาคารสถานที่ | M4: A | N4: =IFERROR( IF( AND( VLOOKUP(B4, 'รายชื่อพนักงานลาออกพ้นสภาพ'!B:I, 8, FALSE)<>"ยกเลิกลาออก", VLOOKUP(B4, 'รายชื่อพนักงานลาออกพ้นสภาพ'!B:I, 7, FALSE)<=TODAY() ), "ลาออกแล้ว", "" ), "") | O4: {=IFERROR(INDEX(PCRent!C:D, MATCH(F4 & " " & G4, PCRent!A:A & " " & PCRent!B:B, 0)), "")} | Q4: {=IFERROR(INDEX(MonitorRent!C:D, MATCH(F4 & " " & G4, MonitorRent!A:A & " " & MonitorRent!B:B, 0)), "")}
A5: 2 | B5: PC680001 | C5: บริษัท เงินสดใจดี จำกัด | D5: 18-09-2025 | E5: นางสาว | F5: กนกวรรณ | G5: ช่างประดับ | H5: ไอซ์ | I5: kanokwanc@moneyjaidee.com | J5: สำนักงานใหญ่ | K5: เจ้าหน้าที่บัญชีทั่วไป | L5: ฝ่ายปฏิบัติการสินเชื่อและบัญชี | M5: V | N5: =IFERROR( IF( AND( VLOOKUP(B5, 'รายชื่อพนักงานลาออกพ้นสภาพ'!B:I, 8, FALSE)<>"ยกเลิกลาออก", VLOOKUP(B5, 'รายชื่อพนักงานลาออกพ้นสภาพ'!B:I, 7, FALSE)<=TODAY() ), "ลาออกแล้ว", "" ), "") | O5: {=IFERROR(INDEX(PCRent!C:D, MATCH(F5 & " " & G5, PCRent!A:A & " " & PCRent!B:B, 0)), "")} | Q5: {=IFERROR(INDEX(MonitorRent!C:D, MATCH(F5 & " " & G5, MonitorRent!A:A & " " & MonitorRent!B:B, 0)), "")}
A6: 3 | B6: PC670001 | C6: บริษัท เงินสดใจดี จำกัด | D6: 12-02-2024 | E6: นางสาว | F6: นิพา | G6: มาตรักชาติ | H6: นิ | I6: nipam@moneyjaidee.com | J6: สำนักงานใหญ่ | K6: ผู้ช่วยหัวหน้าแผนก | L6: ฝ่ายปฏิบัติการสินเชื่อและบัญชี | M6: A | N6: =IFERROR( IF( AND( VLOOKUP(B6, 'รายชื่อพนักงานลาออกพ้นสภาพ'!B:I, 8, FALSE)<>"ยกเลิกลาออก", VLOOKUP(B6, 'รายชื่อพนักงานลาออกพ้นสภาพ'!B:I, 7, FALSE)<=TODAY() ), "ลาออกแล้ว", "" ), "") | O6: {=IFERROR(INDEX(PCRent!C:D, MATCH(F6 & " " & G6, PCRent!A:A & " " & PCRent!B:B, 0)), "")} -> SN:1RRKQ04 | P6: ชุดคอมพิวเตอร์ Dell 7010SFF i5-13500 | Q6: {=IFERROR(INDEX(MonitorRent!C:D, MATCH(F6 & " " & G6, MonitorRent!A:A & " " & MonitorRent!B:B, 0)), "")} -> SN:92D8XY3 | R6: จอคอมพิวเตอร์ DELL FHD 24"
A7: 4 | B7: PC680003 | C7: บริษัท เงินสดใจดี จำกัด | D7: 16-10-2025 | E7: นาย | F7: ปฐมชล | G7: ชื่นชมกิจ | H7: ต้นน้ำ | I7: patomcholc@moneyjaidee.com | J7: สำนักงานใหญ่ | K7: เจ้าหน้าที่สินเชื่อ | L7: ฝ่ายสินเชื่อ | M7: V | N7: =IFERROR( IF( AND( VLOOKUP(B7, 'รายชื่อพนักงานลาออกพ้นสภาพ'!B:I, 8, FALSE)<>"ยกเลิกลาออก", VLOOKUP(B7, 'รายชื่อพนักงานลาออกพ้นสภาพ'!B:I, 7, FALSE)<=TODAY() ), "ลาออกแล้ว", "" ), "") | O7: {=IFERROR(INDEX(PCRent!C:D, MATCH(F7 & " " & G7, PCRent!A:A & " " & PCRent!B:B, 0)), "")} -> SN:MP2EJ2Y0 | P7: Notebook Lenovo Thinkbook G3 14" | Q7: {=IFERROR(INDEX(MonitorRent!C:D, MATCH(F7 & " " & G7, MonitorRent!A:A & " " & MonitorRent!B:B, 0)), "")}
A8: 5 | B8: PC660002 | C8: บริษัท เงินสดใจดี จำกัด | D8: 02-05-2023 | E8: นาย | F8: พิชญ์ | G8: สุนทัน | H8: พิช | I8: pitchs@sena.co.th | J8: สำนักงานใหญ่ | K8: ผู้ช่วยผู้จัดการ | L8: ฝ่ายประสานงานสินเชื่อ | M8: A | N8: =IFERROR( IF( AND( VLOOKUP(B8, 'รายชื่อพนักงานลาออกพ้นสภาพ'!B:I, 8, FALSE)<>"ยกเลิกลาออก", VLOOKUP(B8, 'รายชื่อพนักงานลาออกพ้นสภาพ'!B:I, 7, FALSE)<=TODAY() ), "ลาออกแล้ว", "" ), "") | O8: {=IFERROR(INDEX(PCRent!C:D, MATCH(F8 & " " & G8, PCRent!A:A & " " & PCRent!B:B, 0)), "")} -> SN:MP2EHYDS | P8: Notebook Lenovo Thinkbook G3 14" | Q8: {=IFERROR(INDEX(MonitorRent!C:D, MATCH(F8 & " " & G8, MonitorRent!A:A & " " & MonitorRent!B:B, 0)), "")}
A9: 6 | B9: PC660003 | C9: บริษัท เงินสดใจดี จำกัด | D9: 16-06-2023 | E9: นางสาว | F9: ศุภวรรณ | G9: อุ่นอกแดง | H9: แนน | I9: supawanu@sena.co.th | J9: สำนักงานใหญ่ | K9: ผู้ช่วยหัวหน้าแผนก | L9: ฝ่ายสินเชื่อ | M9: A | N9: =IFERROR( IF( AND( VLOOKUP(B9, 'รายชื่อพนักงานลาออกพ้นสภาพ'!B:I, 8, FALSE)<>"ยกเลิกลาออก", VLOOKUP(B9, 'รายชื่อพนักงานลาออกพ้นสภาพ'!B:I, 7, FALSE)<=TODAY() ), "ลาออกแล้ว", "" ), "") | O9: {=IFERROR(INDEX(PCRent!C:D, MATCH(F9 & " " & G9, PCRent!A:A & " " & PCRent!B:B, 0)), "")} -> SN:PF39GKNJ | P9: Notebook Lenovo V14 GEN2 14" | Q9: {=IFERROR(INDEX(MonitorRent!C:D, MATCH(F9 & " " & G9, MonitorRent!A:A & " " & MonitorRent!B:B, 0)), "")}
A10: 7 | B10: PC660005 | C10: บริษัท เงินสดใจดี จำกัด | D10: 01-11-2023 | E10: นาย | F10: สมศักดิ์ | G10: หัตถ์สุวรรณ | H10: ศักดิ์ | I10: somsakh@moneyjaidee.com | J10: สำนักงานใหญ่ | K10: ผู้จัดการอาวุโส | L10: ฝ่ายสินเชื่อ | M10: A | N10: =IFERROR( IF( AND( VLOOKUP(B10, 'รายชื่อพนักงานลาออกพ้นสภาพ'!B:I, 8, FALSE)<>"ยกเลิกลาออก", VLOOKUP(B10, 'รายชื่อพนักงานลาออกพ้นสภาพ'!B:I, 7, FALSE)<=TODAY() ), "ลาออกแล้ว", "" ), "") | O10: {=IFERROR(INDEX(PCRent!C:D, MATCH(F10 & " " & G10, PCRent!A:A & " " & PCRent!B:B, 0)), "")} -> SN:F4RD314 | P10: ชุดคอมพิวเตอร์ Dell 7010SFF i5-13500 | Q10: {=IFERROR(INDEX(MonitorRent!C:D, MATCH(F10 & " " & G10, MonitorRent!A:A & " " & MonitorRent!B:B, 0)), "")} -> SN:B6S5HZ3 | R10: จอคอมพิวเตอร์ DELL FHD 24"
A11: 8 | B11: PC640001 | C11: บริษัท เงินสดใจดี จำกัด | D11: 11-02-2020 | E11: นาย | F11: สุธรรม | G11: โอฬารกิจอนันต์ | H11: บ็อบ | I11: suthamo@sena.co.th | J11: สำนักงานใหญ่ | K11: กรรมการผู้จัดการ | L11: กลุ่มงานบริการสินเชื่อเงินสดใจดี | M11: A | N11: =IFERROR( IF( AND( VLOOKUP(B11, 'รายชื่อพนักงานลาออกพ้นสภาพ'!B:I, 8, FALSE)<>"ยกเลิกลาออก", VLOOKUP(B11, 'รายชื่อพนักงานลาออกพ้นสภาพ'!B:I, 7, FALSE)<=TODAY() ), "ลาออกแล้ว", "" ), "") | O11: {=IFERROR(INDEX(PCRent!C:D, MATCH(F11 & " " & G11, PCRent!A:A & " " & PCRent!B:B, 0)), "")} | Q11: {=IFERROR(INDEX(MonitorRent!C:D, MATCH(F11 & " " & G11, MonitorRent!A:A & " " & MonitorRent!B:B, 0)), "")}
A12: 9 | B12: PC640003 | C12: บริษัท เงินสดใจดี จำกัด | D12: 01-12-2021 | E12: นางสาว | F12: สุพรรณี | G12: งามเริง | H12: หนุ่ย | I12: supanneeng@sena.co.th | J12: สำนักงานใหญ่ | K12: ผู้จัดการอาวุโส | L12: ฝ่ายปฏิบัติการสินเชื่อและบัญชี | M12: A | N12: =IFERROR( IF( AND( VLOOKUP(B12, 'รายชื่อพนักงานลาออกพ้นสภาพ'!B:I, 8, FALSE)<>"ยกเลิกลาออก", VLOOKUP(B12, 'รายชื่อพนักงานลาออกพ้นสภาพ'!B:I, 7, FALSE)<=TODAY() ), "ลาออกแล้ว", "" ), "") | O12: {=IFERROR(INDEX(PCRent!C:D, MATCH(F12 & " " & G12, PCRent!A:A & " " & PCRent!B:B, 0)), "")} | Q12: {=IFERROR(INDEX(MonitorRent!C:D, MATCH(F12 & " " & G12, MonitorRent!A:A & " " & MonitorRent!B:B, 0)), "")}
A13: 10 | B13: PC660004 | C13: บริษัท เงินสดใจดี จำกัด | D13: 25-09-2023 | E13: นางสาว | F13: สุพิชญา | G13: ภักดีคง | H13: แพร | I13: supichayap@moneyjaidee.com | J13: สำนักงานใหญ่ | K13: เจ้าหน้าที่สินเชื่อ | L13: ฝ่ายสินเชื่อ | M13: A | N13: =IFERROR( IF( AND( VLOOKUP(B13, 'รายชื่อพนักงานลาออกพ้นสภาพ'!B:I, 8, FALSE)<>"ยกเลิกลาออก", VLOOKUP(B13, 'รายชื่อพนักงานลาออกพ้นสภาพ'!B:I, 7, FALSE)<=TODAY() ), "ลาออกแล้ว", "" ), "") | O13: {=IFERROR(INDEX(PCRent!C:D, MATCH(F13 & " " & G13, PCRent!A:A & " " & PCRent!B:B, 0)), "")} -> SN:MP2E2VRX | P13: Notebook Lenovo Thinkbook G3 14" | Q13: {=IFERROR(INDEX(MonitorRent!C:D, MATCH(F13 & " " & G13, MonitorRent!A:A & " " & MonitorRent!B:B, 0)), "")}
A14: 11 | B14: Test9999 | C14: บริษัท เจ.เอ.แมเนจเม้นท์ จำกัด | D14: 23-06-2025 | E14: นาย | F14: eeeee | G14: wwwww | H14: ถังแตก | I14: sarayutearth2542@gmail.com | K14: ผู้อำนวยการ | L14: ก่อสร้างคอนโด 1 | M14: V | N14: =IFERROR( IF( AND( VLOOKUP(B14, 'รายชื่อพนักงานลาออกพ้นสภาพ'!B:I, 8, FALSE)<>"ยกเลิกลาออก", VLOOKUP(B14, 'รายชื่อพนักงานลาออกพ้นสภาพ'!B:I, 7, FALSE)<=TODAY() ), "ลาออกแล้ว", "" ), "") | O14: {=IFERROR(INDEX(PCRent!C:D, MATCH(F14 & " " & G14, PCRent!A:A & " " & PCRent!B:B, 0)), "")} | Q14: {=IFERROR(INDEX(MonitorRent!C:D, MATCH(F14 & " " & G14, MonitorRent!A:A & " " & MonitorRent!B:B, 0)), "")}
A15: 12 | B15: JA630001 | C15: บริษัท เจ.เอ.แมเนจเม้นท์ จำกัด | D15: 27-05-2013 | E15: นาย | F15: ชูศักดิ์ | G15: ชมชื่น | H15: ชู | I15: Chusakc@sena.co.th | J15: สำนักงานใหญ่ | K15: ช่างทั่วไป | L15: ฝ่ายบริหารทรัพย์สิน | M15: A | N15: =IFERROR( IF( AND( VLOOKUP(B15, 'รายชื่อพนักงานลาออกพ้นสภาพ'!B:I, 8, FALSE)<>"ยกเลิกลาออก", VLOOKUP(B15, 'รายชื่อพนักงานลาออกพ้นสภาพ'!B:I, 7, FALSE)<=TODAY() ), "ลาออกแล้ว", "" ), "") | O15: {=IFERROR(INDEX(PCRent!C:D, MATCH(F15 & " " & G15, PCRent!A:A & " " & PCRent!B:B, 0)), "")} | Q15: {=IFERROR(INDEX(MonitorRent!C:D, MATCH(F15 & " " & G15, MonitorRent!A:A & " " & MonitorRent!B:B, 0)), "")}
A16: 13 | B16: SX670004 | C16: บริษัท เซ็น เอกซ์ จำกัด (มหาชน) | D16: 15-08-2022 | E16: นางสาว | F16: กรณิกา | G16: นรรัตน์ | H16: ไก่ | I16: kornnikan@senxgroup.com | J16: สำนักงานใหญ่ | K16: เจ้าหน้าที่การตลาด | L16: สายงานบริหารการขาย และการตลาดบ้าน 2 | M16: A | N16: =IFERROR( IF( AND( VLOOKUP(B16, 'รายชื่อพนักงานลาออกพ้นสภาพ'!B:I, 8, FALSE)<>"ยกเลิกลาออก", VLOOKUP(B16, 'รายชื่อพนักงานลาออกพ้นสภาพ'!B:I, 7, FALSE)<=TODAY() ), "ลาออกแล้ว", "" ), "") | O16: {=IFERROR(INDEX(PCRent!C:D, MATCH(F16 & " " & G16, PCRent!A:A & " " & PCRent!B:B, 0)), "")} | Q16: {=IFERROR(INDEX(MonitorRent!C:D, MATCH(F16 & " " & G16, MonitorRent!A:A & " " & MonitorRent!B:B, 0)), "")}
A17: 14 | B17: SX670018 | C17: บริษัท เซ็น เอกซ์ จำกัด (มหาชน) | D17: 14-03-2022 | E17: นาย | F17: กฤตยา | G17: บุญธา | H17: แจ็ค | I17: kistayab@senxgroup.com | J17: โครงการ | K17: ผู้จัดการโครงการ | L17: ฝ่ายบริหารโครงการคอนโด และบ้าน 12F | M17: A | N17: =IFERROR( IF( AND( VLOOKUP(B17, 'รายชื่อพนักงานลาออกพ้นสภาพ'!B:I, 8, FALSE)<>"ยกเลิกลาออก", VLOOKUP(B17, 'รายชื่อพนักงานลาออกพ้นสภาพ'!B:I, 7, FALSE)<=TODAY() ), "ลาออกแล้ว", "" ), "") | O17: {=IFERROR(INDEX(PCRent!C:D, MATCH(F17 & " " & G17, PCRent!A:A & " " & PCRent!B:B, 0)), "")} | Q17: {=IFERROR(INDEX(MonitorRent!C:D, MATCH(F17 & " " & G17, MonitorRent!A:A & " " & MonitorRent!B:B, 0)), "")}
A18: 15 | B18: SX670019 | C18: บริษัท เซ็น เอกซ์ จำกัด (มหาชน) | D18: 01-04-2022 | E18: นาย | F18: ก้องภัค | G18: ชิตรัตฐา | H18: ก้อง | I18: kongpakc@senxgroup.com | J18: โครงการ | K18: โฟร์แมนควบคุมงานอาวุโส | L18: ฝ่ายบริหารโครงการคอนโด และบ้าน 12G | M18: A | N18: =IFERROR( IF( AND( VLOOKUP(B18, 'รายชื่อพนักงานลาออกพ้นสภาพ'!B:I, 8, FALSE)<>"ยกเลิกลาออก", VLOOKUP(B18, 'รายชื่อพนักงานลาออกพ้นสภาพ'!B:I, 7, FALSE)<=TODAY() ), "ลาออกแล้ว", "" ), "") | O18: {=IFERROR(INDEX(PCRent!C:D, MATCH(F18 & " " & G18, PCRent!A:A & " " & PCRent!B:B, 0)), "")} | Q18: {=IFERROR(INDEX(MonitorRent!C:D, MATCH(F18 & " " & G18, MonitorRent!A:A & " " & MonitorRent!B:B, 0)), "")}
A19: 16 | B19: SX660015 | C19: บริษัท เซ็น เอกซ์ จำกัด (มหาชน) | D19: 12-05-2021 | E19: นางสาว | F19: กัญญาภัทร์ | G19: พันธ์ประเสริฐ | H19: เดียว | I19: kanyapatp@senxgroup.com | J19: สำนักงานใหญ่ | K19: ผู้ช่วยผู้จัดการ | L19: ฝ่ายบัญชีเจ้าหนี้ | M19: A | N19: =IFERROR( IF( AND( VLOOKUP(B19, 'รายชื่อพนักงานลาออกพ้นสภาพ'!B:I, 8, FALSE)<>"ยกเลิกลาออก", VLOOKUP(B19, 'รายชื่อพนักงานลาออกพ้นสภาพ'!B:I, 7, FALSE)<=TODAY() ), "ลาออกแล้ว", "" ), "") | O19: {=IFERROR(INDEX(PCRent!C:D, MATCH(F19 & " " & G19, PCRent!A:A & " " & PCRent!B:B, 0)), "")} -> SN:JSYNPY3 | P19: ชุดคอมพิวเตอร์ Dell 7010SFF i5-13500 | Q19: {=IFERROR(INDEX(MonitorRent!C:D, MATCH(F19 & " " & G19, MonitorRent!A:A & " " & MonitorRent!B:B, 0)), "")} -> SN:9W652Y3 | R19: จอคอมพิวเตอร์ FHD DELL 24"
A20: 17 | B20: SX670061 | C20: บริษัท เซ็น เอกซ์ จำกัด (มหาชน) | D20: 11-01-2021 | E20: นาย | F20: การันต์ | G20: รัตนะ | H20: อบ | I20: karanr@senxgroup.com | J20: โครงการ | K20: ผู้จัดการโครงการ | L20: ฝ่ายบริหารโครงการคอนโด และบ้าน 12B | M20: A | N20: =IFERROR( IF( AND( VLOOKUP(B20, 'รายชื่อพนักงานลาออกพ้นสภาพ'!B:I, 8, FALSE)<>"ยกเลิกลาออก", VLOOKUP(B20, 'รายชื่อพนักงานลาออกพ้นสภาพ'!B:I, 7, FALSE)<=TODAY() ), "ลาออกแล้ว", "" ), "") | O20: {=IFERROR(INDEX(PCRent!C:D, MATCH(F20 & " " & G20, PCRent!A:A & " " & PCRent!B:B, 0)), "")} | Q20: {=IFERROR(INDEX(MonitorRent!C:D, MATCH(F20 & " " & G20, MonitorRent!A:A & " " & MonitorRent!B:B, 0)), "")}
A21: 18 | B21: SX680003 | C21: บริษัท เซ็น เอกซ์ จำกัด (มหาชน) | D21: 01-02-2024 | E21: นาย | F21: เกษมิน | G21: นาคะประทีป | H21: บุ๋น | I21: kaseminn@senxgroup.com | J21: สำนักงานใหญ่ | K21: ผู้อำนวยการ | L21: สายงานพัฒนาธุรกิจ | M21: A | N21: =IFERROR( IF( AND( VLOOKUP(B21, 'รายชื่อพนักงานลาออกพ้นสภาพ'!B:I, 8, FALSE)<>"ยกเลิกลาออก", VLOOKUP(B21, 'รายชื่อพนักงานลาออกพ้นสภาพ'!B:I, 7, FALSE)<=TODAY() ), "ลาออกแล้ว", "" ), "") | O21: {=IFERROR(INDEX(PCRent!C:D, MATCH(F21 & " " & G21, PCRent!A:A & " " & PCRent!B:B, 0)), "")} | Q21: {=IFERROR(INDEX(MonitorRent!C:D, MATCH(F21 & " " & G21, MonitorRent!A:A & " " & MonitorRent!B:B, 0)), "")}
A22: 19 | B22: SX99999 | C22: บริษัท เซ็น เอกซ์ จำกัด (มหาชน) | D22: 01-01-2004 | E22: ดร. | F22: เกษรา | G22: ธัญลักษณ์ภาคย์ | J22: สำนักงานใหญ่ | K22: กรรมการผู้จัดการ | L22: กลุ่มกรรมการผู้จัดการ | M22: A | N22: =IFERROR( IF( AND( VLOOKUP(B22, 'รายชื่อพนักงานลาออกพ้นสภาพ'!B:I, 8, FALSE)<>"ยกเลิกลาออก", VLOOKUP(B22, 'รายชื่อพนักงานลาออกพ้นสภาพ'!B:I, 7, FALSE)<=TODAY() ), "ลาออกแล้ว", "" ), "") | O22: {=IFERROR(INDEX(PCRent!C:D, MATCH(F22 & " " & G22, PCRent!A:A & " " & PCRent!B:B, 0)), "")} | Q22: {=IFERROR(INDEX(MonitorRent!C:D, MATCH(F22 & " " & G22, MonitorRent!A:A & " " & MonitorRent!B:B, 0)), "")}
A23: 20 | B23: SX660021 | C23: บริษัท เซ็น เอกซ์ จำกัด (มหาชน) | D23: 02-05-2023 | E23: นางสาว | F23: ขวัญฤดี | G23: แดงละอุ่น | H23: ขวัญ | I23: kwanrudeed@senxgroup.com | J23: สำนักงานใหญ่ | K23: เจ้าหน้าที่บัญชีต้นทุน | L23: ฝ่ายบัญชีต้นทุน | M23: A | N23: =IFERROR( IF( AND( VLOOKUP(B23, 'รายชื่อพนักงานลาออกพ้นสภาพ'!B:I, 8, FALSE)<>"ยกเลิกลาออก", VLOOKUP(B23, 'รายชื่อพนักงานลาออกพ้นสภาพ'!B:I, 7, FALSE)<=TODAY() ), "ลาออกแล้ว", "" ), "") | O23: {=IFERROR(INDEX(PCRent!C:D, MATCH(F23 & " " & G23, PCRent!A:A & " " & PCRent!B:B, 0)), "")} | Q23: {=IFERROR(INDEX(MonitorRent!C:D, MATCH(F23 & " " & G23, MonitorRent!A:A & " " & MonitorRent!B:B, 0)), "")}
A24: 21 | B24: SX660029 | C24: บริษัท เซ็น เอกซ์ จำกัด (มหาชน) | D24: 04-07-2022 | E24: นางสาว | F24: จอมขวัญ | G24: ศรศรี | H24: แฟง | I24: jomkwans@senxgroup.com | J24: สำนักงานใหญ่ | K24: เจ้าหน้าที่บัญชีปิดงบการเงิน | L24: ฝ่ายบัญชีทั่วไป | M24: A | N24: =IFERROR( IF( AND( VLOOKUP(B24, 'รายชื่อพนักงานลาออกพ้นสภาพ'!B:I, 8, FALSE)<>"ยกเลิกลาออก", VLOOKUP(B24, 'รายชื่อพนักงานลาออกพ้นสภาพ'!B:I, 7, FALSE)<=TODAY() ), "ลาออกแล้ว", "" ), "") | O24: {=IFERROR(INDEX(PCRent!C:D, MATCH(F24 & " " & G24, PCRent!A:A & " " & PCRent!B:B, 0)), "")} | Q24: {=IFERROR(INDEX(MonitorRent!C:D, MATCH(F24 & " " & G24, MonitorRent!A:A & " " & MonitorRent!B:B, 0)), "")}
A25: 22 | B25: SX670127 | C25: บริษัท เซ็น เอกซ์ จำกัด (มหาชน) | D25: 27-04-2020 | E25: นางสาว | F25: จุฑามาศ | G25: พ่ายนรินทร์ | H25: ยาหยี | I25: jutamatp@senxgroup.com | J25: สำนักงานใหญ่ | K25: เจ้าหน้าที่สื่อสารองค์กรอาวุโส | L25: ฝ่าย Graphic Design | M25: A | N25: =IFERROR( IF( AND( VLOOKUP(B25, 'รายชื่อพนักงานลาออกพ้นสภาพ'!B:I, 8, FALSE)<>"ยกเลิกลาออก", VLOOKUP(B25, 'รายชื่อพนักงานลาออกพ้นสภาพ'!B:I, 7, FALSE)<=TODAY() ), "ลาออกแล้ว", "" ), "") | O25: {=IFERROR(INDEX(PCRent!C:D, MATCH(F25 & " " & G25, PCRent!A:A & " " & PCRent!B:B, 0)), "")} -> SN:MP2ET6A7 | P25: Notebook Lenovo Thinkbook 15.6" | Q25: {=IFERROR(INDEX(MonitorRent!C:D, MATCH(F25 & " " & G25, MonitorRent!A:A & " " & MonitorRent!B:B, 0)), "")}
A26: 23 | B26: SX670168 | C26: บริษัท เซ็น เอกซ์ จำกัด (มหาชน) | D26: 07-06-2024 | E26: นางสาว | F26: จุฑามาศ | G26: จุลหงษ์ | H26: ปุ้มปุ้ย | I26: Juthamartj@senxgroup.com | J26: โครงการ | K26: วิศวกรสนาม | L26: ฝ่ายบริหารโครงการคอนโด และบ้าน 12B | M26: A | N26: =IFERROR( IF( AND( VLOOKUP(B26, 'รายชื่อพนักงานลาออกพ้นสภาพ'!B:I, 8, FALSE)<>"ยกเลิกลาออก", VLOOKUP(B26, 'รายชื่อพนักงานลาออกพ้นสภาพ'!B:I, 7, FALSE)<=TODAY() ), "ลาออกแล้ว", "" ), "") | O26: {=IFERROR(INDEX(PCRent!C:D, MATCH(F26 & " " & G26, PCRent!A:A & " " & PCRent!B:B, 0)), "")} | Q26: {=IFERROR(INDEX(MonitorRent!C:D, MATCH(F26 & " " & G26, MonitorRent!A:A & " " & MonitorRent!B:B, 0)), "")}
A27: 24 | B27: SX670184 | C27: บริษัท เซ็น เอกซ์ จำกัด (มหาชน) | D27: 17-02-2020 | E27: นางสาว | F27: จุฑารัตน์ | G27: ชัยพฤกษ์ | H27: พลอย | I27: jutharatc@senxgroup.com | J27: สำนักงานใหญ่ | K27: เจ้าหน้าที่กราฟฟิค | L27: ฝ่าย Graphic Design | M27: A | N27: =IFERROR( IF( AND( VLOOKUP(B27, 'รายชื่อพนักงานลาออกพ้นสภาพ'!B:I, 8, FALSE)<>"ยกเลิกลาออก", VLOOKUP(B27, 'รายชื่อพนักงานลาออกพ้นสภาพ'!B:I, 7, FALSE)<=TODAY() ), "ลาออกแล้ว", "" ), "") | O27: {=IFERROR(INDEX(PCRent!C:D, MATCH(F27 & " " & G27, PCRent!A:A & " " & PCRent!B:B, 0)), "")} -> SN:C02K507X125F | P27: Apple iMac 24 M4/512 MWV53TH | Q27: {=IFERROR(INDEX(MonitorRent!C:D, MATCH(F27 & " " & G27, MonitorRent!A:A & " " & MonitorRent!B:B, 0)), "")}
A28: 25 | B28: SX660018 | C28: บริษัท เซ็น เอกซ์ จำกัด (มหาชน) | D28: 23-06-2021 | E28: นางสาว | F28: จุไรรัตน์ | G28: แป้นเกลี้ยง | H28: สร้อย | I28: churairatp@senxgroup.com | J28: สำนักงานใหญ่ | K28: เจ้าหน้าที่บัญชีลูกหนี้อาวุโส | L28: ฝ่ายบัญชีลูกหนี้ | M28: A | N28: =IFERROR( IF( AND( VLOOKUP(B28, 'รายชื่อพนักงานลาออกพ้นสภาพ'!B:I, 8, FALSE)<>"ยกเลิกลาออก", VLOOKUP(B28, 'รายชื่อพนักงานลาออกพ้นสภาพ'!B:I, 7, FALSE)<=TODAY() ), "ลาออกแล้ว", "" ), "") | O28: {=IFERROR(INDEX(PCRent!C:D, MATCH(F28 & " " & G28, PCRent!A:A & " " & PCRent!B:B, 0)), "")} -> SN:9SRKQ04 | P28: ชุดคอมพิวเตอร์ Dell 7010SFF i5-13500 | Q28: {=IFERROR(INDEX(MonitorRent!C:D, MATCH(F28 & " " & G28, MonitorRent!A:A & " " & MonitorRent!B:B, 0)), "")} -> SN:9GV9XY3 | R28: จอคอมพิวเตอร์ DELL FHD 24"
A29: 26 | B29: SX670107 | C29: บริษัท เซ็น เอกซ์ จำกัด (มหาชน) | D29: 21-10-2021 | E29: นาย | F29: เจษฎา | G29: วงษ์มาก | H29: เอก | I29: jesadaw@senxgroup.com | J29: โครงการ | K29: ผู้จัดการโครงการ | L29: ฝ่ายบริหารโครงการบ้าน 11B | M29: A | N29: =IFERROR( IF( AND( VLOOKUP(B29, 'รายชื่อพนักงานลาออกพ้นสภาพ'!B:I, 8, FALSE)<>"ยกเลิกลาออก", VLOOKUP(B29, 'รายชื่อพนักงานลาออกพ้นสภาพ'!B:I, 7, FALSE)<=TODAY() ), "ลาออกแล้ว", "" ), "") | O29: {=IFERROR(INDEX(PCRent!C:D, MATCH(F29 & " " & G29, PCRent!A:A & " " & PCRent!B:B, 0)), "")} | Q29: {=IFERROR(INDEX(MonitorRent!C:D, MATCH(F29 & " " & G29, MonitorRent!A:A & " " & MonitorRent!B:B, 0)), "")}
A30: 27 | B30: SX660011 | C30: บริษัท เซ็น เอกซ์ จำกัด (มหาชน) | D30: 16-11-2021 | E30: นางสาว | F30: ชญาณ์นันท์ | G30: โภคสมบัติ | H30: สาว | I30: chayananp@senxgroup.com | J30: สำนักงานใหญ่ | K30: ผู้จัดการ | L30: ฝ่ายบัญชีลูกหนี้ | M30: A | N30: =IFERROR( IF( AND( VLOOKUP(B30, 'รายชื่อพนักงานลาออกพ้นสภาพ'!B:I, 8, FALSE)<>"ยกเลิกลาออก", VLOOKUP(B30, 'รายชื่อพนักงานลาออกพ้นสภาพ'!B:I, 7, FALSE)<=TODAY() ), "ลาออกแล้ว", "" ), "") | O30: {=IFERROR(INDEX(PCRent!C:D, MATCH(F30 & " " & G30, PCRent!A:A & " " & PCRent!B:B, 0)), "")} | Q30: {=IFERROR(INDEX(MonitorRent!C:D, MATCH(F30 & " " & G30, MonitorRent!A:A & " " & MonitorRent!B:B, 0)), "")}
A31: 28 | B31: SX680019 | C31: บริษัท เซ็น เอกซ์ จำกัด (มหาชน) | D31: 03-11-2025 | E31: นางสาว | F31: ชลิดา | G31: นุ้ยดำ | H31: วาวา | I31: chalidan@senxgroup.com | J31: สำนักงานใหญ่ | K31: เจ้าหน้าที่บุคคล | L31: ฝ่าย People Capabillity Development | M31: V | N31: =IFERROR( IF( AND( VLOOKUP(B31, 'รายชื่อพนักงานลาออกพ้นสภาพ'!B:I, 8, FALSE)<>"ยกเลิกลาออก", VLOOKUP(B31, 'รายชื่อพนักงานลาออกพ้นสภาพ'!B:I, 7, FALSE)<=TODAY() ), "ลาออกแล้ว", "" ), "") | O31: {=IFERROR(INDEX(PCRent!C:D, MATCH(F31 & " " & G31, PCRent!A:A & " " & PCRent!B:B, 0)), "")} -> SN:85ZNPY3 | P31: ชุดคอมพิวเตอร์ Dell 7010SFF i5-13500 | Q31: {=IFERROR(INDEX(MonitorRent!C:D, MATCH(F31 & " " & G31, MonitorRent!A:A & " " & MonitorRent!B:B, 0)), "")} -> SN:C7RNYV3 | R31: จอคอมพิวเตอร์ FHD DELL 24"
A32: 29 | B32: SX670157 | C32: บริษัท เซ็น เอกซ์ จำกัด (มหาชน) | D32: 21-05-2024 | E32: นางสาว | F32: ฐานิตา | G32: เกิดผล | H32: นานา | I32: thanitak@senxgroup.com | J32: โครงการ | K32: เจ้าหน้าที่ขายและสินเชื่อ | L32: ฝ่ายบริหารการขายบ้าน 2C | M32: A | N32: =IFERROR( IF( AND( VLOOKUP(B32, 'รายชื่อพนักงานลาออกพ้นสภาพ'!B:I, 8, FALSE)<>"ยกเลิกลาออก", VLOOKUP(B32, 'รายชื่อพนักงานลาออกพ้นสภาพ'!B:I, 7, FALSE)<=TODAY() ), "ลาออกแล้ว", "" ), "") | O32: {=IFERROR(INDEX(PCRent!C:D, MATCH(F32 & " " & G32, PCRent!A:A & " " & PCRent!B:B, 0)), "")} -> SN:MP2AN2CT | P32: Computer All in one AIO 3 27IAP7 | Q32: {=IFERROR(INDEX(MonitorRent!C:D, MATCH(F32 & " " & G32, MonitorRent!A:A & " " & MonitorRent!B:B, 0)), "")}
A33: 30 | B33: SX660027 | C33: บริษัท เซ็น เอกซ์ จำกัด (มหาชน) | D33: 16-06-2022 | E33: นางสาว | F33: ณัฐชยา | G33: งามแป้น | H33: ยุ้ย | I33: nutchayan@senxgroup.com | J33: สำนักงานใหญ่ | K33: เจ้าหน้าที่จัดสรรเงินทุน | L33: ฝ่ายจัดสรรเงินทุน | M33: A | N33: =IFERROR( IF( AND( VLOOKUP(B33, 'รายชื่อพนักงานลาออกพ้นสภาพ'!B:I, 8, FALSE)<>"ยกเลิกลาออก", VLOOKUP(B33, 'รายชื่อพนักงานลาออกพ้นสภาพ'!B:I, 7, FALSE)<=TODAY() ), "ลาออกแล้ว", "" ), "") | O33: {=IFERROR(INDEX(PCRent!C:D, MATCH(F33 & " " & G33, PCRent!A:A & " " & PCRent!B:B, 0)), "")} | Q33: {=IFERROR(INDEX(MonitorRent!C:D, MATCH(F33 & " " & G33, MonitorRent!A:A & " " & MonitorRent!B:B, 0)), "")}
A34: 31 | B34: SX680002 | C34: บริษัท เซ็น เอกซ์ จำกัด (มหาชน) | D34: 09-01-2025 | E34: นางสาว | F34: ณัฐณิชา | G34: สุขกุลา | H34: กิ๊ฟ | I34: natnichas@senxgroup.com | J34: สำนักงานใหญ่ | K34: เจ้าหน้าที่การเงิน | L34: สายงานบัญชีและการเงิน | M34: A | N34: =IFERROR( IF( AND( VLOOKUP(B34, 'รายชื่อพนักงานลาออกพ้นสภาพ'!B:I, 8, FALSE)<>"ยกเลิกลาออก", VLOOKUP(B34, 'รายชื่อพนักงานลาออกพ้นสภาพ'!B:I, 7, FALSE)<=TODAY() ), "ลาออกแล้ว", "" ), "") | O34: {=IFERROR(INDEX(PCRent!C:D, MATCH(F34 & " " & G34, PCRent!A:A & " " & PCRent!B:B, 0)), "")} -> SN:4RRKQ04 | P34: ชุดคอมพิวเตอร์ Dell 7010SFF i5-13500 | Q34: {=IFERROR(INDEX(MonitorRent!C:D, MATCH(F34 & " " & G34, MonitorRent!A:A & " " & MonitorRent!B:B, 0)), "")} -> SN:9GC8XY3 | R34: จอคอมพิวเตอร์ DELL FHD 24"
A35: 32 | B35: SX670048 | C35: บริษัท เซ็น เอกซ์ จำกัด (มหาชน) | D35: 16-10-2023 | E35: นาย | F35: ณัฐพงษ์ | G35: เรืองศรี | H35: นัท | I35: natthaphongr@senxgroup.com | J35: โครงการ | K35: เจ้าหน้าที่ขายและสินเชื่อ | L35: ฝ่ายบริหารการขายบ้าน 2B | M35: A | N35: =IFERROR( IF( AND( VLOOKUP(B35, 'รายชื่อพนักงานลาออกพ้นสภาพ'!B:I, 8, FALSE)<>"ยกเลิกลาออก", VLOOKUP(B35, 'รายชื่อพนักงานลาออกพ้นสภาพ'!B:I, 7, FALSE)<=TODAY() ), "ลาออกแล้ว", "" ), "") | O35: {=IFERROR(INDEX(PCRent!C:D, MATCH(F35 & " " & G35, PCRent!A:A & " " & PCRent!B:B, 0)), "")} -> SN:MP2AN2CN | P35: Computer All in one AIO 3 27IAP7 | Q35: {=IFERROR(INDEX(MonitorRent!C:D, MATCH(F35 & " " & G35, MonitorRent!A:A & " " & MonitorRent!B:B, 0)), "")} -> SN:8Z49XY3 | R35: จอคอมพิวเตอร์ FHD DELL 24"
A36: 33 | B36: SX670020 | C36: บริษัท เซ็น เอกซ์ จำกัด (มหาชน) | D36: 01-11-2022 | E36: นางสาว | F36: ณัฐพร | G36: ชยานันทสิริ | H36: อ้อ | I36: natthapornc@senxgroup.com | J36: โครงการ | K36: เจ้าหน้าที่ธุรการโครงการอาวุโส | L36: ฝ่ายบริหารโครงการคอนโด และบ้าน 12G | M36: A | N36: =IFERROR( IF( AND( VLOOKUP(B36, 'รายชื่อพนักงานลาออกพ้นสภาพ'!B:I, 8, FALSE)<>"ยกเลิกลาออก", VLOOKUP(B36, 'รายชื่อพนักงานลาออกพ้นสภาพ'!B:I, 7, FALSE)<=TODAY() ), "ลาออกแล้ว", "" ), "") | O36: {=IFERROR(INDEX(PCRent!C:D, MATCH(F36 & " " & G36, PCRent!A:A & " " & PCRent!B:B, 0)), "")} | Q36: {=IFERROR(INDEX(MonitorRent!C:D, MATCH(F36 & " " & G36, MonitorRent!A:A & " " & MonitorRent!B:B, 0)), "")}
A37: 34 | B37: SX670017 | C37: บริษัท เซ็น เอกซ์ จำกัด (มหาชน) | D37: 10-07-2023 | E37: นาย | F37: ตรึก | G37: โตบัณฑิตย์ | H37: มด | I37: trukt@senxgroup.com | J37: โครงการ | K37: โฟร์แมนควบคุมงานอาวุโส | L37: ฝ่ายบริหารโครงการคอนโด และบ้าน 12G | M37: A | N37: =IFERROR( IF( AND( VLOOKUP(B37, 'รายชื่อพนักงานลาออกพ้นสภาพ'!B:I, 8, FALSE)<>"ยกเลิกลาออก", VLOOKUP(B37, 'รายชื่อพนักงานลาออกพ้นสภาพ'!B:I, 7, FALSE)<=TODAY() ), "ลาออกแล้ว", "" ), "") -> ลาออกแล้ว | O37: {=IFERROR(INDEX(PCRent!C:D, MATCH(F37 & " " & G37, PCRent!A:A & " " & PCRent!B:B, 0)), "")} | Q37: {=IFERROR(INDEX(MonitorRent!C:D, MATCH(F37 & " " & G37, MonitorRent!A:A & " " & MonitorRent!B:B, 0)), "")}
A38: 35 | B38: SX670122 | C38: บริษัท เซ็น เอกซ์ จำกัด (มหาชน) | D38: 01-04-2021 | E38: นาย | F38: ถาวร | G38: ประเสริฐแก้ว | H38: โย | I38: thavornp@senxgroup.com | J38: สำนักงานใหญ่ | K38: ผู้จัดการ | L38: ฝ่ายเทคโนโลยีสารสนเทศ | M38: A | N38: =IFERROR( IF( AND( VLOOKUP(B38, 'รายชื่อพนักงานลาออกพ้นสภาพ'!B:I, 8, FALSE)<>"ยกเลิกลาออก", VLOOKUP(B38, 'รายชื่อพนักงานลาออกพ้นสภาพ'!B:I, 7, FALSE)<=TODAY() ), "ลาออกแล้ว", "" ), "") | O38: {=IFERROR(INDEX(PCRent!C:D, MATCH(F38 & " " & G38, PCRent!A:A & " " & PCRent!B:B, 0)), "")} | Q38: {=IFERROR(INDEX(MonitorRent!C:D, MATCH(F38 & " " & G38, MonitorRent!A:A & " " & MonitorRent!B:B, 0)), "")}
A39: 36 | B39: SX660044 | C39: บริษัท เซ็น เอกซ์ จำกัด (มหาชน) | D39: 02-08-2021 | E39: นาย | F39: ทัศนัย | G39: ว่องวิกย์การ | J39: สำนักงานใหญ่ | K39: ผู้ช่วยกรรมการผู้จัดการ | L39: กลุ่มกรรมการผู้จัดการ | M39: A | N39: =IFERROR( IF( AND( VLOOKUP(B39, 'รายชื่อพนักงานลาออกพ้นสภาพ'!B:I, 8, FALSE)<>"ยกเลิกลาออก", VLOOKUP(B39, 'รายชื่อพนักงานลาออกพ้นสภาพ'!B:I, 7, FALSE)<=TODAY() ), "ลาออกแล้ว", "" ), "") | O39: {=IFERROR(INDEX(PCRent!C:D, MATCH(F39 & " " & G39, PCRent!A:A & " " & PCRent!B:B, 0)), "")} | Q39: {=IFERROR(INDEX(MonitorRent!C:D, MATCH(F39 & " " & G39, MonitorRent!A:A & " " & MonitorRent!B:B, 0)), "")}
A40: 37 | B40: SX680015 | C40: บริษัท เซ็น เอกซ์ จำกัด (มหาชน) | D40: 18-08-2025 | E40: นางสาว | F40: ทิพย์สุดา | G40: เพชรเจริญ | H40: ใบหม่อน | I40: tipsudap@senxgroup.com | J40: สำนักงานใหญ่ | K40: เจ้าหน้าที่ธุรการ | L40: ฝ่ายตรวจสอบและสนับสนุนองค์กร | M40: A | N40: =IFERROR( IF( AND( VLOOKUP(B40, 'รายชื่อพนักงานลาออกพ้นสภาพ'!B:I, 8, FALSE)<>"ยกเลิกลาออก", VLOOKUP(B40, 'รายชื่อพนักงานลาออกพ้นสภาพ'!B:I, 7, FALSE)<=TODAY() ), "ลาออกแล้ว", "" ), "") | O40: {=IFERROR(INDEX(PCRent!C:D, MATCH(F40 & " " & G40, PCRent!A:A & " " & PCRent!B:B, 0)), "")} -> SN:MP2M8GAM | P40: Notebook Lenovo Thinkbook G4 14" | Q40: {=IFERROR(INDEX(MonitorRent!C:D, MATCH(F40 & " " & G40, MonitorRent!A:A & " " & MonitorRent!B:B, 0)), "")}
A41: 38 | B41: SX660005 | C41: บริษัท เซ็น เอกซ์ จำกัด (มหาชน) | D41: 18-06-2012 | E41: นางสาว | F41: ธิดารัตน์ | G41: พัฒน์ทอง | H41: โอชิน | I41: tidaratp@senxgroup.com | J41: สำนักงานใหญ่ | K41: ผู้ช่วยประธานเจ้าหน้าที่บริหาร | L41: สำนักประธานเจ้าหน้าที่บริหาร (SENX) | M41: A | N41: =IFERROR( IF( AND( VLOOKUP(B41, 'รายชื่อพนักงานลาออกพ้นสภาพ'!B:I, 8, FALSE)<>"ยกเลิกลาออก", VLOOKUP(B41, 'รายชื่อพนักงานลาออกพ้นสภาพ'!B:I, 7, FALSE)<=TODAY() ), "ลาออกแล้ว", "" ), "") | O41: {=IFERROR(INDEX(PCRent!C:D, MATCH(F41 & " " & G41, PCRent!A:A & " " & PCRent!B:B, 0)), "")} | Q41: {=IFERROR(INDEX(MonitorRent!C:D, MATCH(F41 & " " & G41, MonitorRent!A:A & " " & MonitorRent!B:B, 0)), "")}
A42: 39 | B42: SX670060 | C42: บริษัท เซ็น เอกซ์ จำกัด (มหาชน) | D42: 01-03-2021 | E42: นาย | F42: ธิติ | G42: ศรีชาวนา | H42: หม่ำ | I42: thitis@senxgroup.com | J42: โครงการ | K42: โฟร์แมนควบคุมงาน | L42: ฝ่ายบริหารโครงการคอนโด และบ้าน 12B | M42: A | N42: =IFERROR( IF( AND( VLOOKUP(B42, 'รายชื่อพนักงานลาออกพ้นสภาพ'!B:I, 8, FALSE)<>"ยกเลิกลาออก", VLOOKUP(B42, 'รายชื่อพนักงานลาออกพ้นสภาพ'!B:I, 7, FALSE)<=TODAY() ), "ลาออกแล้ว", "" ), "") | O42: {=IFERROR(INDEX(PCRent!C:D, MATCH(F42 & " " & G42, PCRent!A:A & " " & PCRent!B:B, 0)), "")} | Q42: {=IFERROR(INDEX(MonitorRent!C:D, MATCH(F42 & " " & G42, MonitorRent!A:A & " " & MonitorRent!B:B, 0)), "")}
A43: 40 | B43: SX670021 | C43: บริษัท เซ็น เอกซ์ จำกัด (มหาชน) | D43: 13-12-2022 | E43: นาย | F43: นพพร | G43: ก้อนคำมา | H43: โบ้ท | I43: nopporng@senxgroup.com | J43: โครงการ | K43: วิศวกรโครงการ | L43: ฝ่ายบริหารโครงการคอนโด และบ้าน 12G | M43: A | N43: =IFERROR( IF( AND( VLOOKUP(B43, 'รายชื่อพนักงานลาออกพ้นสภาพ'!B:I, 8, FALSE)<>"ยกเลิกลาออก", VLOOKUP(B43, 'รายชื่อพนักงานลาออกพ้นสภาพ'!B:I, 7, FALSE)<=TODAY() ), "ลาออกแล้ว", "" ), "") | O43: {=IFERROR(INDEX(PCRent!C:D, MATCH(F43 & " " & G43, PCRent!A:A & " " & PCRent!B:B, 0)), "")} -> SN:MP2EJ0KJ | P43: Notebook Lenovo Thinkbook G3 14" | Q43: {=IFERROR(INDEX(MonitorRent!C:D, MATCH(F43 & " " & G43, MonitorRent!A:A & " " & MonitorRent!B:B, 0)), "")}
A44: 41 | B44: SX670046 | C44: บริษัท เซ็น เอกซ์ จำกัด (มหาชน) | D44: 08-05-2023 | E44: นาย | F44: นพสิทธิ์ | G44: เตโช | H44: หนึ่ง | I44: noppasitt@senxgroup.com | J44: โครงการ | K44: ผู้อำนวยการ | L44: สายงานบริหารโครงการคอนโดและบ้าน 13 | M44: A | N44: =IFERROR( IF( AND( VLOOKUP(B44, 'รายชื่อพนักงานลาออกพ้นสภาพ'!B:I, 8, FALSE)<>"ยกเลิกลาออก", VLOOKUP(B44, 'รายชื่อพนักงานลาออกพ้นสภาพ'!B:I, 7, FALSE)<=TODAY() ), "ลาออกแล้ว", "" ), "") | O44: {=IFERROR(INDEX(PCRent!C:D, MATCH(F44 & " " & G44, PCRent!A:A & " " & PCRent!B:B, 0)), "")} | Q44: {=IFERROR(INDEX(MonitorRent!C:D, MATCH(F44 & " " & G44, MonitorRent!A:A & " " & MonitorRent!B:B, 0)), "")}
A45: 42 | B45: SX670053 | C45: บริษัท เซ็น เอกซ์ จำกัด (มหาชน) | D45: 16-11-2023 | E45: นาย | F45: นภัทร | G45: มัชฉิมวงศ์ | H45: ขวัญ | I45: naphatm@senxgroup.com | J45: โครงการ | K45: ผู้จัดการโครงการ | L45: ฝ่ายบริหารโครงการคอนโด และบ้าน 12A | M45: A | N45: =IFERROR( IF( AND( VLOOKUP(B45, 'รายชื่อพนักงานลาออกพ้นสภาพ'!B:I, 8, FALSE)<>"ยกเลิกลาออก", VLOOKUP(B45, 'รายชื่อพนักงานลาออกพ้นสภาพ'!B:I, 7, FALSE)<=TODAY() ), "ลาออกแล้ว", "" ), "") | O45: {=IFERROR(INDEX(PCRent!C:D, MATCH(F45 & " " & G45, PCRent!A:A & " " & PCRent!B:B, 0)), "")} -> SN:6S4XMX3 | P45: Notebook DELL Inspiron 15.6 นิ้ว i7 - 256GB | Q45: {=IFERROR(INDEX(MonitorRent!C:D, MATCH(F45 & " " & G45, MonitorRent!A:A & " " & MonitorRent!B:B, 0)), "")}
A46: 43 | B46: SX680001 | C46: บริษัท เซ็น เอกซ์ จำกัด (มหาชน) | D46: 02-01-2025 | E46: นางสาว | F46: นันทนิช | G46: กล้าแข็ง | H46: นัน | I46: nantanitg@senxgroup.com | J46: สำนักงานใหญ่ | K46: เจ้าหน้าที่บัญชีลูกหนี้ | L46: ฝ่ายบัญชีลูกหนี้ | M46: A | N46: =IFERROR( IF( AND( VLOOKUP(B46, 'รายชื่อพนักงานลาออกพ้นสภาพ'!B:I, 8, FALSE)<>"ยกเลิกลาออก", VLOOKUP(B46, 'รายชื่อพนักงานลาออกพ้นสภาพ'!B:I, 7, FALSE)<=TODAY() ), "ลาออกแล้ว", "" ), "") | O46: {=IFERROR(INDEX(PCRent!C:D, MATCH(F46 & " " & G46, PCRent!A:A & " " & PCRent!B:B, 0)), "")} -> SN:2RRKQ04 | P46: ชุดคอมพิวเตอร์ Dell 7010SFF i5-13500 | Q46: {=IFERROR(INDEX(MonitorRent!C:D, MATCH(F46 & " " & G46, MonitorRent!A:A & " " & MonitorRent!B:B, 0)), "")} -> SN:91X7XY3 | R46: จอคอมพิวเตอร์ DELL FHD 24"
A47: 44 | B47: SX670123 | C47: บริษัท เซ็น เอกซ์ จำกัด (มหาชน) | D47: 14-11-2009 | E47: นางสาว | F47: นันทิดา | G47: สิงหัส | H47: ดา | I47: nuntidas@senxgroup.com | J47: สำนักงานใหญ่ | K47: ผู้จัดการ | L47: ฝ่ายตรวจสอบและสนับสนุนองค์กร | M47: A | N47: =IFERROR( IF( AND( VLOOKUP(B47, 'รายชื่อพนักงานลาออกพ้นสภาพ'!B:I, 8, FALSE)<>"ยกเลิกลาออก", VLOOKUP(B47, 'รายชื่อพนักงานลาออกพ้นสภาพ'!B:I, 7, FALSE)<=TODAY() ), "ลาออกแล้ว", "" ), "") | O47: {=IFERROR(INDEX(PCRent!C:D, MATCH(F47 & " " & G47, PCRent!A:A & " " & PCRent!B:B, 0)), "")} -> SN:MP2E0NBS | P47: Notebook Lenovo Thinkbook G3 14" | Q47: {=IFERROR(INDEX(MonitorRent!C:D, MATCH(F47 & " " & G47, MonitorRent!A:A & " " & MonitorRent!B:B, 0)), "")}
A48: 45 | B48: SX670164 | C48: บริษัท เซ็น เอกซ์ จำกัด (มหาชน) | D48: 04-06-2024 | E48: นางสาว | F48: น้ำฝน | G48: รงสุวรรณาภรณ์ | H48: ฝน | I48: numfonr@senxgroup.com | J48: โครงการ | K48: เจ้าหน้าที่ขายและสินเชื่อ | L48: ฝ่ายบริหารการขายบ้าน 1C | M48: A | N48: =IFERROR( IF( AND( VLOOKUP(B48, 'รายชื่อพนักงานลาออกพ้นสภาพ'!B:I, 8, FALSE)<>"ยกเลิกลาออก", VLOOKUP(B48, 'รายชื่อพนักงานลาออกพ้นสภาพ'!B:I, 7, FALSE)<=TODAY() ), "ลาออกแล้ว", "" ), "") | O48: {=IFERROR(INDEX(PCRent!C:D, MATCH(F48 & " " & G48, PCRent!A:A & " " & PCRent!B:B, 0)), "")} | Q48: {=IFERROR(INDEX(MonitorRent!C:D, MATCH(F48 & " " & G48, MonitorRent!A:A & " " & MonitorRent!B:B, 0)), "")}
A49: 46 | B49: SX670026 | C49: บริษัท เซ็น เอกซ์ จำกัด (มหาชน) | D49: 16-10-2023 | E49: นาย | F49: บุญสม | G49: สอาดชัย | H49: ปาน | I49: boonsoms@senxgroup.com | J49: โครงการ | K49: โฟร์แมนควบคุมงานอาวุโส | L49: ฝ่ายบริหารโครงการคอนโด และบ้าน 12G | M49: A | N49: =IFERROR( IF( AND( VLOOKUP(B49, 'รายชื่อพนักงานลาออกพ้นสภาพ'!B:I, 8, FALSE)<>"ยกเลิกลาออก", VLOOKUP(B49, 'รายชื่อพนักงานลาออกพ้นสภาพ'!B:I, 7, FALSE)<=TODAY() ), "ลาออกแล้ว", "" ), "") | O49: {=IFERROR(INDEX(PCRent!C:D, MATCH(F49 & " " & G49, PCRent!A:A & " " & PCRent!B:B, 0)), "")} | Q49: {=IFERROR(INDEX(MonitorRent!C:D, MATCH(F49 & " " & G49, MonitorRent!A:A & " " & MonitorRent!B:B, 0)), "")}
A50: 47 | B50: SX670054 | C50: บริษัท เซ็น เอกซ์ จำกัด (มหาชน) | D50: 08-02-2021 | E50: นาง | F50: บุษกร | G50: วิเชียรกุล | H50: เอ๋ | I50: bussakornw@senxgroup.com | J50: โครงการ | K50: พนักงานธุรการโครงการ | L50: ฝ่ายบริหารโครงการคอนโด และบ้าน 12B | M50: A | N50: =IFERROR( IF( AND( VLOOKUP(B50, 'รายชื่อพนักงานลาออกพ้นสภาพ'!B:I, 8, FALSE)<>"ยกเลิกลาออก", VLOOKUP(B50, 'รายชื่อพนักงานลาออกพ้นสภาพ'!B:I, 7, FALSE)<=TODAY() ), "ลาออกแล้ว", "" ), "") | O50: {=IFERROR(INDEX(PCRent!C:D, MATCH(F50 & " " & G50, PCRent!A:A & " " & PCRent!B:B, 0)), "")} -> SN:83RD314 | P50: ชุดคอมพิวเตอร์ Dell 7010SFF i5-13500 | Q50: {=IFERROR(INDEX(MonitorRent!C:D, MATCH(F50 & " " & G50, MonitorRent!A:A & " " & MonitorRent!B:B, 0)), "")} -> SN:7RZVGZ3 | R50: จอคอมพิวเตอร์ DELL FHD 24"
A51: 48 | B51: SX670183 | C51: บริษัท เซ็น เอกซ์ จำกัด (มหาชน) | D51: 02-12-2024 | E51: นาย | F51: ปกรณ์ | G51: พรหโมปกรณ์ | H51: นาว | I51: pakornp@senxgroup.com | J51: สำนักงานใหญ่ | K51: เจ้าหน้าที่สรรหาบุคลากรอาวุโส | L51: ฝ่ายสรรหาและคัดเลือก | M51: A | N51: =IFERROR( IF( AND( VLOOKUP(B51, 'รายชื่อพนักงานลาออกพ้นสภาพ'!B:I, 8, FALSE)<>"ยกเลิกลาออก", VLOOKUP(B51, 'รายชื่อพนักงานลาออกพ้นสภาพ'!B:I, 7, FALSE)<=TODAY() ), "ลาออกแล้ว", "" ), "") | O51: {=IFERROR(INDEX(PCRent!C:D, MATCH(F51 & " " & G51, PCRent!A:A & " " & PCRent!B:B, 0)), "")} | Q51: {=IFERROR(INDEX(MonitorRent!C:D, MATCH(F51 & " " & G51, MonitorRent!A:A & " " & MonitorRent!B:B, 0)), "")}
A52: 49 | B52: SX670108 | C52: บริษัท เซ็น เอกซ์ จำกัด (มหาชน) | D52: 18-07-2022 | E52: นาย | F52: ประเสริฐชัย | G52: เพ็ชร์รักษ์ | H52: เค้ก | I52: prasertchaip@senxgroup.com | J52: โครงการ | K52: วิศวกรโครงการ | L52: ฝ่ายบริหารโครงการคอนโดและบ้าน 12E | M52: A | N52: =IFERROR( IF( AND( VLOOKUP(B52, 'รายชื่อพนักงานลาออกพ้นสภาพ'!B:I, 8, FALSE)<>"ยกเลิกลาออก", VLOOKUP(B52, 'รายชื่อพนักงานลาออกพ้นสภาพ'!B:I, 7, FALSE)<=TODAY() ), "ลาออกแล้ว", "" ), "") | O52: {=IFERROR(INDEX(PCRent!C:D, MATCH(F52 & " " & G52, PCRent!A:A & " " & PCRent!B:B, 0)), "")} -> SN:F1QD314 | P52: ชุดคอมพิวเตอร์ Dell 7010SFF i5-13500 | Q52: {=IFERROR(INDEX(MonitorRent!C:D, MATCH(F52 & " " & G52, MonitorRent!A:A & " " & MonitorRent!B:B, 0)), "")} -> SN:BKW5HZ3 | R52: จอคอมพิวเตอร์ DELL FHD 24"
A53: 50 | B53: SX680018 | C53: บริษัท เซ็น เอกซ์ จำกัด (มหาชน) | D53: 01-12-2023 | E53: นาย | F53: ปรัชญา | G53: ไชยเมืองชื่น | H53: กอล์ฟ | J53: โครงการ | K53: พนักงานทั่วไป | L53: ฝ่ายแรงงานสัมพันธ์ | M53: A | N53: =IFERROR( IF( AND( VLOOKUP(B53, 'รายชื่อพนักงานลาออกพ้นสภาพ'!B:I, 8, FALSE)<>"ยกเลิกลาออก", VLOOKUP(B53, 'รายชื่อพนักงานลาออกพ้นสภาพ'!B:I, 7, FALSE)<=TODAY() ), "ลาออกแล้ว", "" ), "") | O53: {=IFERROR(INDEX(PCRent!C:D, MATCH(F53 & " " & G53, PCRent!A:A & " " & PCRent!B:B, 0)), "")} | Q53: {=IFERROR(INDEX(MonitorRent!C:D, MATCH(F53 & " " & G53, MonitorRent!A:A & " " & MonitorRent!B:B, 0)), "")}
A54: 51 | B54: SX670040 | C54: บริษัท เซ็น เอกซ์ จำกัด (มหาชน) | D54: 16-11-2021 | E54: นาย | F54: ปัญญา | G54: สรสิทธิ์ | H54: บอย | I54: punyas@senxgroup.com | J54: โครงการ | K54: วิศวกรโครงการ | L54: ฝ่ายบริหารโครงการคอนโด และบ้าน 12A | M54: A | N54: =IFERROR( IF( AND( VLOOKUP(B54, 'รายชื่อพนักงานลาออกพ้นสภาพ'!B:I, 8, FALSE)<>"ยกเลิกลาออก", VLOOKUP(B54, 'รายชื่อพนักงานลาออกพ้นสภาพ'!B:I, 7, FALSE)<=TODAY() ), "ลาออกแล้ว", "" ), "") | O54: {=IFERROR(INDEX(PCRent!C:D, MATCH(F54 & " " & G54, PCRent!A:A & " " & PCRent!B:B, 0)), "")} | Q54: {=IFERROR(INDEX(MonitorRent!C:D, MATCH(F54 & " " & G54, MonitorRent!A:A & " " & MonitorRent!B:B, 0)), "")}
A55: 52 | B55: SX670073 | C55: บริษัท เซ็น เอกซ์ จำกัด (มหาชน) | D55: 17-04-2023 | E55: นางสาว | F55: ปาจรีย์ | G55: เศรษฐพานิช | H55: หนึ่ง | I55: pajarees@senxgroup.com | J55: โครงการ | K55: หัวหน้างานขายและสินเชื่อ | L55: ฝ่ายบริหารการขายบ้าน 1B | M55: A | N55: =IFERROR( IF( AND( VLOOKUP(B55, 'รายชื่อพนักงานลาออกพ้นสภาพ'!B:I, 8, FALSE)<>"ยกเลิกลาออก", VLOOKUP(B55, 'รายชื่อพนักงานลาออกพ้นสภาพ'!B:I, 7, FALSE)<=TODAY() ), "ลาออกแล้ว", "" ), "") | O55: {=IFERROR(INDEX(PCRent!C:D, MATCH(F55 & " " & G55, PCRent!A:A & " " & PCRent!B:B, 0)), "")} -> SN:MP2AN2C1 | P55: Computer All in one AIO 3 27IAP7 | Q55: {=IFERROR(INDEX(MonitorRent!C:D, MATCH(F55 & " " & G55, MonitorRent!A:A & " " & MonitorRent!B:B, 0)), "")}
A56: 53 | B56: SX670078 | C56: บริษัท เซ็น เอกซ์ จำกัด (มหาชน) | D56: 28-03-2022 | E56: นางสาว | F56: ปาลิดา | G56: ปิฉิมพลี | H56: แป้น | I56: palidap@senxgroup.com | J56: โครงการ | K56: ผู้จัดการ | L56: ฝ่ายบริหารการขายบ้าน 1A | M56: A | N56: =IFERROR( IF( AND( VLOOKUP(B56, 'รายชื่อพนักงานลาออกพ้นสภาพ'!B:I, 8, FALSE)<>"ยกเลิกลาออก", VLOOKUP(B56, 'รายชื่อพนักงานลาออกพ้นสภาพ'!B:I, 7, FALSE)<=TODAY() ), "ลาออกแล้ว", "" ), "") | O56: {=IFERROR(INDEX(PCRent!C:D, MATCH(F56 & " " & G56, PCRent!A:A & " " & PCRent!B:B, 0)), "")} -> SN:MP2AN2CV | P56: Computer All in one AIO 3 27IAP7 | Q56: {=IFERROR(INDEX(MonitorRent!C:D, MATCH(F56 & " " & G56, MonitorRent!A:A & " " & MonitorRent!B:B, 0)), "")}
A57: 54 | B57: SX670025 | C57: บริษัท เซ็น เอกซ์ จำกัด (มหาชน) | D57: 01-06-2023 | E57: นางสาว | F57: ปิติลักษณ์ | G57: ปูรณะวิบูรณ์ | H57: ยีนส์ | I57: pitiluckp@senxgroup.com | J57: โครงการ | K57: เจ้าหน้าที่ธุรการโครงการอาวุโส | L57: ฝ่ายบริหารโครงการคอนโด และบ้าน 12G | M57: A | N57: =IFERROR( IF( AND( VLOOKUP(B57, 'รายชื่อพนักงานลาออกพ้นสภาพ'!B:I, 8, FALSE)<>"ยกเลิกลาออก", VLOOKUP(B57, 'รายชื่อพนักงานลาออกพ้นสภาพ'!B:I, 7, FALSE)<=TODAY() ), "ลาออกแล้ว", "" ), "") | O57: {=IFERROR(INDEX(PCRent!C:D, MATCH(F57 & " " & G57, PCRent!A:A & " " & PCRent!B:B, 0)), "")} | Q57: {=IFERROR(INDEX(MonitorRent!C:D, MATCH(F57 & " " & G57, MonitorRent!A:A & " " & MonitorRent!B:B, 0)), "")}
A58: 55 | B58: SX680017 | C58: บริษัท เซ็น เอกซ์ จำกัด (มหาชน) | D58: 01-10-2025 | E58: นางสาว | F58: ปุณยนุช | G58: สืบนุกูล | H58: อ้น | I58: poonyanuchs@senxgroup.com | J58: สำนักงานใหญ่ | K58: เจ้าหน้าที่บัญชีลูกหนี้ | L58: ฝ่ายบัญชีลูกหนี้ | M58: V | N58: =IFERROR( IF( AND( VLOOKUP(B58, 'รายชื่อพนักงานลาออกพ้นสภาพ'!B:I, 8, FALSE)<>"ยกเลิกลาออก", VLOOKUP(B58, 'รายชื่อพนักงานลาออกพ้นสภาพ'!B:I, 7, FALSE)<=TODAY() ), "ลาออกแล้ว", "" ), "") -> ลาออกแล้ว | O58: {=IFERROR(INDEX(PCRent!C:D, MATCH(F58 & " " & G58, PCRent!A:A & " " & PCRent!B:B, 0)), "")} | Q58: {=IFERROR(INDEX(MonitorRent!C:D, MATCH(F58 & " " & G58, MonitorRent!A:A & " " & MonitorRent!B:B, 0)), "")}
A59: 56 | B59: SX670067 | C59: บริษัท เซ็น เอกซ์ จำกัด (มหาชน) | D59: 01-02-2021 | E59: นางสาว | F59: พงษ์นภา | G59: เสนาเลี้ยง | H59: กระต่าย | I59: pongnapas@senxgroup.com | J59: โครงการ | K59: หัวหน้างานขายและสินเชื่อ | L59: ฝ่ายบริหารการขายบ้าน 2C | M59: A | N59: =IFERROR( IF( AND( VLOOKUP(B59, 'รายชื่อพนักงานลาออกพ้นสภาพ'!B:I, 8, FALSE)<>"ยกเลิกลาออก", VLOOKUP(B59, 'รายชื่อพนักงานลาออกพ้นสภาพ'!B:I, 7, FALSE)<=TODAY() ), "ลาออกแล้ว", "" ), "") | O59: {=IFERROR(INDEX(PCRent!C:D, MATCH(F59 & " " & G59, PCRent!A:A & " " & PCRent!B:B, 0)), "")} -> SN:5YYNPY3 | P59: ชุดคอมพิวเตอร์ Dell 7010SFF i5-13500 | Q59: {=IFERROR(INDEX(MonitorRent!C:D, MATCH(F59 & " " & G59, MonitorRent!A:A & " " & MonitorRent!B:B, 0)), "")} -> SN:C7KNYV3 | R59: จอคอมพิวเตอร์ FHD DELL 24"
A60: 57 | B60: SX670047 | C60: บริษัท เซ็น เอกซ์ จำกัด (มหาชน) | D60: 11-03-2019 | E60: นาย | F60: พชร | G60: ภู่ประไพ | H60: เดฟ | I60: patcharap@senxgroup.com | J60: โครงการ | K60: โฟร์แมนควบคุมงาน | L60: ฝ่ายบริหารโครงการคอนโด และบ้าน 12D | M60: A | N60: =IFERROR( IF( AND( VLOOKUP(B60, 'รายชื่อพนักงานลาออกพ้นสภาพ'!B:I, 8, FALSE)<>"ยกเลิกลาออก", VLOOKUP(B60, 'รายชื่อพนักงานลาออกพ้นสภาพ'!B:I, 7, FALSE)<=TODAY() ), "ลาออกแล้ว", "" ), "") | O60: {=IFERROR(INDEX(PCRent!C:D, MATCH(F60 & " " & G60, PCRent!A:A & " " & PCRent!B:B, 0)), "")} | Q60: {=IFERROR(INDEX(MonitorRent!C:D, MATCH(F60 & " " & G60, MonitorRent!A:A & " " & MonitorRent!B:B, 0)), "")}
A61: 58 | B61: SX660069 | C61: บริษัท เซ็น เอกซ์ จำกัด (มหาชน) | D61: 10-07-2023 | E61: นางสาว | F61: พรรณนิดา | G61: จารสาร | H61: กิ๊ฟ | I61: punnidaj@senxgroup.com | J61: สำนักงานใหญ่ | K61: เจ้าหน้าที่บัญชีเจ้าหนี้ | L61: ฝ่ายบัญชีเจ้าหนี้ (AP) | M61: A | N61: =IFERROR( IF( AND( VLOOKUP(B61, 'รายชื่อพนักงานลาออกพ้นสภาพ'!B:I, 8, FALSE)<>"ยกเลิกลาออก", VLOOKUP(B61, 'รายชื่อพนักงานลาออกพ้นสภาพ'!B:I, 7, FALSE)<=TODAY() ), "ลาออกแล้ว", "" ), "") | O61: {=IFERROR(INDEX(PCRent!C:D, MATCH(F61 & " " & G61, PCRent!A:A & " " & PCRent!B:B, 0)), "")} -> SN:7T8BXW3 | P61: ชุดคอมพิวเตอร์ Dell 7010SFF i5-13500 | Q61: {=IFERROR(INDEX(MonitorRent!C:D, MATCH(F61 & " " & G61, MonitorRent!A:A & " " & MonitorRent!B:B, 0)), "")} -> SN:F937SS3 | R61: จอคอมพิวเตอร์ FHD DELL 24"
A62: 59 | B62: SX670148 | C62: บริษัท เซ็น เอกซ์ จำกัด (มหาชน) | D62: 13-03-2023 | E62: นางสาว | F62: พัชรินทร์ | G62: สาวิวัฒน์ | H62: พัช | I62: patcharins@senxgroup.com | J62: สำนักงานใหญ่ | K62: เจ้าหน้าที่บัญชีทั่วไป | L62: ฝ่ายบัญชีทั่วไป | M62: A | N62: =IFERROR( IF( AND( VLOOKUP(B62, 'รายชื่อพนักงานลาออกพ้นสภาพ'!B:I, 8, FALSE)<>"ยกเลิกลาออก", VLOOKUP(B62, 'รายชื่อพนักงานลาออกพ้นสภาพ'!B:I, 7, FALSE)<=TODAY() ), "ลาออกแล้ว", "" ), "") | O62: {=IFERROR(INDEX(PCRent!C:D, MATCH(F62 & " " & G62, PCRent!A:A & " " & PCRent!B:B, 0)), "")} | Q62: {=IFERROR(INDEX(MonitorRent!C:D, MATCH(F62 & " " & G62, MonitorRent!A:A & " " & MonitorRent!B:B, 0)), "")}
A63: 60 | B63: SX660031 | C63: บริษัท เซ็น เอกซ์ จำกัด (มหาชน) | D63: 29-08-2022 | E63: นางสาว | F63: พัชรี | G63: รัตนะดี | H63: พิม | I63: phatchareer@senxgroup.com | J63: สำนักงานใหญ่ | K63: เจ้าหน้าที่บัญชีเจ้าหนี้ | L63: ฝ่ายบัญชีเจ้าหนี้ (CA) | M63: A | N63: =IFERROR( IF( AND( VLOOKUP(B63, 'รายชื่อพนักงานลาออกพ้นสภาพ'!B:I, 8, FALSE)<>"ยกเลิกลาออก", VLOOKUP(B63, 'รายชื่อพนักงานลาออกพ้นสภาพ'!B:I, 7, FALSE)<=TODAY() ), "ลาออกแล้ว", "" ), "") | O63: {=IFERROR(INDEX(PCRent!C:D, MATCH(F63 & " " & G63, PCRent!A:A & " " & PCRent!B:B, 0)), "")} -> SN:9H6MBZ3 | P63: ชุดคอมพิวเตอร์ Dell 7010SFF i5-13500 | Q63: {=IFERROR(INDEX(MonitorRent!C:D, MATCH(F63 & " " & G63, MonitorRent!A:A & " " & MonitorRent!B:B, 0)), "")} -> SN:98H7XY3 | R63: จอคอมพิวเตอร์ FHD DELL 24"
A64: 61 | B64: SX680004 | C64: บริษัท เซ็น เอกซ์ จำกัด (มหาชน) | D64: 25-12-2020 | E64: นางสาว | F64: พัชฬวีร์ | G64: ฐษาวงษ์สกุล | H64: เปิ้ล | I64: phatcharaveert@senxgroup.com | J64: สำนักงานใหญ่ | K64: เลขานุการผู้ช่วยประธานเจ้าหน้าที่บริหาร | L64: สำนักประธานเจ้าหน้าที่บริหาร (SENX) | M64: A | N64: =IFERROR( IF( AND( VLOOKUP(B64, 'รายชื่อพนักงานลาออกพ้นสภาพ'!B:I, 8, FALSE)<>"ยกเลิกลาออก", VLOOKUP(B64, 'รายชื่อพนักงานลาออกพ้นสภาพ'!B:I, 7, FALSE)<=TODAY() ), "ลาออกแล้ว", "" ), "") | O64: {=IFERROR(INDEX(PCRent!C:D, MATCH(F64 & " " & G64, PCRent!A:A & " " & PCRent!B:B, 0)), "")} | Q64: {=IFERROR(INDEX(MonitorRent!C:D, MATCH(F64 & " " & G64, MonitorRent!A:A & " " & MonitorRent!B:B, 0)), "")}
A65: 62 | B65: SX680020 | C65: บริษัท เซ็น เอกซ์ จำกัด (มหาชน) | D65: 03-11-2025 | E65: นางสาว | F65: พิณทิพย์ | G65: เกษี | H65: กระต่าย | I65: phinthipk@senxgroup.com | J65: สำนักงานใหญ่ | K65: เจ้าหน้าที่จัดซื้อ | L65: ฝ่ายทรัพย์สินสำนักงาน | M65: V | N65: =IFERROR( IF( AND( VLOOKUP(B65, 'รายชื่อพนักงานลาออกพ้นสภาพ'!B:I, 8, FALSE)<>"ยกเลิกลาออก", VLOOKUP(B65, 'รายชื่อพนักงานลาออกพ้นสภาพ'!B:I, 7, FALSE)<=TODAY() ), "ลาออกแล้ว", "" ), "") | O65: {=IFERROR(INDEX(PCRent!C:D, MATCH(F65 & " " & G65, PCRent!A:A & " " & PCRent!B:B, 0)), "")} | Q65: {=IFERROR(INDEX(MonitorRent!C:D, MATCH(F65 & " " & G65, MonitorRent!A:A & " " & MonitorRent!B:B, 0)), "")}
A66: 63 | B66: SX660016 | C66: บริษัท เซ็น เอกซ์ จำกัด (มหาชน) | D66: 16-06-2020 | E66: นางสาว | F66: พุทธชาติ | G66: ชมบุญมี | H66: มด | I66: puthachadc@senxgroup.com | J66: สำนักงานใหญ่ | K66: เจ้าหน้าที่การเงินอาวุโส | L66: ฝ่ายการเงิน | M66: A | N66: =IFERROR( IF( AND( VLOOKUP(B66, 'รายชื่อพนักงานลาออกพ้นสภาพ'!B:I, 8, FALSE)<>"ยกเลิกลาออก", VLOOKUP(B66, 'รายชื่อพนักงานลาออกพ้นสภาพ'!B:I, 7, FALSE)<=TODAY() ), "ลาออกแล้ว", "" ), "") | O66: {=IFERROR(INDEX(PCRent!C:D, MATCH(F66 & " " & G66, PCRent!A:A & " " & PCRent!B:B, 0)), "")} -> SN:HH6MBZ3 | P66: ชุดคอมพิวเตอร์ Dell 7010SFF i5-13500 | Q66: {=IFERROR(INDEX(MonitorRent!C:D, MATCH(F66 & " " & G66, MonitorRent!A:A & " " & MonitorRent!B:B, 0)), "")} -> SN:90P7XY3 | R66: จอคอมพิวเตอร์ FHD DELL 24"
A67: 64 | B67: SX660006 | C67: บริษัท เซ็น เอกซ์ จำกัด (มหาชน) | D67: 02-05-2017 | E67: นางสาว | F67: ภรดี | G67: รัตนรุจิกร | H67: เปี๊ยก | I67: porradeer@senxgroup.com | J67: สำนักงานใหญ่ | K67: ผู้ช่วยผู้อำนวยการ | L67: สายงานสนับสนุนธุรกิจองค์กร | M67: A | N67: =IFERROR( IF( AND( VLOOKUP(B67, 'รายชื่อพนักงานลาออกพ้นสภาพ'!B:I, 8, FALSE)<>"ยกเลิกลาออก", VLOOKUP(B67, 'รายชื่อพนักงานลาออกพ้นสภาพ'!B:I, 7, FALSE)<=TODAY() ), "ลาออกแล้ว", "" ), "") | O67: {=IFERROR(INDEX(PCRent!C:D, MATCH(F67 & " " & G67, PCRent!A:A & " " & PCRent!B:B, 0)), "")} | Q67: {=IFERROR(INDEX(MonitorRent!C:D, MATCH(F67 & " " & G67, MonitorRent!A:A & " " & MonitorRent!B:B, 0)), "")}
A68: 65 | B68: SX670105 | C68: บริษัท เซ็น เอกซ์ จำกัด (มหาชน) | D68: 01-02-2024 | E68: นาย | F68: ภัคธร | G68: มาศิริ | H68: ทัวร์ | I68: phakkhathornm@senxgroup.com | J68: โครงการ | K68: โฟร์แมนควบคุมงาน | L68: ฝ่ายบริหารโครงการคอนโด และบ้าน 12G | M68: A | N68: =IFERROR( IF( AND( VLOOKUP(B68, 'รายชื่อพนักงานลาออกพ้นสภาพ'!B:I, 8, FALSE)<>"ยกเลิกลาออก", VLOOKUP(B68, 'รายชื่อพนักงานลาออกพ้นสภาพ'!B:I, 7, FALSE)<=TODAY() ), "ลาออกแล้ว", "" ), "") | O68: {=IFERROR(INDEX(PCRent!C:D, MATCH(F68 & " " & G68, PCRent!A:A & " " & PCRent!B:B, 0)), "")} | Q68: {=IFERROR(INDEX(MonitorRent!C:D, MATCH(F68 & " " & G68, MonitorRent!A:A & " " & MonitorRent!B:B, 0)), "")}
A69: 66 | B69: SX680022 | C69: บริษัท เซ็น เอกซ์ จำกัด (มหาชน) | D69: 17-11-2025 | E69: นาย | F69: ภัทกร | G69: น้อยหลุบเลา | H69: เจมส์ | I69: pattakornn@senxgroup.com | J69: สำนักงานใหญ่ | K69: เจ้าหน้าที่สนับสนุนงานคอมพิวเตอร์ | L69: ฝ่ายเทคโนโลยีสารสนเทศ | M69: V | N69: =IFERROR( IF( AND( VLOOKUP(B69, 'รายชื่อพนักงานลาออกพ้นสภาพ'!B:I, 8, FALSE)<>"ยกเลิกลาออก", VLOOKUP(B69, 'รายชื่อพนักงานลาออกพ้นสภาพ'!B:I, 7, FALSE)<=TODAY() ), "ลาออกแล้ว", "" ), "") -> ลาออกแล้ว | O69: {=IFERROR(INDEX(PCRent!C:D, MATCH(F69 & " " & G69, PCRent!A:A & " " & PCRent!B:B, 0)), "")} | Q69: {=IFERROR(INDEX(MonitorRent!C:D, MATCH(F69 & " " & G69, MonitorRent!A:A & " " & MonitorRent!B:B, 0)), "")}
A70: 67 | B70: SX670057 | C70: บริษัท เซ็น เอกซ์ จำกัด (มหาชน) | D70: 03-05-2022 | E70: นาย | F70: ภัทรพงศ์ | G70: เกษแก้ว | H70: ติ๊ก | I70: phattharaphongk@senxgroup.com | J70: โครงการ | K70: โฟร์แมนควบคุมงาน | L70: ฝ่ายบริหารโครงการคอนโด และบ้าน 12B | M70: A | N70: =IFERROR( IF( AND( VLOOKUP(B70, 'รายชื่อพนักงานลาออกพ้นสภาพ'!B:I, 8, FALSE)<>"ยกเลิกลาออก", VLOOKUP(B70, 'รายชื่อพนักงานลาออกพ้นสภาพ'!B:I, 7, FALSE)<=TODAY() ), "ลาออกแล้ว", "" ), "") | O70: {=IFERROR(INDEX(PCRent!C:D, MATCH(F70 & " " & G70, PCRent!A:A & " " & PCRent!B:B, 0)), "")} | Q70: {=IFERROR(INDEX(MonitorRent!C:D, MATCH(F70 & " " & G70, MonitorRent!A:A & " " & MonitorRent!B:B, 0)), "")}
A71: 68 | B71: SX670031 | C71: บริษัท เซ็น เอกซ์ จำกัด (มหาชน) | D71: 18-07-2022 | E71: นาย | F71: ภุชงค์ | G71: คันธรักษ์ | H71: มิ้งค์ | I71: puchongk@senxgroup.com | J71: โครงการ | K71: ผู้จัดการโครงการอาวุโส | L71: ฝ่ายบริหารโครงการบ้าน 11C | M71: A | N71: =IFERROR( IF( AND( VLOOKUP(B71, 'รายชื่อพนักงานลาออกพ้นสภาพ'!B:I, 8, FALSE)<>"ยกเลิกลาออก", VLOOKUP(B71, 'รายชื่อพนักงานลาออกพ้นสภาพ'!B:I, 7, FALSE)<=TODAY() ), "ลาออกแล้ว", "" ), "") | O71: {=IFERROR(INDEX(PCRent!C:D, MATCH(F71 & " " & G71, PCRent!A:A & " " & PCRent!B:B, 0)), "")} | Q71: {=IFERROR(INDEX(MonitorRent!C:D, MATCH(F71 & " " & G71, MonitorRent!A:A & " " & MonitorRent!B:B, 0)), "")}
